Workbook

Sheet Q4 Summary
A1: TOP GLOBAL FOOD AND BEVERAGES SDN BHD
A2: Forecast bank position at 31 December 2026 — Maybank & RHB
A3: From the 30 Sep forecast balances. Weekly detail in 'Q4 Weekly Cash Flow' (cash flow template layout); inputs in 'Q4 Assumptions'.
A5: RM | B5: Maybank | C5: RHB | D5: Maybank + RHB
A6: Bank balance at 1 Oct 2026 | B6: ='Q4 Assumptions'!$B$7 | C6: ='Q4 Assumptions'!$B$8 | D6: ='Q4 Weekly Cash Flow'!R76
A7: Net Cash Flow from Operations | B7: =D7-C7 | C7: ='Q4 Weekly Cash Flow'!R94+'Q4 Weekly Cash Flow'!R95 | D7: ='Q4 Weekly Cash Flow'!R41
A8: Net Cash Flow from Investing Activities | B8: =D8-C8 | C8: 0 | D8: ='Q4 Weekly Cash Flow'!R56
A9: Net Cash Flow from Financing Activities | B9: =D9-C9 | C9: 0 | D9: ='Q4 Weekly Cash Flow'!R72
A10: Transfers Maybank → RHB (payroll top-ups) | B10: =-'Q4 Weekly Cash Flow'!R97 | C10: ='Q4 Weekly Cash Flow'!R97 | D10: =B10+C10
A11: Net Cash Flow 1 Oct – 31 Dec | B11: =SUM(B7:B10) | C11: =SUM(C7:C10) | D11: =SUM(D7:D10)
A12: Forecast bank balance at 31 Dec 2026 | B12: =B6+B11 | C12: =C6+C11 | D12: =D6+D11
A13: Check vs weekly sheet (should be 0) | B13: =ROUND(B12-'Q4 Weekly Cash Flow'!R99,2) | C13: =ROUND(C12-'Q4 Weekly Cash Flow'!R98,2) | D13: =ROUND(D12-'Q4 Weekly Cash Flow'!R77,2)
A15: Key indicators
A16: Lowest weekly closing balance (Maybank + RHB) | D16: =MIN('Q4 Weekly Cash Flow'!$D$77:$Q$77)
A17: Week ending of lowest balance | D17: =INDEX('Q4 Weekly Cash Flow'!$D$11:$Q$11,MATCH(D16,'Q4 Weekly Cash Flow'!$D$77:$Q$77,0))
A18: Lowest weekly Maybank balance | B18: =MIN('Q4 Weekly Cash Flow'!$D$99:$Q$99)
A19: Outlets operating at 31 Dec (34 + new openings) | D19: ='Q4 Outlet Schedule'!C21
A20: New-outlet sales Oct–Dec | D20: ='Q4 Outlet Schedule'!W18
A21: Capex on new outlets Oct–Dec | D21: =-'Q4 Weekly Cash Flow'!R89
A23: Assumptions to confirm (yellow in 'Q4 Assumptions')
A24: 1. Existing 34 outlets: each template line runs at its September actual (1–28 Sep, Maybank) — daily lines ÷ 28 days, monthly lines once a month. One-offs (Sep licensing fee, deposits, capex, RM2M FD placement) are not repeated.
A25: 2. Wages: RM1M in the first week of each month (Maybank, 3rd) + RM475k in the week of the 25th (RHB; you said RM450k–500k), each +2% per new outlet open. Foreign workers RM920k mid-Oct and RM200k mid-Dec; bonus RM300k end-Dec.
A26: 3. Advance to related parties (RM192.7k in Sep) assumed to repeat monthly (prudent). Switch its Basis to 'Excluded' if it was one-off.
A27: 4. New outlets: RM8k/day sales; each new outlet open adds +3% to inventory purchases and +1% to branch upkeep (on the Sep daily level); rental 5% of new-outlet sales. Bebeks RM400k mid-Oct, Kopitiam RM350k on 31 Dec.
A28: 5. Deposits for 5 new outlets RM30k each (amount not given). SST Sep–Oct ≈ Jul–Aug amount, due 30 Nov.
A29: 6. Capex balance paid 45 days before grand opening (Cheras & PJ balances on 1 Oct). Pasir Gudang fully paid. ICOMSRWK excluded (GO TBD). FD excluded (matures 2027).

Sheet Sep30 Bridge
A1: TGFB — Forecast Cash Position as at 30 September 2026
A2: Bridge from actual 28 Sep balances to 30 Sep. Maybank inflow uses same-weekday September median; RHB uses average daily cash deposits.
A4: Date | B4: Bank | C4: Opening Balance | D4: Forecast Cash In | E4: Forecast Cash Out | F4: Net Cash Flow | G4: Closing Balance | H4: Basis
A5: 46293 | B5: Maybank | C5: 13269623 | D5: 0 | E5: 0 | F5: 0 | G5: 13269623 | H5: Actual closing balance 28 Sep
A6: 46294 | B6: Maybank | C6: =G5 | D6: 317348.35 | E6: 393281.82 | F6: =D6-E6 | G6: =C6+F6 | H6: Tue median inflow; remaining payment schedule incl. 28 Sep Maker carry-forward
A7: 46295 | B7: Maybank | C7: =G6 | D7: 305975.2 | E7: 1165510.3 | F7: =D7-E7 | G7: =C7+F7 | H7: Wed median inflow + RM8k Pasir Gudang opening-day sales; TGFB payment schedule
A8: 46295 | B8: Maybank Total Sep | C8: 14257278 | D8: =9377264.19+D6+D7 | E8: =10364919.54+E6+E7 | F8: =D8-E8 | G8: =C8+F8 | H8: Monthly Sep forecast after 29-30 Sep bridge
A10: 46293 | B10: RHB | C10: 14440.97 | D10: 0 | E10: 0 | F10: 0 | G10: 14440.97 | H10: Actual closing balance from RHB transaction CSV
A11: 46294 | B11: RHB | C11: =G10 | D11: 1775.7143 | E11: 0 | F11: =D11-E11 | G11: =C11+F11 | H11: Forecast using average daily cash deposits; no known scheduled RHB outflow
A12: 46295 | B12: RHB | C12: =G11 | D12: 1775.7143 | E12: 0 | F12: =D12-E12 | G12: =C12+F12 | H12: Forecast using average daily cash deposits; no known scheduled RHB outflow
A13: 46295 | B13: RHB Total Sep | C13: 35880.04 | D13: 425699.58 | E13: 443587.22 | F13: =D13-E13 | G13: =C13+F13 | H13: Monthly Sep forecast
A15: CONSOLIDATED TGFB BANK POSITION
A16: Opening balance 1 Sep 2026 | B16: 14293158
A17: Forecast closing Maybank 30 Sep | B17: =G7
A18: Forecast closing RHB 30 Sep | B18: =G12
A19: Forecast combined cash at 30 Sep | B19: =B17+B18
A21: Forecast combined Sep Net Cash Flow | B21: =B19-B16
A22: Maybank forecast 29-30 cash inflow | B22: =D6+D7
A23: Maybank forecast 29-30 cash outflow | B23: =E6+E7
A24: RHB forecast 29-30 cash inflow | B24: =D11+D12
A25: Incremental Pasir Gudang sales on 30 Sep | B25: 8000

Sheet Remaining Payments
A1: Original Date | B1: Forecast Pay Date | C1: Supplier | D1: Description | E1: Amount (RM) | F1: Payment Type | G1: Outlet | H1: Status / Note
A2: 46293 | B2: 46294 | C2: KONG FU PLUMBERS | D2: Repair water tank - Seremban | E2: 400 | F2: Interbank | G2: SEREMBAN | H2: Maker Carry to 29 Sep forecast
A3: 46293 | B3: 46294 | C3: TENAGA NASIONAL BERHAD | D3: TNB Sep - Segamat 40 outlet | E3: 4607.95 | F3: JomPAY | G3: SEGAMAT | H3: Maker Carry to 29 Sep forecast
A4: 46293 | B4: 46294 | C4: EL GREAT SOLUTION | D4: Upkeep of branch - KLTS | E4: 35 | F4: MBB | G4: KLTS | H4: Maker Carry to 29 Sep forecast
A5: 46294 | B5: 46294 | C5: TGCK | D5: Inventory TGCK 07.09.2026 to 08.09.2026 | E5: 214982.6 | F5: M2E | G5: TGCK | H5: Maker
A6: 46294 | B6: 46294 | C6: AHRA INTERIOR | D6: Outlet renovation - Petaling Jaya (1st payment) | E6: 122330.7 | F6: M2E | G6: PETALING JAYA | H6: Maker
A7: 46294 | B7: 46294 | C7: TK STEEL SUPPLIES | D7: Foodtruck - 6th payment | E7: 20219 | F7: M2E | G7: HQ | H7: Maker
A8: 46294 | B8: 46294 | C8: TENAGA NASIONAL BERHAD | D8: TNB Sep - Sg Besi outlet | E8: 5685 | F8: JomPAY | G8: SG BESI | H8: Maker
A9: 46294 | B9: 46294 | C9: TOP GLOBAL FOOD AND BEVERAGES | D9: Hire purchase RU9577 - Jul 2026 | E9: 4433 | F9: Interbank | G9: HQ | H9: Maker
A10: 46294 | B10: 46294 | C10: IRHAS PUTRA | D10: Rental Oct - S13 G15 training centre | E10: 3900 | F10: MBB | G10: HQ | H10: Maker
A11: 46294 | B11: 46294 | C11: HUSNA | D11: Cash advance - F1 Event | E11: 3845.77 | F11: MBB | G11: HQ | H11: Maker
A12: 46294 | B12: 46294 | C12: TENAGA NASIONAL BERHAD | D12: TNB Sep - BSP 29G outlet | E12: 3540.1 | F12: JomPAY | G12: BSP | H12: Maker
A13: 46294 | B13: 46294 | C13: TENAGA NASIONAL BERHAD | D13: TNB Sep - Cheras 85G outlet | E13: 2754.6 | F13: JomPAY | G13: CHERAS | H13: Maker
... A29: 46294 | B29: 46294 | C29: SYABAS | D29: Syabas Sep - Cheras hostel 3 | E29: 32.45 | F29: JomPAY | G29: CHERAS | H29: Maker
A30: 46295 | B30: 46295 | C30: JABATAN KASTAM DIRAJA MALAYSIA | D30: SST TGFB - Jul & Aug 2026 | E30: 1152543.6 | F30: M2E | G30: TGFB
A31: 46295 | B31: 46295 | C31: TOP GLOBAL FOOD AND BEVERAGES | D31: Hire purchase VHQ537 - Jul 2026 | E31: 5444 | F31: Interbank | G31: HQ | H31: Maker
A32: 46295 | B32: 46295 | C32: NUR HANA NASIHAH | D32: Food training for staff | E32: 5000 | F32: Interbank | G32: HQ
A33: 46295 | B33: 46295 | C33: AINA NOORA | D33: Cash advance - Aina | E33: 2522.66 | F33: Interbank | G33: HQ

Sheet RHB Sep Transactions
A1: Date | B1: Description | C1: Sender / Beneficiary | D1: Reference 1 | E1: Reference 2 | F1: Debit (RM) | G1: Credit (RM) | H1: Balance (RM)
A2: 46266 | B2: CDT CASH DEPOSIT | C2: / | D2: / | E2: / | F2: 0 | G2: 100 | H2: 35980.04
A3: 46266 | B3: CDT CASH DEPOSIT | C3: / | D3: / | E3: / | F3: 0 | G3: 1500 | H3: 37480.04
A4: 46266 | B4: RPP INWARD INST TRF | C4: AMPERA RAYA GLOBAL S / | D4: /KLTS Ampera | E4: /KLTS Gr Sewa Sep26 | F4: 0 | G4: 8600 | H4: 46080.04
A5: 46266 | B5: REFLEX SERVICE TAX D | C5: / | D5: / | E5: M01/ | F5: 4 | G5: 0 | H5: 46076.04
A6: 46266 | B6: REFLEX-SUBSCRIP CHAR | C6: / | D6: / | E6: M01/ | F6: 50 | G6: 0 | H6: 46026.04
A7: 46267 | B7: CDT CASH DEPOSIT | C7: / | D7: / | E7: / | F7: 0 | G7: 1580 | H7: 47606.04
A8: 46268 | B8: CDT CASH DEPOSIT | C8: / | D8: / | E8: / | F8: 0 | G8: 1920 | H8: 49526.04
A9: 46269 | B9: CDT CASH DEPOSIT | C9: / | D9: / | E9: / | F9: 0 | G9: 50 | H9: 49576.04
A10: 46269 | B10: CDT CASH DEPOSIT | C10: / | D10: / | E10: / | F10: 0 | G10: 350 | H10: 49926.04
A11: 46270 | B11: CDT CASH DEPOSIT | C11: / | D11: / | E11: / | F11: 0 | G11: 1180 | H11: 51106.04
A12: 46270 | B12: CDT CASH DEPOSIT | C12: / | D12: / | E12: / | F12: 0 | G12: 1970 | H12: 53076.04
A13: 46271 | B13: CDT CASH DEPOSIT | C13: / | D13: / | E13: / | F13: 0 | G13: 1420 | H13: 54496.04
... A49: 46293 | B49: RFLX INSTANT TRF DR | C49: / AHMAD HANIF ALBAB | D49: 260928013896/salary sept | E49: / | F49: 3600 | G49: 0 | H49: 14440.97
A51: FORECAST 29-30 SEP
A52: 46294 | B52: Forecast cash deposits | F52: 0 | G52: 1775.7143 | H52: =H49+G52-F52
A53: 46295 | B53: Forecast cash deposits | F53: 0 | G53: 1775.7143 | H53: =H52+G53-F53

Sheet Outlet Plan
A1: No. | B1: Project | C1: Grand Opening | D1: Capex Assumption (RM) | E1: Project Cash-Out Date | F1: Daily New Outlet Sales (RM) | G1: Incremental Sales Sep-26 | H1: Incremental Sales Oct-Dec 2026 | I1: Notes
A2: 10 | B2: PASIR GUDANG | C2: 46295 | D2: 650000 | E2: 46265 | F2: 8000 | G2: 8000 | H2: 736000 | I2: First 3 projects: RM650k capex/outlet; project cash-out date falls before Q4
A3: 11 | B3: CHERAS DWITASIK | C3: 46307 | D3: 650000 | E3: 46277 | F3: 8000 | G3: 0 | H3: 648000 | I3: First 3 projects: RM650k capex/outlet; project cash-out date falls before Q4
A4: 12 | B4: PETALING JAYA | C4: 46322 | D4: 650000 | E4: 46292 | F4: 8000 | G4: 0 | H4: 528000 | I4: First 3 projects: RM650k capex/outlet; project cash-out date falls before Q4
A5: 13 | B5: TAIPAN USJ | C5: 46342 | D5: 450000 | E5: 46312 | F5: 8000 | G5: 0 | H5: 368000 | I5: Subsequent projects: RM450k capex/outlet
A6: 14 | B6: BANGSAR | C6: 46344 | D6: 450000 | E6: 46314 | F6: 8000 | G6: 0 | H6: 352000 | I6: Subsequent projects: RM450k capex/outlet
A7: 15 | B7: MACHANG | C7: 46344 | D7: 450000 | E7: 46314 | F7: 8000 | G7: 0 | H7: 352000 | I7: Subsequent projects: RM450k capex/outlet
A8: 16 | B8: ARAU | C8: 46349 | D8: 450000 | E8: 46319 | F8: 8000 | G8: 0 | H8: 312000 | I8: Subsequent projects: RM450k capex/outlet
A9: 17 | B9: PASIR MAS | C9: 46356 | D9: 450000 | E9: 46326 | F9: 8000 | G9: 0 | H9: 256000 | I9: Subsequent projects: RM450k capex/outlet
A10: 18 | B10: KEMAMAN | C10: 46363 | D10: 450000 | E10: 46333 | F10: 8000 | G10: 0 | H10: 200000 | I10: Subsequent projects: RM450k capex/outlet
A11: 19 | B11: CHANGLUN | C11: 46365 | D11: 450000 | E11: 46335 | F11: 8000 | G11: 0 | H11: 184000 | I11: Subsequent projects: RM450k capex/outlet
A12: 20 | B12: MUAR | C12: 46371 | D12: 450000 | E12: 46341 | F12: 8000 | G12: 0 | H12: 136000 | I12: Subsequent projects: RM450k capex/outlet
A13: 21 | B13: ICOMSRWK | C13: TBD | D13: 450000 | E13: TBD | F13: 8000 | G13: 0 | H13: 0 | I13: GO date TBD; excluded until date confirmed
A16: Planning summary
A17: Current outlet count stated as at 30 Sep 2026 | B17: 34
A18: New outlet daily sales assumption | B18: 8000 | C18: RM / day
A19: Sep incremental sales from listed openings | B19: =SUM(G2:G13)
A20: Oct-Dec incremental sales from listed openings | B20: =SUM(H2:H13)

Sheet Q4 Assumptions
A1: TGFB — Q4 2026 Cash Flow Forecast: Assumptions
A2: Blue = input (from you / estimate) · Green = link to another sheet · Black = formula · Yellow = estimate to confirm. Outflows are negative, as in the cash flow template.
A4: GENERAL
A5: Forecast start | B5: 46296 | I5: Day after the Sep-30 bridge
A6: Forecast end | B6: 46387 | I6: Your item 1: up to 31 Dec
A7: Opening Maybank balance (forecast 30 Sep) | B7: ='Sep30 Bridge'!G7 | I7: Sep30 Bridge closing
A8: Opening RHB balance (forecast 30 Sep) | B8: ='Sep30 Bridge'!G12 | I8: Sep30 Bridge closing
A9: Outlets operating at 30 Sep (incl. Pasir Gudang) | B9: 34 | I9: Your item 4
A10: Fixed deposit | B10: Excluded | I10: Your item 11: FD matures 2027 (1-yr tenure) — no FD cash movement in Q4
A12: NEW OUTLETS
A13: Sales per new outlet per day (RM) | B13: 8000 | I13: Your item 2
A14: Rental % of new-outlet sales | B14: 0.05 | I14: Rental part of your original 15% running cost (wages now follow the 2%-per-outlet rule below)
A15: Wage increase per new outlet open | B15: 0.02 | I15: Your instruction: +2% on the payroll (1st-week + 25th) for each new outlet open
A16: Branch Expenditure & Upkeep increase per new outlet open | B16: 0.01 | I16: Your instruction: +1% per new outlet
A17: Inventory purchases increase per new outlet open | B17: 0.03 | I17: Your instruction: +3% per new outlet
A18: Capex paid N days before grand opening | B18: 45 | I18: Your item 6. Lump sum on GO−45; if already past, balance paid 1 Oct
A19: Capex — first 3 outlets (RM/outlet) | B19: 650000 | I19: Your item 5
A20: Capex — subsequent outlets (RM/outlet) | B20: 450000 | I20: Your item 6
A21: Capex paid to 30 Sep — Pasir Gudang | B21: 650000 | I21: ASSUMPTION: Pasir Gudang (opened 30 Sep) fully paid — no further capex in Q4
A22: Capex paid to 30 Sep — Cheras Dwitasik | B22: 91500 | I22: Your item 9
A23: Capex paid to 30 Sep — Petaling Jaya | B23: 122330.7 | I23: Your item 9 (AHRA Interior, 29 Sep)
A24: Deposit per new outlet — 5 outlets Oct–Nov (RM) | B24: 30000 | I24: ASSUMPTION: amount not given (your item 14) — placeholder
A26: WAGES & RHB
A27: RHB cash deposits per day | B27: ='Sep30 Bridge'!D11 | I27: Sep30 Bridge (average daily cash deposit)
A28: Payroll on the 25th (RHB) — base | B28: 475000 | I28: Your instruction: RM450k–500k in the week of the 25th — midpoint RM475k used (Sep RHB payroll was RM439,928)
A29: Minimum RHB balance before Maybank top-up | B29: 20000 | I29: Maybank tops RHB up only when needed for payroll (as on 25 Sep)
A30: Wages — first week of each month (Maybank) — base | B30: 1000000 | I30: Your instruction: RM1M in the first week of the month (paid on the 3rd)
A31: EXISTING 34 OUTLETS — BASELINE FROM SEPTEMBER CASH FLOW STATEMENT (MAYBANK, 1–28 SEP)
A32: Days covered by September actual | B32: 28 | I32: TGFB Cash Flow Sept 2026: 1 Sep opening 14,257,277.95 → 13,269,622.60 (28 Sep actual)
A33: Sep opening balance (Maybank, 1 Sep) | B33: 14257278 | I33: Cash flow statement
A34: Basis: Daily = Sep actual ÷ 28 days, spread every day · Monthly = paid once a month on 'Pay day' · Excluded = one-off, not repeated (Q4 amounts come from the events table below)
A35: Template line | B35: Section | C35: Sep'26 actual | D35: Adjustment | E35: Basis | F35: Pay day | G35: Per day (Q4) | H35: Per month (Q4) | I35: Why
A36: Customers & Sales | B36: Operations — in | C36: 8833557.3 | D36: 0 | E36: Daily | G36: =IF(E36="Daily",(C36+D36)/'Q4 Assumptions'!$B$32,0) | H36: =IF(E36="Monthly",C36+D36,0) | I36: Existing outlets at Sep daily rate. New-outlet sales and RHB cash deposits added on the weekly sheet
A37: Licensing fee | B37: Operations — in | C37: 120000 | D37: 0 | E37: Excluded | G37: =IF(E37="Daily",(C37+D37)/'Q4 Assumptions'!$B$32,0) | H37: =IF(E37="Monthly",C37+D37,0) | I37: One-off licensee fee in Sep — not assumed to recur
A38: Licensing package | B38: Operations — in | C38: 0 | D38: 0 | E38: Excluded | G38: =IF(E38="Daily",(C38+D38)/'Q4 Assumptions'!$B$32,0) | H38: =IF(E38="Monthly",C38+D38,0) | I38: Q4: PJ balance RM255k (events)
A39: Royalty | B39: Operations — in | C39: 296844.55 | D39: 0 | E39: Monthly | F39: 10 | G39: =IF(E39="Daily",(C39+D39)/'Q4 Assumptions'!$B$32,0) | H39: =IF(E39="Monthly",C39+D39,0) | I39: Monthly royalty from licensees
A40: Other operations | B40: Operations — in | C40: 37586.57 | D40: 0 | E40: Daily | G40: =IF(E40="Daily",(C40+D40)/'Q4 Assumptions'!$B$32,0) | H40: =IF(E40="Monthly",C40+D40,0)
A41: Inventory purchases | B41: Operations — out | C41: -4009021.4 | D41: 0 | E41: Daily | G41: =IF(E41="Daily",(C41+D41)/'Q4 Assumptions'!$B$32,0) | H41: =IF(E41="Monthly",C41+D41,0) | I41: Existing outlets at Sep daily rate
A42: Distribution Fee | B42: Operations — out | C42: -187370 | D42: 0 | E42: Daily | G42: =IF(E42="Daily",(C42+D42)/'Q4 Assumptions'!$B$32,0) | H42: =IF(E42="Monthly",C42+D42,0)
A43: Deposit | B43: Operations — out | C43: -227765 | D43: 0 | E43: Excluded | G43: =IF(E43="Daily",(C43+D43)/'Q4 Assumptions'!$B$32,0) | H43: =IF(E43="Monthly",C43+D43,0) | I43: Sep deposits one-off. Q4: 5 new-outlet deposits (events)
A44: HQ Operation | B44: Operations — out | C44: -273878.42 | D44: 0 | E44: Daily | G44: =IF(E44="Daily",(C44+D44)/'Q4 Assumptions'!$B$32,0) | H44: =IF(E44="Monthly",C44+D44,0)
A45: Operation | B45: Operations — out | C45: 0 | D45: 0 | E45: Excluded | G45: =IF(E45="Daily",(C45+D45)/'Q4 Assumptions'!$B$32,0) | H45: =IF(E45="Monthly",C45+D45,0)
A46: Marketing | B46: Operations — out | C46: -6945.85 | D46: 0 | E46: Daily | G46: =IF(E46="Daily",(C46+D46)/'Q4 Assumptions'!$B$32,0) | H46: =IF(E46="Monthly",C46+D46,0)
A47: Profit sharing | B47: Operations — out | C47: -67013.9 | D47: 0 | E47: Monthly | F47: 15 | G47: =IF(E47="Daily",(C47+D47)/'Q4 Assumptions'!$B$32,0) | H47: =IF(E47="Monthly",C47+D47,0)
A48: Wage expenses | B48: Operations — out | C48: -1493708.5 | D48: 0 | E48: Excluded | G48: =IF(E48="Daily",(C48+D48)/'Q4 Assumptions'!$B$32,0) | H48: =IF(E48="Monthly",C48+D48,0) | I48: Q4 wages per your schedule (events): RM1M first week (Maybank) + RM475k on the 25th (RHB), +2% per new outlet; plus foreign workers & bonus
A49: Bank Charges | B49: Operations — out | C49: -239.04 | D49: 0 | E49: Daily | G49: =IF(E49="Daily",(C49+D49)/'Q4 Assumptions'!$B$32,0) | H49: =IF(E49="Monthly",C49+D49,0)
A50: Income taxes | B50: Operations — out | C50: -250000 | D50: 0 | E50: Monthly | F50: 15 | G50: =IF(E50="Daily",(C50+D50)/'Q4 Assumptions'!$B$32,0) | H50: =IF(E50="Monthly",C50+D50,0) | I50: Monthly tax instalment (CP204), due 15th
A51: New Branches Expenses | B51: Operations — out | C51: -13664 | D51: 0 | E51: Daily | G51: =IF(E51="Daily",(C51+D51)/'Q4 Assumptions'!$B$32,0) | H51: =IF(E51="Monthly",C51+D51,0)
A52: Branch Expenditure & Upkeep | B52: Operations — out | C52: -153655.6 | D52: 0 | E52: Daily | G52: =IF(E52="Daily",(C52+D52)/'Q4 Assumptions'!$B$32,0) | H52: =IF(E52="Monthly",C52+D52,0)
A53: Credit Card | B53: Operations — out | C53: -102185.69 | D53: 0 | E53: Monthly | F53: 20 | G53: =IF(E53="Daily",(C53+D53)/'Q4 Assumptions'!$B$32,0) | H53: =IF(E53="Monthly",C53+D53,0)
A54: Open House & Iftar | B54: Operations — out | C54: 0 | D54: 0 | E54: Excluded | G54: =IF(E54="Daily",(C54+D54)/'Q4 Assumptions'!$B$32,0) | H54: =IF(E54="Monthly",C54+D54,0)
A55: Co Trip | B55: Operations — out | C55: 0 | D55: 0 | E55: Excluded | G55: =IF(E55="Daily",(C55+D55)/'Q4 Assumptions'!$B$32,0) | H55: =IF(E55="Monthly",C55+D55,0)
A56: Utilities | B56: Operations — out | C56: -169005.7 | D56: 0 | E56: Daily | G56: =IF(E56="Daily",(C56+D56)/'Q4 Assumptions'!$B$32,0) | H56: =IF(E56="Monthly",C56+D56,0)
A57: Rental | B57: Operations — out | C57: -468891.05 | D57: 0 | E57: Monthly | F57: 7 | G57: =IF(E57="Daily",(C57+D57)/'Q4 Assumptions'!$B$32,0) | H57: =IF(E57="Monthly",C57+D57,0) | I57: Existing outlets; new-outlet rental added on the weekly sheet
A58: Sponsorship | B58: Operations — out | C58: 0 | D58: 0 | E58: Excluded | G58: =IF(E58="Daily",(C58+D58)/'Q4 Assumptions'!$B$32,0) | H58: =IF(E58="Monthly",C58+D58,0)
A59: SST | B59: Operations — out | C59: 0 | D59: 0 | E59: Excluded | G59: =IF(E59="Daily",(C59+D59)/'Q4 Assumptions'!$B$32,0) | H59: =IF(E59="Monthly",C59+D59,0) | I59: Q4: Sep–Oct SST due 30 Nov (events)
A60: Donation | B60: Operations — out | C60: 0 | D60: 0 | E60: Excluded | G60: =IF(E60="Daily",(C60+D60)/'Q4 Assumptions'!$B$32,0) | H60: =IF(E60="Monthly",C60+D60,0)
A61: Proceeds from sale of equipment | B61: Investing — in | C61: 0 | D61: 0 | E61: Excluded | G61: =IF(E61="Daily",(C61+D61)/'Q4 Assumptions'!$B$32,0) | H61: =IF(E61="Monthly",C61+D61,0)
A62: Proceeds from sale of motor vehicle | B62: Investing — in | C62: 0 | D62: 0 | E62: Excluded | G62: =IF(E62="Daily",(C62+D62)/'Q4 Assumptions'!$B$32,0) | H62: =IF(E62="Monthly",C62+D62,0)
A63: Collection of Investor funds | B63: Investing — in | C63: 0 | D63: 0 | E63: Excluded | G63: =IF(E63="Daily",(C63+D63)/'Q4 Assumptions'!$B$32,0) | H63: =IF(E63="Monthly",C63+D63,0) | I63: Q4: RM450k + RM200k (events)
A64: Interest received from Maybank pooled | B64: Investing — in | C64: 8970.22 | D64: 0 | E64: Monthly | F64: 28 | G64: =IF(E64="Daily",(C64+D64)/'Q4 Assumptions'!$B$32,0) | H64: =IF(E64="Monthly",C64+D64,0)
A65: Sale of investment securities | B65: Investing — in | C65: 0 | D65: 0 | E65: Excluded | G65: =IF(E65="Daily",(C65+D65)/'Q4 Assumptions'!$B$32,0) | H65: =IF(E65="Monthly",C65+D65,0)
A66: Purchase of property and equipment | B66: Investing — out | C66: -14400 | D66: 0 | E66: Daily | G66: =IF(E66="Daily",(C66+D66)/'Q4 Assumptions'!$B$32,0) | H66: =IF(E66="Monthly",C66+D66,0)
A67: Capex New Branches | B67: Investing — out | C67: -517519.25 | D67: 0 | E67: Excluded | G67: =IF(E67="Daily",(C67+D67)/'Q4 Assumptions'!$B$32,0) | H67: =IF(E67="Monthly",C67+D67,0) | I67: Sep capex (Pasir Gudang/Cheras) one-off. Q4 capex from 'Q4 Outlet Schedule'
A68: Placement of Fixed Deposit | B68: Investing — out | C68: -2000000 | D68: 0 | E68: Excluded | G68: =IF(E68="Daily",(C68+D68)/'Q4 Assumptions'!$B$32,0) | H68: =IF(E68="Monthly",C68+D68,0) | I68: One-off RM2M FD placement in Sep; FD matures 2027
A69: Purchase of investment | B69: Investing — out | C69: 0 | D69: 0 | E69: Excluded | G69: =IF(E69="Daily",(C69+D69)/'Q4 Assumptions'!$B$32,0) | H69: =IF(E69="Monthly",C69+D69,0) | I69: Q4: Bebeks RM400k, Kopitiam RM350k (events)
A70: Issuance of stock | B70: Financing — in | C70: 0 | D70: 0 | E70: Excluded | G70: =IF(E70="Daily",(C70+D70)/'Q4 Assumptions'!$B$32,0) | H70: =IF(E70="Monthly",C70+D70,0)
A71: Loan received | B71: Financing — in | C71: 0 | D71: 0 | E71: Excluded | G71: =IF(E71="Daily",(C71+D71)/'Q4 Assumptions'!$B$32,0) | H71: =IF(E71="Monthly",C71+D71,0)
A72: Borrowing | B72: Financing — in | C72: 0 | D72: 0 | E72: Excluded | G72: =IF(E72="Daily",(C72+D72)/'Q4 Assumptions'!$B$32,0) | H72: =IF(E72="Monthly",C72+D72,0)
A73: Repayment from related parties | B73: Financing — in | C73: 0 | D73: 0 | E73: Excluded | G73: =IF(E73="Daily",(C73+D73)/'Q4 Assumptions'!$B$32,0) | H73: =IF(E73="Monthly",C73+D73,0)
A74: Repurchase of stock (treasury stock) | B74: Financing — out | C74: 0 | D74: 0 | E74: Excluded | G74: =IF(E74="Daily",(C74+D74)/'Q4 Assumptions'!$B$32,0) | H74: =IF(E74="Monthly",C74+D74,0)
A75: Purchase of investment (financing) | B75: Financing — out | C75: 0 | D75: 0 | E75: Excluded | G75: =IF(E75="Daily",(C75+D75)/'Q4 Assumptions'!$B$32,0) | H75: =IF(E75="Monthly",C75+D75,0)
A76: Repayment of loans | B76: Financing — out | C76: -138136.29 | D76: 0 | E76: Monthly | F76: 5 | G76: =IF(E76="Daily",(C76+D76)/'Q4 Assumptions'!$B$32,0) | H76: =IF(E76="Monthly",C76+D76,0) | I76: Monthly loan / hire-purchase instalments
A77: Dividends | B77: Financing — out | C77: 0 | D77: 0 | E77: Excluded | G77: =IF(E77="Daily",(C77+D77)/'Q4 Assumptions'!$B$32,0) | H77: =IF(E77="Monthly",C77+D77,0)
A78: Advance to related parties | B78: Financing — out | C78: -192684.6 | D78: 0 | E78: Monthly | F78: 15 | G78: =IF(E78="Daily",(C78+D78)/'Q4 Assumptions'!$B$32,0) | H78: =IF(E78="Monthly",C78+D78,0) | I78: ASSUMPTION (prudent): Sep level repeats monthly. Set Basis to Excluded if it was one-off
A79: Repayment to related parties | B79: Financing — out | C79: 0 | D79: 0 | E79: Excluded | G79: =IF(E79="Daily",(C79+D79)/'Q4 Assumptions'!$B$32,0) | H79: =IF(E79="Monthly",C79+D79,0)
A80: Pending | B80: Financing — out | C80: 1470.3 | D80: 0 | E80: Excluded | G80: =IF(E80="Daily",(C80+D80)/'Q4 Assumptions'!$B$32,0) | H80: =IF(E80="Monthly",C80+D80,0) | I80: Sep reconciling item
A81: Check: Sep net cash flow (should be −987,655.35) | C81: =SUM(C36:C80) | D81: =C81-('Sep30 Bridge'!D8-'Sep30 Bridge'!D6-'Sep30 Bridge'!D7-('Sep30 Bridge'!E8-'Sep30 Bridge'!E6-'Sep30 Bridge'!E7)) | I81: Column D = difference vs Sep30 Bridge 1–28 Sep net (should be 0)
A83: DATED CASH EVENTS — one-offs you gave me + recurring monthly items (edit dates / amounts here; outflows negative)
A84: Description | B84: Date | C84: Amount (RM) | D84: Template line | E84: Bank | F84: +2%/outlet | G84: Source / note
A85: Licensing package — Petaling Jaya balance (invoice 655k − 400k received) | B85: 46310 | C85: =655000-400000 | D85: Licensing package | E85: RHB | G85: Your items 12 & 13. RHB, like the 23 Sep PJ receipt. Mid-Oct assumed
A86: Investor fund #1 | B86: 46310 | C86: 450000 | D86: Collection of Investor funds | E86: Maybank | G86: Your item 12. Mid-Oct assumed
A87: Investor fund #2 | B87: 46310 | C87: 200000 | D87: Collection of Investor funds | E87: Maybank | G87: Your item 12. Mid-Oct assumed
A88: Foreign worker expense | B88: 46310 | C88: -920000 | D88: Wage expenses | E88: Maybank | G88: Your item 7
A89: Investment — Bebeks | B89: 46310 | C89: -400000 | D89: Purchase of investment | E89: Maybank | G89: Updated: RM400k in October. Mid-Oct assumed
A90: Deposit — new outlet 1 | B90: 46304 | C90: =-'Q4 Assumptions'!$B$24 | D90: Deposit | E90: Maybank | G90: Your item 14, spread Oct–Nov
A91: Deposit — new outlet 2 | B91: 46318 | C91: =-'Q4 Assumptions'!$B$24 | D91: Deposit | E91: Maybank
A92: Deposit — new outlet 3 | B92: 46332 | C92: =-'Q4 Assumptions'!$B$24 | D92: Deposit | E92: Maybank
A93: Deposit — new outlet 4 | B93: 46342 | C93: =-'Q4 Assumptions'!$B$24 | D93: Deposit | E93: Maybank
A94: Deposit — new outlet 5 | B94: 46353 | C94: =-'Q4 Assumptions'!$B$24 | D94: Deposit | E94: Maybank
A95: Wages first week — October | B95: 46298 | C95: =-'Q4 Assumptions'!$B$30 | D95: Wage expenses | E95: Maybank | F95: Y | G95: RM1M first week of month
A96: Wages first week — November | B96: 46329 | C96: =-'Q4 Assumptions'!$B$30 | D96: Wage expenses | E96: Maybank | F96: Y
A97: Wages first week — December | B97: 46359 | C97: =-'Q4 Assumptions'!$B$30 | D97: Wage expenses | E97: Maybank | F97: Y
A98: Payroll 25th — October | B98: 46320 | C98: =-'Q4 Assumptions'!$B$28 | D98: Wage expenses | E98: RHB | F98: Y | G98: RM450k–500k week of the 25th
A99: Payroll 25th — November | B99: 46351 | C99: =-'Q4 Assumptions'!$B$28 | D99: Wage expenses | E99: RHB | F99: Y
A100: Payroll 25th — December | B100: 46380 | C100: =-'Q4 Assumptions'!$B$28 | D100: Wage expenses | E100: RHB | F100: Y | G100: 24 Dec (25 Dec public holiday)
A101: SST Sep–Oct 2026 | B101: 46356 | C101: =-'Remaining Payments'!E30 | D101: SST | E101: Maybank | G101: ASSUMPTION: bi-monthly SST, same as Jul–Aug (paid 30 Sep); due end of following month
A102: Foreign worker expense | B102: 46371 | C102: -200000 | D102: Wage expenses | E102: Maybank | G102: Your item 7
A103: Staff bonus | B103: 46387 | C103: -300000 | D103: Wage expenses | E103: RHB | G103: Your item 8 (paid with payroll from RHB)
A104: Investment — Kopitiam | B104: 46387 | C104: -350000 | D104: Purchase of investment | E104: Maybank | G104: Your item 16
...

Sheet Q4 Weekly Cash Flow
A1: TOP GLOBAL FOOD AND BEVERAGES SDN BHD
A2: Q4 2026 WEEKLY CASH FLOW FORECAST — MAYBANK + RHB COMBINED
B4: Period Beginning | C4: ='Q4 Assumptions'!$B$5
B5: Period Ending | C5: ='Q4 Assumptions'!$B$6
B6: Cash at Beginning of Period | C6: =R76
B7: Cash at End of Period | C7: =R77
A9: Operations | C9: Sept'26 Actual | D9: Week 1 | E9: Week 2 | F9: Week 3 | G9: Week 4 | H9: Week 5 | I9: Week 6 | J9: Week 7 | K9: Week 8 | L9: Week 9 | M9: Week 10 | N9: Week 11 | O9: Week 12 | P9: Week 13 | Q9: Week 14 | R9: Q4 Total
B10: Week start | C10: 1-Sep-26 to | D10: ='Q4 Assumptions'!$B$5 | E10: =D11+1 | F10: =E11+1 | G10: =F11+1 | H10: =G11+1 | I10: =H11+1 | J10: =I11+1 | K10: =J11+1 | L10: =K11+1 | ... Q10: =P11+1
B11: Week end | C11: 28-Sep-26 | D11: =MIN(D10+6-MOD(D10-2,7),'Q4 Assumptions'!$B$6) | E11: =MIN(E10+6-MOD(E10-2,7),'Q4 Assumptions'!$B$6) | F11: =MIN(F10+6-MOD(F10-2,7),'Q4 Assumptions'!$B$6) | G11: =MIN(G10+6-MOD(G10-2,7),'Q4 Assumptions'!$B$6) | H11: =MIN(H10+6-MOD(H10-2,7),'Q4 Assumptions'!$B$6) | I11: =MIN(I10+6-MOD(I10-2,7),'Q4 Assumptions'!$B$6) | J11: =MIN(J10+6-MOD(J10-2,7),'Q4 Assumptions'!$B$6) | K11: =MIN(K10+6-MOD(K10-2,7),'Q4 Assumptions'!$B$6) | ... Q11: =MIN(Q10+6-MOD(Q10-2,7),'Q4 Assumptions'!$B$6)
B12: Days | C12: Maybank only | D12: =D11-D10+1 | E12: =E11-E10+1 | F12: =F11-F10+1 | G12: =G11-G10+1 | H12: =H11-H10+1 | I12: =I11-I10+1 | J12: =J11-J10+1 | K12: =K11-K10+1 | ... Q12: =Q11-Q10+1 | R12: =SUM(D12:Q12)
A13: Cash receipts from
B14: Customers & Sales | C14: ='Q4 Assumptions'!C36 | D14: ='Q4 Assumptions'!$G$36*D$12+SUMIFS('Q4 Assumptions'!$C$85:$C$133,'Q4 Assumptions'!$D$85:$D$133,'Q4 Assumptions'!$A$36,'Q4 Assumptions'!$B$85:$B$133,">="&D$10,'Q4 Assumptions'!$B$85:$B$133,"<="&D$11)+D83+D90 | E14: ='Q4 Assumptions'!$G$36*E$12+SUMIFS('Q4 Assumptions'!$C$85:$C$133,'Q4 Assumptions'!$D$85:$D$133,'Q4 Assumptions'!$A$36,'Q4 Assumptions'!$B$85:$B$133,">="&E$10,'Q4 Assumptions'!$B$85:$B$133,"<="&E$11)+E83+E90 | F14: ='Q4 Assumptions'!$G$36*F$12+SUMIFS('Q4 Assumptions'!$C$85:$C$133,'Q4 Assumptions'!$D$85:$D$133,'Q4 Assumptions'!$A$36,'Q4 Assumptions'!$B$85:$B$133,">="&F$10,'Q4 Assumptions'!$B$85:$B$133,"<="&F$11)+F83+F90 | G14: ='Q4 Assumptions'!$G$36*G$12+SUMIFS('Q4 Assumptions'!$C$85:$C$133,'Q4 Assumptions'!$D$85:$D$133,'Q4 Assumptions'!$A$36,'Q4 Assumptions'!$B$85:$B$133,">="&G$10,'Q4 Assumptions'!$B$85:$B$133,"<="&G$11)+G83+G90 | H14: ='Q4 Assumptions'!$G$36*H$12+SUMIFS('Q4 Assumptions'!$C$85:$C$133,'Q4 Assumptions'!$D$85:$D$133,'Q4 Assumptions'!$A$36,'Q4 Assumptions'!$B$85:$B$133,">="&H$10,'Q4 Assumptions'!$B$85:$B$133,"<="&H$11)+H83+H90 | I14: ='Q4 Assumptions'!$G$36*I$12+SUMIFS('Q4 Assumptions'!$C$85:$C$133,'Q4 Assumptions'!$D$85:$D$133,'Q4 Assumptions'!$A$36,'Q4 Assumptions'!$B$85:$B$133,">="&I$10,'Q4 Assumptions'!$B$85:$B$133,"<="&I$11)+I83+I90 | J14: ='Q4 Assumptions'!$G$36*J$12+SUMIFS('Q4 Assumptions'!$C$85:$C$133,'Q4 Assumptions'!$D$85:$D$133,'Q4 Assumptions'!$A$36,'Q4 Assumptions'!$B$85:$B$133,">="&J$10,'Q4 Assumptions'!$B$85:$B$133,"<="&J$11)+J83+J90 | K14: ='Q4 Assumptions'!$G$36*K$12+SUMIFS('Q4 Assumptions'!$C$85:$C$133,'Q4 Assumptions'!$D$85:$D$133,'Q4 Assumptions'!$A$36,'Q4 Assumptions'!$B$85:$B$133,">="&K$10,'Q4 Assumptions'!$B$85:$B$133,"<="&K$11)+K83+K90 | ... Q14: ='Q4 Assumptions'!$G$36*Q$12+SUMIFS('Q4 Assumptions'!$C$85:$C$133,'Q4 Assumptions'!$D$85:$D$133,'Q4 Assumptions'!$A$36,'Q4 Assumptions'!$B$85:$B$133,">="&Q$10,'Q4 Assumptions'!$B$85:$B$133,"<="&Q$11)+Q83+Q90 | R14: =SUM(D14:Q14)
B15: Licensing fee | C15: ='Q4 Assumptions'!C37 | D15: ='Q4 Assumptions'!$G$37*D$12+SUMIFS('Q4 Assumptions'!$C$85:$C$133,'Q4 Assumptions'!$D$85:$D$133,'Q4 Assumptions'!$A$37,'Q4 Assumptions'!$B$85:$B$133,">="&D$10,'Q4 Assumptions'!$B$85:$B$133,"<="&D$11) | E15: ='Q4 Assumptions'!$G$37*E$12+SUMIFS('Q4 Assumptions'!$C$85:$C$133,'Q4 Assumptions'!$D$85:$D$133,'Q4 Assumptions'!$A$37,'Q4 Assumptions'!$B$85:$B$133,">="&E$10,'Q4 Assumptions'!$B$85:$B$133,"<="&E$11) | F15: ='Q4 Assumptions'!$G$37*F$12+SUMIFS('Q4 Assumptions'!$C$85:$C$133,'Q4 Assumptions'!$D$85:$D$133,'Q4 Assumptions'!$A$37,'Q4 Assumptions'!$B$85:$B$133,">="&F$10,'Q4 Assumptions'!$B$85:$B$133,"<="&F$11) | G15: ='Q4 Assumptions'!$G$37*G$12+SUMIFS('Q4 Assumptions'!$C$85:$C$133,'Q4 Assumptions'!$D$85:$D$133,'Q4 Assumptions'!$A$37,'Q4 Assumptions'!$B$85:$B$133,">="&G$10,'Q4 Assumptions'!$B$85:$B$133,"<="&G$11) | H15: ='Q4 Assumptions'!$G$37*H$12+SUMIFS('Q4 Assumptions'!$C$85:$C$133,'Q4 Assumptions'!$D$85:$D$133,'Q4 Assumptions'!$A$37,'Q4 Assumptions'!$B$85:$B$133,">="&H$10,'Q4 Assumptions'!$B$85:$B$133,"<="&H$11) | I15: ='Q4 Assumptions'!$G$37*I$12+SUMIFS('Q4 Assumptions'!$C$85:$C$133,'Q4 Assumptions'!$D$85:$D$133,'Q4 Assumptions'!$A$37,'Q4 Assumptions'!$B$85:$B$133,">="&I$10,'Q4 Assumptions'!$B$85:$B$133,"<="&I$11) | J15: ='Q4 Assumptions'!$G$37*J$12+SUMIFS('Q4 Assumptions'!$C$85:$C$133,'Q4 Assumptions'!$D$85:$D$133,'Q4 Assumptions'!$A$37,'Q4 Assumptions'!$B$85:$B$133,">="&J$10,'Q4 Assumptions'!$B$85:$B$133,"<="&J$11) | K15: ='Q4 Assumptions'!$G$37*K$12+SUMIFS('Q4 Assumptions'!$C$85:$C$133,'Q4 Assumptions'!$D$85:$D$133,'Q4 Assumptions'!$A$37,'Q4 Assumptions'!$B$85:$B$133,">="&K$10,'Q4 Assumptions'!$B$85:$B$133,"<="&K$11) | ... Q15: ='Q4 Assumptions'!$G$37*Q$12+SUMIFS('Q4 Assumptions'!$C$85:$C$133,'Q4 Assumptions'!$D$85:$D$133,'Q4 Assumptions'!$A$37,'Q4 Assumptions'!$B$85:$B$133,">="&Q$10,'Q4 Assumptions'!$B$85:$B$133,"<="&Q$11) | R15: =SUM(D15:Q15)
B16: Licensing package | C16: ='Q4 Assumptions'!C38 | D16: ='Q4 Assumptions'!$G$38*D$12+SUMIFS('Q4 Assumptions'!$C$85:$C$133,'Q4 Assumptions'!$D$85:$D$133,'Q4 Assumptions'!$A$38,'Q4 Assumptions'!$B$85:$B$133,">="&D$10,'Q4 Assumptions'!$B$85:$B$133,"<="&D$11) | E16: ='Q4 Assumptions'!$G$38*E$12+SUMIFS('Q4 Assumptions'!$C$85:$C$133,'Q4 Assumptions'!$D$85:$D$133,'Q4 Assumptions'!$A$38,'Q4 Assumptions'!$B$85:$B$133,">="&E$10,'Q4 Assumptions'!$B$85:$B$133,"<="&E$11) | F16: ='Q4 Assumptions'!$G$38*F$12+SUMIFS('Q4 Assumptions'!$C$85:$C$133,'Q4 Assumptions'!$D$85:$D$133,'Q4 Assumptions'!$A$38,'Q4 Assumptions'!$B$85:$B$133,">="&F$10,'Q4 Assumptions'!$B$85:$B$133,"<="&F$11) | G16: ='Q4 Assumptions'!$G$38*G$12+SUMIFS('Q4 Assumptions'!$C$85:$C$133,'Q4 Assumptions'!$D$85:$D$133,'Q4 Assumptions'!$A$38,'Q4 Assumptions'!$B$85:$B$133,">="&G$10,'Q4 Assumptions'!$B$85:$B$133,"<="&G$11) | H16: ='Q4 Assumptions'!$G$38*H$12+SUMIFS('Q4 Assumptions'!$C$85:$C$133,'Q4 Assumptions'!$D$85:$D$133,'Q4 Assumptions'!$A$38,'Q4 Assumptions'!$B$85:$B$133,">="&H$10,'Q4 Assumptions'!$B$85:$B$133,"<="&H$11) | I16: ='Q4 Assumptions'!$G$38*I$12+SUMIFS('Q4 Assumptions'!$C$85:$C$133,'Q4 Assumptions'!$D$85:$D$133,'Q4 Assumptions'!$A$38,'Q4 Assumptions'!$B$85:$B$133,">="&I$10,'Q4 Assumptions'!$B$85:$B$133,"<="&I$11) | J16: ='Q4 Assumptions'!$G$38*J$12+SUMIFS('Q4 Assumptions'!$C$85:$C$133,'Q4 Assumptions'!$D$85:$D$133,'Q4 Assumptions'!$A$38,'Q4 Assumptions'!$B$85:$B$133,">="&J$10,'Q4 Assumptions'!$B$85:$B$133,"<="&J$11) | K16: ='Q4 Assumptions'!$G$38*K$12+SUMIFS('Q4 Assumptions'!$C$85:$C$133,'Q4 Assumptions'!$D$85:$D$133,'Q4 Assumptions'!$A$38,'Q4 Assumptions'!$B$85:$B$133,">="&K$10,'Q4 Assumptions'!$B$85:$B$133,"<="&K$11) | ... Q16: ='Q4 Assumptions'!$G$38*Q$12+SUMIFS('Q4 Assumptions'!$C$85:$C$133,'Q4 Assumptions'!$D$85:$D$133,'Q4 Assumptions'!$A$38,'Q4 Assumptions'!$B$85:$B$133,">="&Q$10,'Q4 Assumptions'!$B$85:$B$133,"<="&Q$11) | R16: =SUM(D16:Q16)
B17: Royalty | C17: ='Q4 Assumptions'!C39 | D17: ='Q4 Assumptions'!$G$39*D$12+SUMIFS('Q4 Assumptions'!$C$85:$C$133,'Q4 Assumptions'!$D$85:$D$133,'Q4 Assumptions'!$A$39,'Q4 Assumptions'!$B$85:$B$133,">="&D$10,'Q4 Assumptions'!$B$85:$B$133,"<="&D$11) | E17: ='Q4 Assumptions'!$G$39*E$12+SUMIFS('Q4 Assumptions'!$C$85:$C$133,'Q4 Assumptions'!$D$85:$D$133,'Q4 Assumptions'!$A$39,'Q4 Assumptions'!$B$85:$B$133,">="&E$10,'Q4 Assumptions'!$B$85:$B$133,"<="&E$11) | F17: ='Q4 Assumptions'!$G$39*F$12+SUMIFS('Q4 Assumptions'!$C$85:$C$133,'Q4 Assumptions'!$D$85:$D$133,'Q4 Assumptions'!$A$39,'Q4 Assumptions'!$B$85:$B$133,">="&F$10,'Q4 Assumptions'!$B$85:$B$133,"<="&F$11) | G17: ='Q4 Assumptions'!$G$39*G$12+SUMIFS('Q4 Assumptions'!$C$85:$C$133,'Q4 Assumptions'!$D$85:$D$133,'Q4 Assumptions'!$A$39,'Q4 Assumptions'!$B$85:$B$133,">="&G$10,'Q4 Assumptions'!$B$85:$B$133,"<="&G$11) | H17: ='Q4 Assumptions'!$G$39*H$12+SUMIFS('Q4 Assumptions'!$C$85:$C$133,'Q4 Assumptions'!$D$85:$D$133,'Q4 Assumptions'!$A$39,'Q4 Assumptions'!$B$85:$B$133,">="&H$10,'Q4 Assumptions'!$B$85:$B$133,"<="&H$11) | I17: ='Q4 Assumptions'!$G$39*I$12+SUMIFS('Q4 Assumptions'!$C$85:$C$133,'Q4 Assumptions'!$D$85:$D$133,'Q4 Assumptions'!$A$39,'Q4 Assumptions'!$B$85:$B$133,">="&I$10,'Q4 Assumptions'!$B$85:$B$133,"<="&I$11) | J17: ='Q4 Assumptions'!$G$39*J$12+SUMIFS('Q4 Assumptions'!$C$85:$C$133,'Q4 Assumptions'!$D$85:$D$133,'Q4 Assumptions'!$A$39,'Q4 Assumptions'!$B$85:$B$133,">="&J$10,'Q4 Assumptions'!$B$85:$B$133,"<="&J$11) | K17: ='Q4 Assumptions'!$G$39*K$12+SUMIFS('Q4 Assumptions'!$C$85:$C$133,'Q4 Assumptions'!$D$85:$D$133,'Q4 Assumptions'!$A$39,'Q4 Assumptions'!$B$85:$B$133,">="&K$10,'Q4 Assumptions'!$B$85:$B$133,"<="&K$11) | ... Q17: ='Q4 Assumptions'!$G$39*Q$12+SUMIFS('Q4 Assumptions'!$C$85:$C$133,'Q4 Assumptions'!$D$85:$D$133,'Q4 Assumptions'!$A$39,'Q4 Assumptions'!$B$85:$B$133,">="&Q$10,'Q4 Assumptions'!$B$85:$B$133,"<="&Q$11) | R17: =SUM(D17:Q17)
B18: Other operations | C18: ='Q4 Assumptions'!C40 | D18: ='Q4 Assumptions'!$G$40*D$12+SUMIFS('Q4 Assumptions'!$C$85:$C$133,'Q4 Assumptions'!$D$85:$D$133,'Q4 Assumptions'!$A$40,'Q4 Assumptions'!$B$85:$B$133,">="&D$10,'Q4 Assumptions'!$B$85:$B$133,"<="&D$11) | E18: ='Q4 Assumptions'!$G$40*E$12+SUMIFS('Q4 Assumptions'!$C$85:$C$133,'Q4 Assumptions'!$D$85:$D$133,'Q4 Assumptions'!$A$40,'Q4 Assumptions'!$B$85:$B$133,">="&E$10,'Q4 Assumptions'!$B$85:$B$133,"<="&E$11) | F18: ='Q4 Assumptions'!$G$40*F$12+SUMIFS('Q4 Assumptions'!$C$85:$C$133,'Q4 Assumptions'!$D$85:$D$133,'Q4 Assumptions'!$A$40,'Q4 Assumptions'!$B$85:$B$133,">="&F$10,'Q4 Assumptions'!$B$85:$B$133,"<="&F$11) | G18: ='Q4 Assumptions'!$G$40*G$12+SUMIFS('Q4 Assumptions'!$C$85:$C$133,'Q4 Assumptions'!$D$85:$D$133,'Q4 Assumptions'!$A$40,'Q4 Assumptions'!$B$85:$B$133,">="&G$10,'Q4 Assumptions'!$B$85:$B$133,"<="&G$11) | H18: ='Q4 Assumptions'!$G$40*H$12+SUMIFS('Q4 Assumptions'!$C$85:$C$133,'Q4 Assumptions'!$D$85:$D$133,'Q4 Assumptions'!$A$40,'Q4 Assumptions'!$B$85:$B$133,">="&H$10,'Q4 Assumptions'!$B$85:$B$133,"<="&H$11) | I18: ='Q4 Assumptions'!$G$40*I$12+SUMIFS('Q4 Assumptions'!$C$85:$C$133,'Q4 Assumptions'!$D$85:$D$133,'Q4 Assumptions'!$A$40,'Q4 Assumptions'!$B$85:$B$133,">="&I$10,'Q4 Assumptions'!$B$85:$B$133,"<="&I$11) | J18: ='Q4 Assumptions'!$G$40*J$12+SUMIFS('Q4 Assumptions'!$C$85:$C$133,'Q4 Assumptions'!$D$85:$D$133,'Q4 Assumptions'!$A$40,'Q4 Assumptions'!$B$85:$B$133,">="&J$10,'Q4 Assumptions'!$B$85:$B$133,"<="&J$11) | K18: ='Q4 Assumptions'!$G$40*K$12+SUMIFS('Q4 Assumptions'!$C$85:$C$133,'Q4 Assumptions'!$D$85:$D$133,'Q4 Assumptions'!$A$40,'Q4 Assumptions'!$B$85:$B$133,">="&K$10,'Q4 Assumptions'!$B$85:$B$133,"<="&K$11) | ... Q18: ='Q4 Assumptions'!$G$40*Q$12+SUMIFS('Q4 Assumptions'!$C$85:$C$133,'Q4 Assumptions'!$D$85:$D$133,'Q4 Assumptions'!$A$40,'Q4 Assumptions'!$B$85:$B$133,">="&Q$10,'Q4 Assumptions'!$B$85:$B$133,"<="&Q$11) | R18: =SUM(D18:Q18)
C19: =SUM(C14:C18) | D19: =SUM(D14:D18) | E19: =SUM(E14:E18) | F19: =SUM(F14:F18) | G19: =SUM(G14:G18) | H19: =SUM(H14:H18) | I19: =SUM(I14:I18) | J19: =SUM(J14:J18) | ... R19: =SUM(R14:R18)
A20: Cash paid for
B21: Inventory purchases | C21: ='Q4 Assumptions'!C41 | D21: ='Q4 Assumptions'!$G$41*D$12+SUMIFS('Q4 Assumptions'!$C$85:$C$133,'Q4 Assumptions'!$D$85:$D$133,'Q4 Assumptions'!$A$41,'Q4 Assumptions'!$B$85:$B$133,">="&D$10,'Q4 Assumptions'!$B$85:$B$133,"<="&D$11)+D87 | E21: ='Q4 Assumptions'!$G$41*E$12+SUMIFS('Q4 Assumptions'!$C$85:$C$133,'Q4 Assumptions'!$D$85:$D$133,'Q4 Assumptions'!$A$41,'Q4 Assumptions'!$B$85:$B$133,">="&E$10,'Q4 Assumptions'!$B$85:$B$133,"<="&E$11)+E87 | F21: ='Q4 Assumptions'!$G$41*F$12+SUMIFS('Q4 Assumptions'!$C$85:$C$133,'Q4 Assumptions'!$D$85:$D$133,'Q4 Assumptions'!$A$41,'Q4 Assumptions'!$B$85:$B$133,">="&F$10,'Q4 Assumptions'!$B$85:$B$133,"<="&F$11)+F87 | G21: ='Q4 Assumptions'!$G$41*G$12+SUMIFS('Q4 Assumptions'!$C$85:$C$133,'Q4 Assumptions'!$D$85:$D$133,'Q4 Assumptions'!$A$41,'Q4 Assumptions'!$B$85:$B$133,">="&G$10,'Q4 Assumptions'!$B$85:$B$133,"<="&G$11)+G87 | H21: ='Q4 Assumptions'!$G$41*H$12+SUMIFS('Q4 Assumptions'!$C$85:$C$133,'Q4 Assumptions'!$D$85:$D$133,'Q4 Assumptions'!$A$41,'Q4 Assumptions'!$B$85:$B$133,">="&H$10,'Q4 Assumptions'!$B$85:$B$133,"<="&H$11)+H87 | I21: ='Q4 Assumptions'!$G$41*I$12+SUMIFS('Q4 Assumptions'!$C$85:$C$133,'Q4 Assumptions'!$D$85:$D$133,'Q4 Assumptions'!$A$41,'Q4 Assumptions'!$B$85:$B$133,">="&I$10,'Q4 Assumptions'!$B$85:$B$133,"<="&I$11)+I87 | J21: ='Q4 Assumptions'!$G$41*J$12+SUMIFS('Q4 Assumptions'!$C$85:$C$133,'Q4 Assumptions'!$D$85:$D$133,'Q4 Assumptions'!$A$41,'Q4 Assumptions'!$B$85:$B$133,">="&J$10,'Q4 Assumptions'!$B$85:$B$133,"<="&J$11)+J87 | K21: ='Q4 Assumptions'!$G$41*K$12+SUMIFS('Q4 Assumptions'!$C$85:$C$133,'Q4 Assumptions'!$D$85:$D$133,'Q4 Assumptions'!$A$41,'Q4 Assumptions'!$B$85:$B$133,">="&K$10,'Q4 Assumptions'!$B$85:$B$133,"<="&K$11)+K87 | ... Q21: ='Q4 Assumptions'!$G$41*Q$12+SUMIFS('Q4 Assumptions'!$C$85:$C$133,'Q4 Assumptions'!$D$85:$D$133,'Q4 Assumptions'!$A$41,'Q4 Assumptions'!$B$85:$B$133,">="&Q$10,'Q4 Assumptions'!$B$85:$B$133,"<="&Q$11)+Q87 | R21: =SUM(D21:Q21)
B22: Distribution Fee | C22: ='Q4 Assumptions'!C42 | D22: ='Q4 Assumptions'!$G$42*D$12+SUMIFS('Q4 Assumptions'!$C$85:$C$133,'Q4 Assumptions'!$D$85:$D$133,'Q4 Assumptions'!$A$42,'Q4 Assumptions'!$B$85:$B$133,">="&D$10,'Q4 Assumptions'!$B$85:$B$133,"<="&D$11) | E22: ='Q4 Assumptions'!$G$42*E$12+SUMIFS('Q4 Assumptions'!$C$85:$C$133,'Q4 Assumptions'!$D$85:$D$133,'Q4 Assumptions'!$A$42,'Q4 Assumptions'!$B$85:$B$133,">="&E$10,'Q4 Assumptions'!$B$85:$B$133,"<="&E$11) | F22: ='Q4 Assumptions'!$G$42*F$12+SUMIFS('Q4 Assumptions'!$C$85:$C$133,'Q4 Assumptions'!$D$85:$D$133,'Q4 Assumptions'!$A$42,'Q4 Assumptions'!$B$85:$B$133,">="&F$10,'Q4 Assumptions'!$B$85:$B$133,"<="&F$11) | G22: ='Q4 Assumptions'!$G$42*G$12+SUMIFS('Q4 Assumptions'!$C$85:$C$133,'Q4 Assumptions'!$D$85:$D$133,'Q4 Assumptions'!$A$42,'Q4 Assumptions'!$B$85:$B$133,">="&G$10,'Q4 Assumptions'!$B$85:$B$133,"<="&G$11) | H22: ='Q4 Assumptions'!$G$42*H$12+SUMIFS('Q4 Assumptions'!$C$85:$C$133,'Q4 Assumptions'!$D$85:$D$133,'Q4 Assumptions'!$A$42,'Q4 Assumptions'!$B$85:$B$133,">="&H$10,'Q4 Assumptions'!$B$85:$B$133,"<="&H$11) | I22: ='Q4 Assumptions'!$G$42*I$12+SUMIFS('Q4 Assumptions'!$C$85:$C$133,'Q4 Assumptions'!$D$85:$D$133,'Q4 Assumptions'!$A$42,'Q4 Assumptions'!$B$85:$B$133,">="&I$10,'Q4 Assumptions'!$B$85:$B$133,"<="&I$11) | J22: ='Q4 Assumptions'!$G$42*J$12+SUMIFS('Q4 Assumptions'!$C$85:$C$133,'Q4 Assumptions'!$D$85:$D$133,'Q4 Assumptions'!$A$42,'Q4 Assumptions'!$B$85:$B$133,">="&J$10,'Q4 Assumptions'!$B$85:$B$133,"<="&J$11) | K22: ='Q4 Assumptions'!$G$42*K$12+SUMIFS('Q4 Assumptions'!$C$85:$C$133,'Q4 Assumptions'!$D$85:$D$133,'Q4 Assumptions'!$A$42,'Q4 Assumptions'!$B$85:$B$133,">="&K$10,'Q4 Assumptions'!$B$85:$B$133,"<="&K$11) | ... Q22: ='Q4 Assumptions'!$G$42*Q$12+SUMIFS('Q4 Assumptions'!$C$85:$C$133,'Q4 Assumptions'!$D$85:$D$133,'Q4 Assumptions'!$A$42,'Q4 Assumptions'!$B$85:$B$133,">="&Q$10,'Q4 Assumptions'!$B$85:$B$133,"<="&Q$11) | R22: =SUM(D22:Q22)
B23: Deposit | C23: ='Q4 Assumptions'!C43 | D23: ='Q4 Assumptions'!$G$43*D$12+SUMIFS('Q4 Assumptions'!$C$85:$C$133,'Q4 Assumptions'!$D$85:$D$133,'Q4 Assumptions'!$A$43,'Q4 Assumptions'!$B$85:$B$133,">="&D$10,'Q4 Assumptions'!$B$85:$B$133,"<="&D$11) | E23: ='Q4 Assumptions'!$G$43*E$12+SUMIFS('Q4 Assumptions'!$C$85:$C$133,'Q4 Assumptions'!$D$85:$D$133,'Q4 Assumptions'!$A$43,'Q4 Assumptions'!$B$85:$B$133,">="&E$10,'Q4 Assumptions'!$B$85:$B$133,"<="&E$11) | F23: ='Q4 Assumptions'!$G$43*F$12+SUMIFS('Q4 Assumptions'!$C$85:$C$133,'Q4 Assumptions'!$D$85:$D$133,'Q4 Assumptions'!$A$43,'Q4 Assumptions'!$B$85:$B$133,">="&F$10,'Q4 Assumptions'!$B$85:$B$133,"<="&F$11) | G23: ='Q4 Assumptions'!$G$43*G$12+SUMIFS('Q4 Assumptions'!$C$85:$C$133,'Q4 Assumptions'!$D$85:$D$133,'Q4 Assumptions'!$A$43,'Q4 Assumptions'!$B$85:$B$133,">="&G$10,'Q4 Assumptions'!$B$85:$B$133,"<="&G$11) | H23: ='Q4 Assumptions'!$G$43*H$12+SUMIFS('Q4 Assumptions'!$C$85:$C$133,'Q4 Assumptions'!$D$85:$D$133,'Q4 Assumptions'!$A$43,'Q4 Assumptions'!$B$85:$B$133,">="&H$10,'Q4 Assumptions'!$B$85:$B$133,"<="&H$11) | I23: ='Q4 Assumptions'!$G$43*I$12+SUMIFS('Q4 Assumptions'!$C$85:$C$133,'Q4 Assumptions'!$D$85:$D$133,'Q4 Assumptions'!$A$43,'Q4 Assumptions'!$B$85:$B$133,">="&I$10,'Q4 Assumptions'!$B$85:$B$133,"<="&I$11) | J23: ='Q4 Assumptions'!$G$43*J$12+SUMIFS('Q4 Assumptions'!$C$85:$C$133,'Q4 Assumptions'!$D$85:$D$133,'Q4 Assumptions'!$A$43,'Q4 Assumptions'!$B$85:$B$133,">="&J$10,'Q4 Assumptions'!$B$85:$B$133,"<="&J$11) | K23: ='Q4 Assumptions'!$G$43*K$12+SUMIFS('Q4 Assumptions'!$C$85:$C$133,'Q4 Assumptions'!$D$85:$D$133,'Q4 Assumptions'!$A$43,'Q4 Assumptions'!$B$85:$B$133,">="&K$10,'Q4 Assumptions'!$B$85:$B$133,"<="&K$11) | ... Q23: ='Q4 Assumptions'!$G$43*Q$12+SUMIFS('Q4 Assumptions'!$C$85:$C$133,'Q4 Assumptions'!$D$85:$D$133,'Q4 Assumptions'!$A$43,'Q4 Assumptions'!$B$85:$B$133,">="&Q$10,'Q4 Assumptions'!$B$85:$B$133,"<="&Q$11) | R23: =SUM(D23:Q23)
B24: HQ Operation | C24: ='Q4 Assumptions'!C44 | D24: ='Q4 Assumptions'!$G$44*D$12+SUMIFS('Q4 Assumptions'!$C$85:$C$133,'Q4 Assumptions'!$D$85:$D$133,'Q4 Assumptions'!$A$44,'Q4 Assumptions'!$B$85:$B$133,">="&D$10,'Q4 Assumptions'!$B$85:$B$133,"<="&D$11) | E24: ='Q4 Assumptions'!$G$44*E$12+SUMIFS('Q4 Assumptions'!$C$85:$C$133,'Q4 Assumptions'!$D$85:$D$133,'Q4 Assumptions'!$A$44,'Q4 Assumptions'!$B$85:$B$133,">="&E$10,'Q4 Assumptions'!$B$85:$B$133,"<="&E$11) | F24: ='Q4 Assumptions'!$G$44*F$12+SUMIFS('Q4 Assumptions'!$C$85:$C$133,'Q4 Assumptions'!$D$85:$D$133,'Q4 Assumptions'!$A$44,'Q4 Assumptions'!$B$85:$B$133,">="&F$10,'Q4 Assumptions'!$B$85:$B$133,"<="&F$11) | G24: ='Q4 Assumptions'!$G$44*G$12+SUMIFS('Q4 Assumptions'!$C$85:$C$133,'Q4 Assumptions'!$D$85:$D$133,'Q4 Assumptions'!$A$44,'Q4 Assumptions'!$B$85:$B$133,">="&G$10,'Q4 Assumptions'!$B$85:$B$133,"<="&G$11) | H24: ='Q4 Assumptions'!$G$44*H$12+SUMIFS('Q4 Assumptions'!$C$85:$C$133,'Q4 Assumptions'!$D$85:$D$133,'Q4 Assumptions'!$A$44,'Q4 Assumptions'!$B$85:$B$133,">="&H$10,'Q4 Assumptions'!$B$85:$B$133,"<="&H$11) | I24: ='Q4 Assumptions'!$G$44*I$12+SUMIFS('Q4 Assumptions'!$C$85:$C$133,'Q4 Assumptions'!$D$85:$D$133,'Q4 Assumptions'!$A$44,'Q4 Assumptions'!$B$85:$B$133,">="&I$10,'Q4 Assumptions'!$B$85:$B$133,"<="&I$11) | J24: ='Q4 Assumptions'!$G$44*J$12+SUMIFS('Q4 Assumptions'!$C$85:$C$133,'Q4 Assumptions'!$D$85:$D$133,'Q4 Assumptions'!$A$44,'Q4 Assumptions'!$B$85:$B$133,">="&J$10,'Q4 Assumptions'!$B$85:$B$133,"<="&J$11) | K24: ='Q4 Assumptions'!$G$44*K$12+SUMIFS('Q4 Assumptions'!$C$85:$C$133,'Q4 Assumptions'!$D$85:$D$133,'Q4 Assumptions'!$A$44,'Q4 Assumptions'!$B$85:$B$133,">="&K$10,'Q4 Assumptions'!$B$85:$B$133,"<="&K$11) | ... Q24: ='Q4 Assumptions'!$G$44*Q$12+SUMIFS('Q4 Assumptions'!$C$85:$C$133,'Q4 Assumptions'!$D$85:$D$133,'Q4 Assumptions'!$A$44,'Q4 Assumptions'!$B$85:$B$133,">="&Q$10,'Q4 Assumptions'!$B$85:$B$133,"<="&Q$11) | R24: =SUM(D24:Q24)
B25: Operation | C25: ='Q4 Assumptions'!C45 | D25: ='Q4 Assumptions'!$G$45*D$12+SUMIFS('Q4 Assumptions'!$C$85:$C$133,'Q4 Assumptions'!$D$85:$D$133,'Q4 Assumptions'!$A$45,'Q4 Assumptions'!$B$85:$B$133,">="&D$10,'Q4 Assumptions'!$B$85:$B$133,"<="&D$11) | E25: ='Q4 Assumptions'!$G$45*E$12+SUMIFS('Q4 Assumptions'!$C$85:$C$133,'Q4 Assumptions'!$D$85:$D$133,'Q4 Assumptions'!$A$45,'Q4 Assumptions'!$B$85:$B$133,">="&E$10,'Q4 Assumptions'!$B$85:$B$133,"<="&E$11) | F25: ='Q4 Assumptions'!$G$45*F$12+SUMIFS('Q4 Assumptions'!$C$85:$C$133,'Q4 Assumptions'!$D$85:$D$133,'Q4 Assumptions'!$A$45,'Q4 Assumptions'!$B$85:$B$133,">="&F$10,'Q4 Assumptions'!$B$85:$B$133,"<="&F$11) | G25: ='Q4 Assumptions'!$G$45*G$12+SUMIFS('Q4 Assumptions'!$C$85:$C$133,'Q4 Assumptions'!$D$85:$D$133,'Q4 Assumptions'!$A$45,'Q4 Assumptions'!$B$85:$B$133,">="&G$10,'Q4 Assumptions'!$B$85:$B$133,"<="&G$11) | H25: ='Q4 Assumptions'!$G$45*H$12+SUMIFS('Q4 Assumptions'!$C$85:$C$133,'Q4 Assumptions'!$D$85:$D$133,'Q4 Assumptions'!$A$45,'Q4 Assumptions'!$B$85:$B$133,">="&H$10,'Q4 Assumptions'!$B$85:$B$133,"<="&H$11) | I25: ='Q4 Assumptions'!$G$45*I$12+SUMIFS('Q4 Assumptions'!$C$85:$C$133,'Q4 Assumptions'!$D$85:$D$133,'Q4 Assumptions'!$A$45,'Q4 Assumptions'!$B$85:$B$133,">="&I$10,'Q4 Assumptions'!$B$85:$B$133,"<="&I$11) | J25: ='Q4 Assumptions'!$G$45*J$12+SUMIFS('Q4 Assumptions'!$C$85:$C$133,'Q4 Assumptions'!$D$85:$D$133,'Q4 Assumptions'!$A$45,'Q4 Assumptions'!$B$85:$B$133,">="&J$10,'Q4 Assumptions'!$B$85:$B$133,"<="&J$11) | K25: ='Q4 Assumptions'!$G$45*K$12+SUMIFS('Q4 Assumptions'!$C$85:$C$133,'Q4 Assumptions'!$D$85:$D$133,'Q4 Assumptions'!$A$45,'Q4 Assumptions'!$B$85:$B$133,">="&K$10,'Q4 Assumptions'!$B$85:$B$133,"<="&K$11) | ... Q25: ='Q4 Assumptions'!$G$45*Q$12+SUMIFS('Q4 Assumptions'!$C$85:$C$133,'Q4 Assumptions'!$D$85:$D$133,'Q4 Assumptions'!$A$45,'Q4 Assumptions'!$B$85:$B$133,">="&Q$10,'Q4 Assumptions'!$B$85:$B$133,"<="&Q$11) | R25: =SUM(D25:Q25)
B26: Marketing | C26: ='Q4 Assumptions'!C46 | D26: ='Q4 Assumptions'!$G$46*D$12+SUMIFS('Q4 Assumptions'!$C$85:$C$133,'Q4 Assumptions'!$D$85:$D$133,'Q4 Assumptions'!$A$46,'Q4 Assumptions'!$B$85:$B$133,">="&D$10,'Q4 Assumptions'!$B$85:$B$133,"<="&D$11) | E26: ='Q4 Assumptions'!$G$46*E$12+SUMIFS('Q4 Assumptions'!$C$85:$C$133,'Q4 Assumptions'!$D$85:$D$133,'Q4 Assumptions'!$A$46,'Q4 Assumptions'!$B$85:$B$133,">="&E$10,'Q4 Assumptions'!$B$85:$B$133,"<="&E$11) | F26: ='Q4 Assumptions'!$G$46*F$12+SUMIFS('Q4 Assumptions'!$C$85:$C$133,'Q4 Assumptions'!$D$85:$D$133,'Q4 Assumptions'!$A$46,'Q4 Assumptions'!$B$85:$B$133,">="&F$10,'Q4 Assumptions'!$B$85:$B$133,"<="&F$11) | G26: ='Q4 Assumptions'!$G$46*G$12+SUMIFS('Q4 Assumptions'!$C$85:$C$133,'Q4 Assumptions'!$D$85:$D$133,'Q4 Assumptions'!$A$46,'Q4 Assumptions'!$B$85:$B$133,">="&G$10,'Q4 Assumptions'!$B$85:$B$133,"<="&G$11) | H26: ='Q4 Assumptions'!$G$46*H$12+SUMIFS('Q4 Assumptions'!$C$85:$C$133,'Q4 Assumptions'!$D$85:$D$133,'Q4 Assumptions'!$A$46,'Q4 Assumptions'!$B$85:$B$133,">="&H$10,'Q4 Assumptions'!$B$85:$B$133,"<="&H$11) | I26: ='Q4 Assumptions'!$G$46*I$12+SUMIFS('Q4 Assumptions'!$C$85:$C$133,'Q4 Assumptions'!$D$85:$D$133,'Q4 Assumptions'!$A$46,'Q4 Assumptions'!$B$85:$B$133,">="&I$10,'Q4 Assumptions'!$B$85:$B$133,"<="&I$11) | J26: ='Q4 Assumptions'!$G$46*J$12+SUMIFS('Q4 Assumptions'!$C$85:$C$133,'Q4 Assumptions'!$D$85:$D$133,'Q4 Assumptions'!$A$46,'Q4 Assumptions'!$B$85:$B$133,">="&J$10,'Q4 Assumptions'!$B$85:$B$133,"<="&J$11) | K26: ='Q4 Assumptions'!$G$46*K$12+SUMIFS('Q4 Assumptions'!$C$85:$C$133,'Q4 Assumptions'!$D$85:$D$133,'Q4 Assumptions'!$A$46,'Q4 Assumptions'!$B$85:$B$133,">="&K$10,'Q4 Assumptions'!$B$85:$B$133,"<="&K$11) | ... Q26: ='Q4 Assumptions'!$G$46*Q$12+SUMIFS('Q4 Assumptions'!$C$85:$C$133,'Q4 Assumptions'!$D$85:$D$133,'Q4 Assumptions'!$A$46,'Q4 Assumptions'!$B$85:$B$133,">="&Q$10,'Q4 Assumptions'!$B$85:$B$133,"<="&Q$11) | R26: =SUM(D26:Q26)
B27: Profit sharing | C27: ='Q4 Assumptions'!C47 | D27: ='Q4 Assumptions'!$G$47*D$12+SUMIFS('Q4 Assumptions'!$C$85:$C$133,'Q4 Assumptions'!$D$85:$D$133,'Q4 Assumptions'!$A$47,'Q4 Assumptions'!$B$85:$B$133,">="&D$10,'Q4 Assumptions'!$B$85:$B$133,"<="&D$11) | E27: ='Q4 Assumptions'!$G$47*E$12+SUMIFS('Q4 Assumptions'!$C$85:$C$133,'Q4 Assumptions'!$D$85:$D$133,'Q4 Assumptions'!$A$47,'Q4 Assumptions'!$B$85:$B$133,">="&E$10,'Q4 Assumptions'!$B$85:$B$133,"<="&E$11) | F27: ='Q4 Assumptions'!$G$47*F$12+SUMIFS('Q4 Assumptions'!$C$85:$C$133,'Q4 Assumptions'!$D$85:$D$133,'Q4 Assumptions'!$A$47,'Q4 Assumptions'!$B$85:$B$133,">="&F$10,'Q4 Assumptions'!$B$85:$B$133,"<="&F$11) | G27: ='Q4 Assumptions'!$G$47*G$12+SUMIFS('Q4 Assumptions'!$C$85:$C$133,'Q4 Assumptions'!$D$85:$D$133,'Q4 Assumptions'!$A$47,'Q4 Assumptions'!$B$85:$B$133,">="&G$10,'Q4 Assumptions'!$B$85:$B$133,"<="&G$11) | H27: ='Q4 Assumptions'!$G$47*H$12+SUMIFS('Q4 Assumptions'!$C$85:$C$133,'Q4 Assumptions'!$D$85:$D$133,'Q4 Assumptions'!$A$47,'Q4 Assumptions'!$B$85:$B$133,">="&H$10,'Q4 Assumptions'!$B$85:$B$133,"<="&H$11) | I27: ='Q4 Assumptions'!$G$47*I$12+SUMIFS('Q4 Assumptions'!$C$85:$C$133,'Q4 Assumptions'!$D$85:$D$133,'Q4 Assumptions'!$A$47,'Q4 Assumptions'!$B$85:$B$133,">="&I$10,'Q4 Assumptions'!$B$85:$B$133,"<="&I$11) | J27: ='Q4 Assumptions'!$G$47*J$12+SUMIFS('Q4 Assumptions'!$C$85:$C$133,'Q4 Assumptions'!$D$85:$D$133,'Q4 Assumptions'!$A$47,'Q4 Assumptions'!$B$85:$B$133,">="&J$10,'Q4 Assumptions'!$B$85:$B$133,"<="&J$11) | K27: ='Q4 Assumptions'!$G$47*K$12+SUMIFS('Q4 Assumptions'!$C$85:$C$133,'Q4 Assumptions'!$D$85:$D$133,'Q4 Assumptions'!$A$47,'Q4 Assumptions'!$B$85:$B$133,">="&K$10,'Q4 Assumptions'!$B$85:$B$133,"<="&K$11) | ... Q27: ='Q4 Assumptions'!$G$47*Q$12+SUMIFS('Q4 Assumptions'!$C$85:$C$133,'Q4 Assumptions'!$D$85:$D$133,'Q4 Assumptions'!$A$47,'Q4 Assumptions'!$B$85:$B$133,">="&Q$10,'Q4 Assumptions'!$B$85:$B$133,"<="&Q$11) | R27: =SUM(D27:Q27)
B28: Wage expenses | C28: ='Q4 Assumptions'!C48 | D28: ='Q4 Assumptions'!$G$48*D$12+SUMIFS('Q4 Assumptions'!$C$85:$C$133,'Q4 Assumptions'!$D$85:$D$133,'Q4 Assumptions'!$A$48,'Q4 Assumptions'!$B$85:$B$133,">="&D$10,'Q4 Assumptions'!$B$85:$B$133,"<="&D$11)+D85 | E28: ='Q4 Assumptions'!$G$48*E$12+SUMIFS('Q4 Assumptions'!$C$85:$C$133,'Q4 Assumptions'!$D$85:$D$133,'Q4 Assumptions'!$A$48,'Q4 Assumptions'!$B$85:$B$133,">="&E$10,'Q4 Assumptions'!$B$85:$B$133,"<="&E$11)+E85 | F28: ='Q4 Assumptions'!$G$48*F$12+SUMIFS('Q4 Assumptions'!$C$85:$C$133,'Q4 Assumptions'!$D$85:$D$133,'Q4 Assumptions'!$A$48,'Q4 Assumptions'!$B$85:$B$133,">="&F$10,'Q4 Assumptions'!$B$85:$B$133,"<="&F$11)+F85 | G28: ='Q4 Assumptions'!$G$48*G$12+SUMIFS('Q4 Assumptions'!$C$85:$C$133,'Q4 Assumptions'!$D$85:$D$133,'Q4 Assumptions'!$A$48,'Q4 Assumptions'!$B$85:$B$133,">="&G$10,'Q4 Assumptions'!$B$85:$B$133,"<="&G$11)+G85 | H28: ='Q4 Assumptions'!$G$48*H$12+SUMIFS('Q4 Assumptions'!$C$85:$C$133,'Q4 Assumptions'!$D$85:$D$133,'Q4 Assumptions'!$A$48,'Q4 Assumptions'!$B$85:$B$133,">="&H$10,'Q4 Assumptions'!$B$85:$B$133,"<="&H$11)+H85 | I28: ='Q4 Assumptions'!$G$48*I$12+SUMIFS('Q4 Assumptions'!$C$85:$C$133,'Q4 Assumptions'!$D$85:$D$133,'Q4 Assumptions'!$A$48,'Q4 Assumptions'!$B$85:$B$133,">="&I$10,'Q4 Assumptions'!$B$85:$B$133,"<="&I$11)+I85 | J28: ='Q4 Assumptions'!$G$48*J$12+SUMIFS('Q4 Assumptions'!$C$85:$C$133,'Q4 Assumptions'!$D$85:$D$133,'Q4 Assumptions'!$A$48,'Q4 Assumptions'!$B$85:$B$133,">="&J$10,'Q4 Assumptions'!$B$85:$B$133,"<="&J$11)+J85 | K28: ='Q4 Assumptions'!$G$48*K$12+SUMIFS('Q4 Assumptions'!$C$85:$C$133,'Q4 Assumptions'!$D$85:$D$133,'Q4 Assumptions'!$A$48,'Q4 Assumptions'!$B$85:$B$133,">="&K$10,'Q4 Assumptions'!$B$85:$B$133,"<="&K$11)+K85 | ... Q28: ='Q4 Assumptions'!$G$48*Q$12+SUMIFS('Q4 Assumptions'!$C$85:$C$133,'Q4 Assumptions'!$D$85:$D$133,'Q4 Assumptions'!$A$48,'Q4 Assumptions'!$B$85:$B$133,">="&Q$10,'Q4 Assumptions'!$B$85:$B$133,"<="&Q$11)+Q85 | R28: =SUM(D28:Q28)
B29: Bank Charges | C29: ='Q4 Assumptions'!C49 | D29: ='Q4 Assumptions'!$G$49*D$12+SUMIFS('Q4 Assumptions'!$C$85:$C$133,'Q4 Assumptions'!$D$85:$D$133,'Q4 Assumptions'!$A$49,'Q4 Assumptions'!$B$85:$B$133,">="&D$10,'Q4 Assumptions'!$B$85:$B$133,"<="&D$11) | E29: ='Q4 Assumptions'!$G$49*E$12+SUMIFS('Q4 Assumptions'!$C$85:$C$133,'Q4 Assumptions'!$D$85:$D$133,'Q4 Assumptions'!$A$49,'Q4 Assumptions'!$B$85:$B$133,">="&E$10,'Q4 Assumptions'!$B$85:$B$133,"<="&E$11) | F29: ='Q4 Assumptions'!$G$49*F$12+SUMIFS('Q4 Assumptions'!$C$85:$C$133,'Q4 Assumptions'!$D$85:$D$133,'Q4 Assumptions'!$A$49,'Q4 Assumptions'!$B$85:$B$133,">="&F$10,'Q4 Assumptions'!$B$85:$B$133,"<="&F$11) | G29: ='Q4 Assumptions'!$G$49*G$12+SUMIFS('Q4 Assumptions'!$C$85:$C$133,'Q4 Assumptions'!$D$85:$D$133,'Q4 Assumptions'!$A$49,'Q4 Assumptions'!$B$85:$B$133,">="&G$10,'Q4 Assumptions'!$B$85:$B$133,"<="&G$11) | H29: ='Q4 Assumptions'!$G$49*H$12+SUMIFS('Q4 Assumptions'!$C$85:$C$133,'Q4 Assumptions'!$D$85:$D$133,'Q4 Assumptions'!$A$49,'Q4 Assumptions'!$B$85:$B$133,">="&H$10,'Q4 Assumptions'!$B$85:$B$133,"<="&H$11) | I29: ='Q4 Assumptions'!$G$49*I$12+SUMIFS('Q4 Assumptions'!$C$85:$C$133,'Q4 Assumptions'!$D$85:$D$133,'Q4 Assumptions'!$A$49,'Q4 Assumptions'!$B$85:$B$133,">="&I$10,'Q4 Assumptions'!$B$85:$B$133,"<="&I$11) | J29: ='Q4 Assumptions'!$G$49*J$12+SUMIFS('Q4 Assumptions'!$C$85:$C$133,'Q4 Assumptions'!$D$85:$D$133,'Q4 Assumptions'!$A$49,'Q4 Assumptions'!$B$85:$B$133,">="&J$10,'Q4 Assumptions'!$B$85:$B$133,"<="&J$11) | K29: ='Q4 Assumptions'!$G$49*K$12+SUMIFS('Q4 Assumptions'!$C$85:$C$133,'Q4 Assumptions'!$D$85:$D$133,'Q4 Assumptions'!$A$49,'Q4 Assumptions'!$B$85:$B$133,">="&K$10,'Q4 Assumptions'!$B$85:$B$133,"<="&K$11) | ... Q29: ='Q4 Assumptions'!$G$49*Q$12+SUMIFS('Q4 Assumptions'!$C$85:$C$133,'Q4 Assumptions'!$D$85:$D$133,'Q4 Assumptions'!$A$49,'Q4 Assumptions'!$B$85:$B$133,">="&Q$10,'Q4 Assumptions'!$B$85:$B$133,"<="&Q$11) | R29: =SUM(D29:Q29)
B30: Income taxes | C30: ='Q4 Assumptions'!C50 | D30: ='Q4 Assumptions'!$G$50*D$12+SUMIFS('Q4 Assumptions'!$C$85:$C$133,'Q4 Assumptions'!$D$85:$D$133,'Q4 Assumptions'!$A$50,'Q4 Assumptions'!$B$85:$B$133,">="&D$10,'Q4 Assumptions'!$B$85:$B$133,"<="&D$11) | E30: ='Q4 Assumptions'!$G$50*E$12+SUMIFS('Q4 Assumptions'!$C$85:$C$133,'Q4 Assumptions'!$D$85:$D$133,'Q4 Assumptions'!$A$50,'Q4 Assumptions'!$B$85:$B$133,">="&E$10,'Q4 Assumptions'!$B$85:$B$133,"<="&E$11) | F30: ='Q4 Assumptions'!$G$50*F$12+SUMIFS('Q4 Assumptions'!$C$85:$C$133,'Q4 Assumptions'!$D$85:$D$133,'Q4 Assumptions'!$A$50,'Q4 Assumptions'!$B$85:$B$133,">="&F$10,'Q4 Assumptions'!$B$85:$B$133,"<="&F$11) | G30: ='Q4 Assumptions'!$G$50*G$12+SUMIFS('Q4 Assumptions'!$C$85:$C$133,'Q4 Assumptions'!$D$85:$D$133,'Q4 Assumptions'!$A$50,'Q4 Assumptions'!$B$85:$B$133,">="&G$10,'Q4 Assumptions'!$B$85:$B$133,"<="&G$11) | H30: ='Q4 Assumptions'!$G$50*H$12+SUMIFS('Q4 Assumptions'!$C$85:$C$133,'Q4 Assumptions'!$D$85:$D$133,'Q4 Assumptions'!$A$50,'Q4 Assumptions'!$B$85:$B$133,">="&H$10,'Q4 Assumptions'!$B$85:$B$133,"<="&H$11) | I30: ='Q4 Assumptions'!$G$50*I$12+SUMIFS('Q4 Assumptions'!$C$85:$C$133,'Q4 Assumptions'!$D$85:$D$133,'Q4 Assumptions'!$A$50,'Q4 Assumptions'!$B$85:$B$133,">="&I$10,'Q4 Assumptions'!$B$85:$B$133,"<="&I$11) | J30: ='Q4 Assumptions'!$G$50*J$12+SUMIFS('Q4 Assumptions'!$C$85:$C$133,'Q4 Assumptions'!$D$85:$D$133,'Q4 Assumptions'!$A$50,'Q4 Assumptions'!$B$85:$B$133,">="&J$10,'Q4 Assumptions'!$B$85:$B$133,"<="&J$11) | K30: ='Q4 Assumptions'!$G$50*K$12+SUMIFS('Q4 Assumptions'!$C$85:$C$133,'Q4 Assumptions'!$D$85:$D$133,'Q4 Assumptions'!$A$50,'Q4 Assumptions'!$B$85:$B$133,">="&K$10,'Q4 Assumptions'!$B$85:$B$133,"<="&K$11) | ... Q30: ='Q4 Assumptions'!$G$50*Q$12+SUMIFS('Q4 Assumptions'!$C$85:$C$133,'Q4 Assumptions'!$D$85:$D$133,'Q4 Assumptions'!$A$50,'Q4 Assumptions'!$B$85:$B$133,">="&Q$10,'Q4 Assumptions'!$B$85:$B$133,"<="&Q$11) | R30: =SUM(D30:Q30)
B31: New Branches Expenses | C31: ='Q4 Assumptions'!C51 | D31: ='Q4 Assumptions'!$G$51*D$12+SUMIFS('Q4 Assumptions'!$C$85:$C$133,'Q4 Assumptions'!$D$85:$D$133,'Q4 Assumptions'!$A$51,'Q4 Assumptions'!$B$85:$B$133,">="&D$10,'Q4 Assumptions'!$B$85:$B$133,"<="&D$11) | E31: ='Q4 Assumptions'!$G$51*E$12+SUMIFS('Q4 Assumptions'!$C$85:$C$133,'Q4 Assumptions'!$D$85:$D$133,'Q4 Assumptions'!$A$51,'Q4 Assumptions'!$B$85:$B$133,">="&E$10,'Q4 Assumptions'!$B$85:$B$133,"<="&E$11) | F31: ='Q4 Assumptions'!$G$51*F$12+SUMIFS('Q4 Assumptions'!$C$85:$C$133,'Q4 Assumptions'!$D$85:$D$133,'Q4 Assumptions'!$A$51,'Q4 Assumptions'!$B$85:$B$133,">="&F$10,'Q4 Assumptions'!$B$85:$B$133,"<="&F$11) | G31: ='Q4 Assumptions'!$G$51*G$12+SUMIFS('Q4 Assumptions'!$C$85:$C$133,'Q4 Assumptions'!$D$85:$D$133,'Q4 Assumptions'!$A$51,'Q4 Assumptions'!$B$85:$B$133,">="&G$10,'Q4 Assumptions'!$B$85:$B$133,"<="&G$11) | H31: ='Q4 Assumptions'!$G$51*H$12+SUMIFS('Q4 Assumptions'!$C$85:$C$133,'Q4 Assumptions'!$D$85:$D$133,'Q4 Assumptions'!$A$51,'Q4 Assumptions'!$B$85:$B$133,">="&H$10,'Q4 Assumptions'!$B$85:$B$133,"<="&H$11) | I31: ='Q4 Assumptions'!$G$51*I$12+SUMIFS('Q4 Assumptions'!$C$85:$C$133,'Q4 Assumptions'!$D$85:$D$133,'Q4 Assumptions'!$A$51,'Q4 Assumptions'!$B$85:$B$133,">="&I$10,'Q4 Assumptions'!$B$85:$B$133,"<="&I$11) | J31: ='Q4 Assumptions'!$G$51*J$12+SUMIFS('Q4 Assumptions'!$C$85:$C$133,'Q4 Assumptions'!$D$85:$D$133,'Q4 Assumptions'!$A$51,'Q4 Assumptions'!$B$85:$B$133,">="&J$10,'Q4 Assumptions'!$B$85:$B$133,"<="&J$11) | K31: ='Q4 Assumptions'!$G$51*K$12+SUMIFS('Q4 Assumptions'!$C$85:$C$133,'Q4 Assumptions'!$D$85:$D$133,'Q4 Assumptions'!$A$51,'Q4 Assumptions'!$B$85:$B$133,">="&K$10,'Q4 Assumptions'!$B$85:$B$133,"<="&K$11) | ... Q31: ='Q4 Assumptions'!$G$51*Q$12+SUMIFS('Q4 Assumptions'!$C$85:$C$133,'Q4 Assumptions'!$D$85:$D$133,'Q4 Assumptions'!$A$51,'Q4 Assumptions'!$B$85:$B$133,">="&Q$10,'Q4 Assumptions'!$B$85:$B$133,"<="&Q$11) | R31: =SUM(D31:Q31)
B32: Branch Expenditure & Upkeep | C32: ='Q4 Assumptions'!C52 | D32: ='Q4 Assumptions'!$G$52*D$12+SUMIFS('Q4 Assumptions'!$C$85:$C$133,'Q4 Assumptions'!$D$85:$D$133,'Q4 Assumptions'!$A$52,'Q4 Assumptions'!$B$85:$B$133,">="&D$10,'Q4 Assumptions'!$B$85:$B$133,"<="&D$11)+D86 | E32: ='Q4 Assumptions'!$G$52*E$12+SUMIFS('Q4 Assumptions'!$C$85:$C$133,'Q4 Assumptions'!$D$85:$D$133,'Q4 Assumptions'!$A$52,'Q4 Assumptions'!$B$85:$B$133,">="&E$10,'Q4 Assumptions'!$B$85:$B$133,"<="&E$11)+E86 | F32: ='Q4 Assumptions'!$G$52*F$12+SUMIFS('Q4 Assumptions'!$C$85:$C$133,'Q4 Assumptions'!$D$85:$D$133,'Q4 Assumptions'!$A$52,'Q4 Assumptions'!$B$85:$B$133,">="&F$10,'Q4 Assumptions'!$B$85:$B$133,"<="&F$11)+F86 | G32: ='Q4 Assumptions'!$G$52*G$12+SUMIFS('Q4 Assumptions'!$C$85:$C$133,'Q4 Assumptions'!$D$85:$D$133,'Q4 Assumptions'!$A$52,'Q4 Assumptions'!$B$85:$B$133,">="&G$10,'Q4 Assumptions'!$B$85:$B$133,"<="&G$11)+G86 | H32: ='Q4 Assumptions'!$G$52*H$12+SUMIFS('Q4 Assumptions'!$C$85:$C$133,'Q4 Assumptions'!$D$85:$D$133,'Q4 Assumptions'!$A$52,'Q4 Assumptions'!$B$85:$B$133,">="&H$10,'Q4 Assumptions'!$B$85:$B$133,"<="&H$11)+H86 | I32: ='Q4 Assumptions'!$G$52*I$12+SUMIFS('Q4 Assumptions'!$C$85:$C$133,'Q4 Assumptions'!$D$85:$D$133,'Q4 Assumptions'!$A$52,'Q4 Assumptions'!$B$85:$B$133,">="&I$10,'Q4 Assumptions'!$B$85:$B$133,"<="&I$11)+I86 | J32: ='Q4 Assumptions'!$G$52*J$12+SUMIFS('Q4 Assumptions'!$C$85:$C$133,'Q4 Assumptions'!$D$85:$D$133,'Q4 Assumptions'!$A$52,'Q4 Assumptions'!$B$85:$B$133,">="&J$10,'Q4 Assumptions'!$B$85:$B$133,"<="&J$11)+J86 | K32: ='Q4 Assumptions'!$G$52*K$12+SUMIFS('Q4 Assumptions'!$C$85:$C$133,'Q4 Assumptions'!$D$85:$D$133,'Q4 Assumptions'!$A$52,'Q4 Assumptions'!$B$85:$B$133,">="&K$10,'Q4 Assumptions'!$B$85:$B$133,"<="&K$11)+K86 | ... Q32: ='Q4 Assumptions'!$G$52*Q$12+SUMIFS('Q4 Assumptions'!$C$85:$C$133,'Q4 Assumptions'!$D$85:$D$133,'Q4 Assumptions'!$A$52,'Q4 Assumptions'!$B$85:$B$133,">="&Q$10,'Q4 Assumptions'!$B$85:$B$133,"<="&Q$11)+Q86 | R32: =SUM(D32:Q32)
B33: Credit Card | C33: ='Q4 Assumptions'!C53 | D33: ='Q4 Assumptions'!$G$53*D$12+SUMIFS('Q4 Assumptions'!$C$85:$C$133,'Q4 Assumptions'!$D$85:$D$133,'Q4 Assumptions'!$A$53,'Q4 Assumptions'!$B$85:$B$133,">="&D$10,'Q4 Assumptions'!$B$85:$B$133,"<="&D$11) | E33: ='Q4 Assumptions'!$G$53*E$12+SUMIFS('Q4 Assumptions'!$C$85:$C$133,'Q4 Assumptions'!$D$85:$D$133,'Q4 Assumptions'!$A$53,'Q4 Assumptions'!$B$85:$B$133,">="&E$10,'Q4 Assumptions'!$B$85:$B$133,"<="&E$11) | F33: ='Q4 Assumptions'!$G$53*F$12+SUMIFS('Q4 Assumptions'!$C$85:$C$133,'Q4 Assumptions'!$D$85:$D$133,'Q4 Assumptions'!$A$53,'Q4 Assumptions'!$B$85:$B$133,">="&F$10,'Q4 Assumptions'!$B$85:$B$133,"<="&F$11) | G33: ='Q4 Assumptions'!$G$53*G$12+SUMIFS('Q4 Assumptions'!$C$85:$C$133,'Q4 Assumptions'!$D$85:$D$133,'Q4 Assumptions'!$A$53,'Q4 Assumptions'!$B$85:$B$133,">="&G$10,'Q4 Assumptions'!$B$85:$B$133,"<="&G$11) | H33: ='Q4 Assumptions'!$G$53*H$12+SUMIFS('Q4 Assumptions'!$C$85:$C$133,'Q4 Assumptions'!$D$85:$D$133,'Q4 Assumptions'!$A$53,'Q4 Assumptions'!$B$85:$B$133,">="&H$10,'Q4 Assumptions'!$B$85:$B$133,"<="&H$11) | I33: ='Q4 Assumptions'!$G$53*I$12+SUMIFS('Q4 Assumptions'!$C$85:$C$133,'Q4 Assumptions'!$D$85:$D$133,'Q4 Assumptions'!$A$53,'Q4 Assumptions'!$B$85:$B$133,">="&I$10,'Q4 Assumptions'!$B$85:$B$133,"<="&I$11) | J33: ='Q4 Assumptions'!$G$53*J$12+SUMIFS('Q4 Assumptions'!$C$85:$C$133,'Q4 Assumptions'!$D$85:$D$133,'Q4 Assumptions'!$A$53,'Q4 Assumptions'!$B$85:$B$133,">="&J$10,'Q4 Assumptions'!$B$85:$B$133,"<="&J$11) | K33: ='Q4 Assumptions'!$G$53*K$12+SUMIFS('Q4 Assumptions'!$C$85:$C$133,'Q4 Assumptions'!$D$85:$D$133,'Q4 Assumptions'!$A$53,'Q4 Assumptions'!$B$85:$B$133,">="&K$10,'Q4 Assumptions'!$B$85:$B$133,"<="&K$11) | ... Q33: ='Q4 Assumptions'!$G$53*Q$12+SUMIFS('Q4 Assumptions'!$C$85:$C$133,'Q4 Assumptions'!$D$85:$D$133,'Q4 Assumptions'!$A$53,'Q4 Assumptions'!$B$85:$B$133,">="&Q$10,'Q4 Assumptions'!$B$85:$B$133,"<="&Q$11) | R33: =SUM(D33:Q33)
B34: Open House & Iftar | C34: ='Q4 Assumptions'!C54 | D34: ='Q4 Assumptions'!$G$54*D$12+SUMIFS('Q4 Assumptions'!$C$85:$C$133,'Q4 Assumptions'!$D$85:$D$133,'Q4 Assumptions'!$A$54,'Q4 Assumptions'!$B$85:$B$133,">="&D$10,'Q4 Assumptions'!$B$85:$B$133,"<="&D$11) | E34: ='Q4 Assumptions'!$G$54*E$12+SUMIFS('Q4 Assumptions'!$C$85:$C$133,'Q4 Assumptions'!$D$85:$D$133,'Q4 Assumptions'!$A$54,'Q4 Assumptions'!$B$85:$B$133,">="&E$10,'Q4 Assumptions'!$B$85:$B$133,"<="&E$11) | F34: ='Q4 Assumptions'!$G$54*F$12+SUMIFS('Q4 Assumptions'!$C$85:$C$133,'Q4 Assumptions'!$D$85:$D$133,'Q4 Assumptions'!$A$54,'Q4 Assumptions'!$B$85:$B$133,">="&F$10,'Q4 Assumptions'!$B$85:$B$133,"<="&F$11) | G34: ='Q4 Assumptions'!$G$54*G$12+SUMIFS('Q4 Assumptions'!$C$85:$C$133,'Q4 Assumptions'!$D$85:$D$133,'Q4 Assumptions'!$A$54,'Q4 Assumptions'!$B$85:$B$133,">="&G$10,'Q4 Assumptions'!$B$85:$B$133,"<="&G$11) | H34: ='Q4 Assumptions'!$G$54*H$12+SUMIFS('Q4 Assumptions'!$C$85:$C$133,'Q4 Assumptions'!$D$85:$D$133,'Q4 Assumptions'!$A$54,'Q4 Assumptions'!$B$85:$B$133,">="&H$10,'Q4 Assumptions'!$B$85:$B$133,"<="&H$11) | I34: ='Q4 Assumptions'!$G$54*I$12+SUMIFS('Q4 Assumptions'!$C$85:$C$133,'Q4 Assumptions'!$D$85:$D$133,'Q4 Assumptions'!$A$54,'Q4 Assumptions'!$B$85:$B$133,">="&I$10,'Q4 Assumptions'!$B$85:$B$133,"<="&I$11) | J34: ='Q4 Assumptions'!$G$54*J$12+SUMIFS('Q4 Assumptions'!$C$85:$C$133,'Q4 Assumptions'!$D$85:$D$133,'Q4 Assumptions'!$A$54,'Q4 Assumptions'!$B$85:$B$133,">="&J$10,'Q4 Assumptions'!$B$85:$B$133,"<="&J$11) | K34: ='Q4 Assumptions'!$G$54*K$12+SUMIFS('Q4 Assumptions'!$C$85:$C$133,'Q4 Assumptions'!$D$85:$D$133,'Q4 Assumptions'!$A$54,'Q4 Assumptions'!$B$85:$B$133,">="&K$10,'Q4 Assumptions'!$B$85:$B$133,"<="&K$11) | ... Q34: ='Q4 Assumptions'!$G$54*Q$12+SUMIFS('Q4 Assumptions'!$C$85:$C$133,'Q4 Assumptions'!$D$85:$D$133,'Q4 Assumptions'!$A$54,'Q4 Assumptions'!$B$85:$B$133,">="&Q$10,'Q4 Assumptions'!$B$85:$B$133,"<="&Q$11) | R34: =SUM(D34:Q34)
B35: Co Trip | C35: ='Q4 Assumptions'!C55 | D35: ='Q4 Assumptions'!$G$55*D$12+SUMIFS('Q4 Assumptions'!$C$85:$C$133,'Q4 Assumptions'!$D$85:$D$133,'Q4 Assumptions'!$A$55,'Q4 Assumptions'!$B$85:$B$133,">="&D$10,'Q4 Assumptions'!$B$85:$B$133,"<="&D$11) | E35: ='Q4 Assumptions'!$G$55*E$12+SUMIFS('Q4 Assumptions'!$C$85:$C$133,'Q4 Assumptions'!$D$85:$D$133,'Q4 Assumptions'!$A$55,'Q4 Assumptions'!$B$85:$B$133,">="&E$10,'Q4 Assumptions'!$B$85:$B$133,"<="&E$11) | F35: ='Q4 Assumptions'!$G$55*F$12+SUMIFS('Q4 Assumptions'!$C$85:$C$133,'Q4 Assumptions'!$D$85:$D$133,'Q4 Assumptions'!$A$55,'Q4 Assumptions'!$B$85:$B$133,">="&F$10,'Q4 Assumptions'!$B$85:$B$133,"<="&F$11) | G35: ='Q4 Assumptions'!$G$55*G$12+SUMIFS('Q4 Assumptions'!$C$85:$C$133,'Q4 Assumptions'!$D$85:$D$133,'Q4 Assumptions'!$A$55,'Q4 Assumptions'!$B$85:$B$133,">="&G$10,'Q4 Assumptions'!$B$85:$B$133,"<="&G$11) | H35: ='Q4 Assumptions'!$G$55*H$12+SUMIFS('Q4 Assumptions'!$C$85:$C$133,'Q4 Assumptions'!$D$85:$D$133,'Q4 Assumptions'!$A$55,'Q4 Assumptions'!$B$85:$B$133,">="&H$10,'Q4 Assumptions'!$B$85:$B$133,"<="&H$11) | I35: ='Q4 Assumptions'!$G$55*I$12+SUMIFS('Q4 Assumptions'!$C$85:$C$133,'Q4 Assumptions'!$D$85:$D$133,'Q4 Assumptions'!$A$55,'Q4 Assumptions'!$B$85:$B$133,">="&I$10,'Q4 Assumptions'!$B$85:$B$133,"<="&I$11) | J35: ='Q4 Assumptions'!$G$55*J$12+SUMIFS('Q4 Assumptions'!$C$85:$C$133,'Q4 Assumptions'!$D$85:$D$133,'Q4 Assumptions'!$A$55,'Q4 Assumptions'!$B$85:$B$133,">="&J$10,'Q4 Assumptions'!$B$85:$B$133,"<="&J$11) | K35: ='Q4 Assumptions'!$G$55*K$12+SUMIFS('Q4 Assumptions'!$C$85:$C$133,'Q4 Assumptions'!$D$85:$D$133,'Q4 Assumptions'!$A$55,'Q4 Assumptions'!$B$85:$B$133,">="&K$10,'Q4 Assumptions'!$B$85:$B$133,"<="&K$11) | ... Q35: ='Q4 Assumptions'!$G$55*Q$12+SUMIFS('Q4 Assumptions'!$C$85:$C$133,'Q4 Assumptions'!$D$85:$D$133,'Q4 Assumptions'!$A$55,'Q4 Assumptions'!$B$85:$B$133,">="&Q$10,'Q4 Assumptions'!$B$85:$B$133,"<="&Q$11) | R35: =SUM(D35:Q35)
B36: Utilities | C36: ='Q4 Assumptions'!C56 | D36: ='Q4 Assumptions'!$G$56*D$12+SUMIFS('Q4 Assumptions'!$C$85:$C$133,'Q4 Assumptions'!$D$85:$D$133,'Q4 Assumptions'!$A$56,'Q4 Assumptions'!$B$85:$B$133,">="&D$10,'Q4 Assumptions'!$B$85:$B$133,"<="&D$11) | E36: ='Q4 Assumptions'!$G$56*E$12+SUMIFS('Q4 Assumptions'!$C$85:$C$133,'Q4 Assumptions'!$D$85:$D$133,'Q4 Assumptions'!$A$56,'Q4 Assumptions'!$B$85:$B$133,">="&E$10,'Q4 Assumptions'!$B$85:$B$133,"<="&E$11) | F36: ='Q4 Assumptions'!$G$56*F$12+SUMIFS('Q4 Assumptions'!$C$85:$C$133,'Q4 Assumptions'!$D$85:$D$133,'Q4 Assumptions'!$A$56,'Q4 Assumptions'!$B$85:$B$133,">="&F$10,'Q4 Assumptions'!$B$85:$B$133,"<="&F$11) | G36: ='Q4 Assumptions'!$G$56*G$12+SUMIFS('Q4 Assumptions'!$C$85:$C$133,'Q4 Assumptions'!$D$85:$D$133,'Q4 Assumptions'!$A$56,'Q4 Assumptions'!$B$85:$B$133,">="&G$10,'Q4 Assumptions'!$B$85:$B$133,"<="&G$11) | H36: ='Q4 Assumptions'!$G$56*H$12+SUMIFS('Q4 Assumptions'!$C$85:$C$133,'Q4 Assumptions'!$D$85:$D$133,'Q4 Assumptions'!$A$56,'Q4 Assumptions'!$B$85:$B$133,">="&H$10,'Q4 Assumptions'!$B$85:$B$133,"<="&H$11) | I36: ='Q4 Assumptions'!$G$56*I$12+SUMIFS('Q4 Assumptions'!$C$85:$C$133,'Q4 Assumptions'!$D$85:$D$133,'Q4 Assumptions'!$A$56,'Q4 Assumptions'!$B$85:$B$133,">="&I$10,'Q4 Assumptions'!$B$85:$B$133,"<="&I$11) | J36: ='Q4 Assumptions'!$G$56*J$12+SUMIFS('Q4 Assumptions'!$C$85:$C$133,'Q4 Assumptions'!$D$85:$D$133,'Q4 Assumptions'!$A$56,'Q4 Assumptions'!$B$85:$B$133,">="&J$10,'Q4 Assumptions'!$B$85:$B$133,"<="&J$11) | K36: ='Q4 Assumptions'!$G$56*K$12+SUMIFS('Q4 Assumptions'!$C$85:$C$133,'Q4 Assumptions'!$D$85:$D$133,'Q4 Assumptions'!$A$56,'Q4 Assumptions'!$B$85:$B$133,">="&K$10,'Q4 Assumptions'!$B$85:$B$133,"<="&K$11) | ... Q36: ='Q4 Assumptions'!$G$56*Q$12+SUMIFS('Q4 Assumptions'!$C$85:$C$133,'Q4 Assumptions'!$D$85:$D$133,'Q4 Assumptions'!$A$56,'Q4 Assumptions'!$B$85:$B$133,">="&Q$10,'Q4 Assumptions'!$B$85:$B$133,"<="&Q$11) | R36: =SUM(D36:Q36)
B37: Rental | C37: ='Q4 Assumptions'!C57 | D37: ='Q4 Assumptions'!$G$57*D$12+SUMIFS('Q4 Assumptions'!$C$85:$C$133,'Q4 Assumptions'!$D$85:$D$133,'Q4 Assumptions'!$A$57,'Q4 Assumptions'!$B$85:$B$133,">="&D$10,'Q4 Assumptions'!$B$85:$B$133,"<="&D$11)+D88 | E37: ='Q4 Assumptions'!$G$57*E$12+SUMIFS('Q4 Assumptions'!$C$85:$C$133,'Q4 Assumptions'!$D$85:$D$133,'Q4 Assumptions'!$A$57,'Q4 Assumptions'!$B$85:$B$133,">="&E$10,'Q4 Assumptions'!$B$85:$B$133,"<="&E$11)+E88 | F37: ='Q4 Assumptions'!$G$57*F$12+SUMIFS('Q4 Assumptions'!$C$85:$C$133,'Q4 Assumptions'!$D$85:$D$133,'Q4 Assumptions'!$A$57,'Q4 Assumptions'!$B$85:$B$133,">="&F$10,'Q4 Assumptions'!$B$85:$B$133,"<="&F$11)+F88 | G37: ='Q4 Assumptions'!$G$57*G$12+SUMIFS('Q4 Assumptions'!$C$85:$C$133,'Q4 Assumptions'!$D$85:$D$133,'Q4 Assumptions'!$A$57,'Q4 Assumptions'!$B$85:$B$133,">="&G$10,'Q4 Assumptions'!$B$85:$B$133,"<="&G$11)+G88 | H37: ='Q4 Assumptions'!$G$57*H$12+SUMIFS('Q4 Assumptions'!$C$85:$C$133,'Q4 Assumptions'!$D$85:$D$133,'Q4 Assumptions'!$A$57,'Q4 Assumptions'!$B$85:$B$133,">="&H$10,'Q4 Assumptions'!$B$85:$B$133,"<="&H$11)+H88 | I37: ='Q4 Assumptions'!$G$57*I$12+SUMIFS('Q4 Assumptions'!$C$85:$C$133,'Q4 Assumptions'!$D$85:$D$133,'Q4 Assumptions'!$A$57,'Q4 Assumptions'!$B$85:$B$133,">="&I$10,'Q4 Assumptions'!$B$85:$B$133,"<="&I$11)+I88 | J37: ='Q4 Assumptions'!$G$57*J$12+SUMIFS('Q4 Assumptions'!$C$85:$C$133,'Q4 Assumptions'!$D$85:$D$133,'Q4 Assumptions'!$A$57,'Q4 Assumptions'!$B$85:$B$133,">="&J$10,'Q4 Assumptions'!$B$85:$B$133,"<="&J$11)+J88 | K37: ='Q4 Assumptions'!$G$57*K$12+SUMIFS('Q4 Assumptions'!$C$85:$C$133,'Q4 Assumptions'!$D$85:$D$133,'Q4 Assumptions'!$A$57,'Q4 Assumptions'!$B$85:$B$133,">="&K$10,'Q4 Assumptions'!$B$85:$B$133,"<="&K$11)+K88 | ... Q37: ='Q4 Assumptions'!$G$57*Q$12+SUMIFS('Q4 Assumptions'!$C$85:$C$133,'Q4 Assumptions'!$D$85:$D$133,'Q4 Assumptions'!$A$57,'Q4 Assumptions'!$B$85:$B$133,">="&Q$10,'Q4 Assumptions'!$B$85:$B$133,"<="&Q$11)+Q88 | R37: =SUM(D37:Q37)
B38: Sponsorship | C38: ='Q4 Assumptions'!C58 | D38: ='Q4 Assumptions'!$G$58*D$12+SUMIFS('Q4 Assumptions'!$C$85:$C$133,'Q4 Assumptions'!$D$85:$D$133,'Q4 Assumptions'!$A$58,'Q4 Assumptions'!$B$85:$B$133,">="&D$10,'Q4 Assumptions'!$B$85:$B$133,"<="&D$11) | E38: ='Q4 Assumptions'!$G$58*E$12+SUMIFS('Q4 Assumptions'!$C$85:$C$133,'Q4 Assumptions'!$D$85:$D$133,'Q4 Assumptions'!$A$58,'Q4 Assumptions'!$B$85:$B$133,">="&E$10,'Q4 Assumptions'!$B$85:$B$133,"<="&E$11) | F38: ='Q4 Assumptions'!$G$58*F$12+SUMIFS('Q4 Assumptions'!$C$85:$C$133,'Q4 Assumptions'!$D$85:$D$133,'Q4 Assumptions'!$A$58,'Q4 Assumptions'!$B$85:$B$133,">="&F$10,'Q4 Assumptions'!$B$85:$B$133,"<="&F$11) | G38: ='Q4 Assumptions'!$G$58*G$12+SUMIFS('Q4 Assumptions'!$C$85:$C$133,'Q4 Assumptions'!$D$85:$D$133,'Q4 Assumptions'!$A$58,'Q4 Assumptions'!$B$85:$B$133,">="&G$10,'Q4 Assumptions'!$B$85:$B$133,"<="&G$11) | H38: ='Q4 Assumptions'!$G$58*H$12+SUMIFS('Q4 Assumptions'!$C$85:$C$133,'Q4 Assumptions'!$D$85:$D$133,'Q4 Assumptions'!$A$58,'Q4 Assumptions'!$B$85:$B$133,">="&H$10,'Q4 Assumptions'!$B$85:$B$133,"<="&H$11) | I38: ='Q4 Assumptions'!$G$58*I$12+SUMIFS('Q4 Assumptions'!$C$85:$C$133,'Q4 Assumptions'!$D$85:$D$133,'Q4 Assumptions'!$A$58,'Q4 Assumptions'!$B$85:$B$133,">="&I$10,'Q4 Assumptions'!$B$85:$B$133,"<="&I$11) | J38: ='Q4 Assumptions'!$G$58*J$12+SUMIFS('Q4 Assumptions'!$C$85:$C$133,'Q4 Assumptions'!$D$85:$D$133,'Q4 Assumptions'!$A$58,'Q4 Assumptions'!$B$85:$B$133,">="&J$10,'Q4 Assumptions'!$B$85:$B$133,"<="&J$11) | K38: ='Q4 Assumptions'!$G$58*K$12+SUMIFS('Q4 Assumptions'!$C$85:$C$133,'Q4 Assumptions'!$D$85:$D$133,'Q4 Assumptions'!$A$58,'Q4 Assumptions'!$B$85:$B$133,">="&K$10,'Q4 Assumptions'!$B$85:$B$133,"<="&K$11) | ... Q38: ='Q4 Assumptions'!$G$58*Q$12+SUMIFS('Q4 Assumptions'!$C$85:$C$133,'Q4 Assumptions'!$D$85:$D$133,'Q4 Assumptions'!$A$58,'Q4 Assumptions'!$B$85:$B$133,">="&Q$10,'Q4 Assumptions'!$B$85:$B$133,"<="&Q$11) | R38: =SUM(D38:Q38)
B39: SST | C39: ='Q4 Assumptions'!C59 | D39: ='Q4 Assumptions'!$G$59*D$12+SUMIFS('Q4 Assumptions'!$C$85:$C$133,'Q4 Assumptions'!$D$85:$D$133,'Q4 Assumptions'!$A$59,'Q4 Assumptions'!$B$85:$B$133,">="&D$10,'Q4 Assumptions'!$B$85:$B$133,"<="&D$11) | E39: ='Q4 Assumptions'!$G$59*E$12+SUMIFS('Q4 Assumptions'!$C$85:$C$133,'Q4 Assumptions'!$D$85:$D$133,'Q4 Assumptions'!$A$59,'Q4 Assumptions'!$B$85:$B$133,">="&E$10,'Q4 Assumptions'!$B$85:$B$133,"<="&E$11) | F39: ='Q4 Assumptions'!$G$59*F$12+SUMIFS('Q4 Assumptions'!$C$85:$C$133,'Q4 Assumptions'!$D$85:$D$133,'Q4 Assumptions'!$A$59,'Q4 Assumptions'!$B$85:$B$133,">="&F$10,'Q4 Assumptions'!$B$85:$B$133,"<="&F$11) | G39: ='Q4 Assumptions'!$G$59*G$12+SUMIFS('Q4 Assumptions'!$C$85:$C$133,'Q4 Assumptions'!$D$85:$D$133,'Q4 Assumptions'!$A$59,'Q4 Assumptions'!$B$85:$B$133,">="&G$10,'Q4 Assumptions'!$B$85:$B$133,"<="&G$11) | H39: ='Q4 Assumptions'!$G$59*H$12+SUMIFS('Q4 Assumptions'!$C$85:$C$133,'Q4 Assumptions'!$D$85:$D$133,'Q4 Assumptions'!$A$59,'Q4 Assumptions'!$B$85:$B$133,">="&H$10,'Q4 Assumptions'!$B$85:$B$133,"<="&H$11) | I39: ='Q4 Assumptions'!$G$59*I$12+SUMIFS('Q4 Assumptions'!$C$85:$C$133,'Q4 Assumptions'!$D$85:$D$133,'Q4 Assumptions'!$A$59,'Q4 Assumptions'!$B$85:$B$133,">="&I$10,'Q4 Assumptions'!$B$85:$B$133,"<="&I$11) | J39: ='Q4 Assumptions'!$G$59*J$12+SUMIFS('Q4 Assumptions'!$C$85:$C$133,'Q4 Assumptions'!$D$85:$D$133,'Q4 Assumptions'!$A$59,'Q4 Assumptions'!$B$85:$B$133,">="&J$10,'Q4 Assumptions'!$B$85:$B$133,"<="&J$11) | K39: ='Q4 Assumptions'!$G$59*K$12+SUMIFS('Q4 Assumptions'!$C$85:$C$133,'Q4 Assumptions'!$D$85:$D$133,'Q4 Assumptions'!$A$59,'Q4 Assumptions'!$B$85:$B$133,">="&K$10,'Q4 Assumptions'!$B$85:$B$133,"<="&K$11) | ... Q39: ='Q4 Assumptions'!$G$59*Q$12+SUMIFS('Q4 Assumptions'!$C$85:$C$133,'Q4 Assumptions'!$D$85:$D$133,'Q4 Assumptions'!$A$59,'Q4 Assumptions'!$B$85:$B$133,">="&Q$10,'Q4 Assumptions'!$B$85:$B$133,"<="&Q$11) | R39: =SUM(D39:Q39)
B40: Donation | C40: ='Q4 Assumptions'!C60 | D40: ='Q4 Assumptions'!$G$60*D$12+SUMIFS('Q4 Assumptions'!$C$85:$C$133,'Q4 Assumptions'!$D$85:$D$133,'Q4 Assumptions'!$A$60,'Q4 Assumptions'!$B$85:$B$133,">="&D$10,'Q4 Assumptions'!$B$85:$B$133,"<="&D$11) | E40: ='Q4 Assumptions'!$G$60*E$12+SUMIFS('Q4 Assumptions'!$C$85:$C$133,'Q4 Assumptions'!$D$85:$D$133,'Q4 Assumptions'!$A$60,'Q4 Assumptions'!$B$85:$B$133,">="&E$10,'Q4 Assumptions'!$B$85:$B$133,"<="&E$11) | F40: ='Q4 Assumptions'!$G$60*F$12+SUMIFS('Q4 Assumptions'!$C$85:$C$133,'Q4 Assumptions'!$D$85:$D$133,'Q4 Assumptions'!$A$60,'Q4 Assumptions'!$B$85:$B$133,">="&F$10,'Q4 Assumptions'!$B$85:$B$133,"<="&F$11) | G40: ='Q4 Assumptions'!$G$60*G$12+SUMIFS('Q4 Assumptions'!$C$85:$C$133,'Q4 Assumptions'!$D$85:$D$133,'Q4 Assumptions'!$A$60,'Q4 Assumptions'!$B$85:$B$133,">="&G$10,'Q4 Assumptions'!$B$85:$B$133,"<="&G$11) | H40: ='Q4 Assumptions'!$G$60*H$12+SUMIFS('Q4 Assumptions'!$C$85:$C$133,'Q4 Assumptions'!$D$85:$D$133,'Q4 Assumptions'!$A$60,'Q4 Assumptions'!$B$85:$B$133,">="&H$10,'Q4 Assumptions'!$B$85:$B$133,"<="&H$11) | I40: ='Q4 Assumptions'!$G$60*I$12+SUMIFS('Q4 Assumptions'!$C$85:$C$133,'Q4 Assumptions'!$D$85:$D$133,'Q4 Assumptions'!$A$60,'Q4 Assumptions'!$B$85:$B$133,">="&I$10,'Q4 Assumptions'!$B$85:$B$133,"<="&I$11) | J40: ='Q4 Assumptions'!$G$60*J$12+SUMIFS('Q4 Assumptions'!$C$85:$C$133,'Q4 Assumptions'!$D$85:$D$133,'Q4 Assumptions'!$A$60,'Q4 Assumptions'!$B$85:$B$133,">="&J$10,'Q4 Assumptions'!$B$85:$B$133,"<="&J$11) | K40: ='Q4 Assumptions'!$G$60*K$12+SUMIFS('Q4 Assumptions'!$C$85:$C$133,'Q4 Assumptions'!$D$85:$D$133,'Q4 Assumptions'!$A$60,'Q4 Assumptions'!$B$85:$B$133,">="&K$10,'Q4 Assumptions'!$B$85:$B$133,"<="&K$11) | ... Q40: ='Q4 Assumptions'!$G$60*Q$12+SUMIFS('Q4 Assumptions'!$C$85:$C$133,'Q4 Assumptions'!$D$85:$D$133,'Q4 Assumptions'!$A$60,'Q4 Assumptions'!$B$85:$B$133,">="&Q$10,'Q4 Assumptions'!$B$85:$B$133,"<="&Q$11) | R40: =SUM(D40:Q40)
A41: Net Cash Flow from Operations | C41: =C14+C15+C16+C17+C18+C21+C22+C23+C24+C25+C26+C27+C28+C29+C30+C31+C32+C33+C34+C35+C36+C37+C38+C39+C40 | D41: =D14+D15+D16+D17+D18+D21+D22+D23+D24+D25+D26+D27+D28+D29+D30+D31+D32+D33+D34+D35+D36+D37+D38+D39+D40 | E41: =E14+E15+E16+E17+E18+E21+E22+E23+E24+E25+E26+E27+E28+E29+E30+E31+E32+E33+E34+E35+E36+E37+E38+E39+E40 | F41: =F14+F15+F16+F17+F18+F21+F22+F23+F24+F25+F26+F27+F28+F29+F30+F31+F32+F33+F34+F35+F36+F37+F38+F39+F40 | G41: =G14+G15+G16+G17+G18+G21+G22+G23+G24+G25+G26+G27+G28+G29+G30+G31+G32+G33+G34+G35+G36+G37+G38+G39+G40 | H41: =H14+H15+H16+H17+H18+H21+H22+H23+H24+H25+H26+H27+H28+H29+H30+H31+H32+H33+H34+H35+H36+H37+H38+H39+H40 | I41: =I14+I15+I16+I17+I18+I21+I22+I23+I24+I25+I26+I27+I28+I29+I30+I31+I32+I33+I34+I35+I36+I37+I38+I39+I40 | J41: =J14+J15+J16+J17+J18+J21+J22+J23+J24+J25+J26+J27+J28+J29+J30+J31+J32+J33+J34+J35+J36+J37+J38+J39+J40 | ... R41: =R14+R15+R16+R17+R18+R21+R22+R23+R24+R25+R26+R27+R28+R29+R30+R31+R32+R33+R34+R35+R36+R37+R38+R39+R40
A44: Investing Activities
A45: Cash receipts from
B46: Proceeds from sale of equipment | C46: ='Q4 Assumptions'!C61 | D46: ='Q4 Assumptions'!$G$61*D$12+SUMIFS('Q4 Assumptions'!$C$85:$C$133,'Q4 Assumptions'!$D$85:$D$133,'Q4 Assumptions'!$A$61,'Q4 Assumptions'!$B$85:$B$133,">="&D$10,'Q4 Assumptions'!$B$85:$B$133,"<="&D$11) | E46: ='Q4 Assumptions'!$G$61*E$12+SUMIFS('Q4 Assumptions'!$C$85:$C$133,'Q4 Assumptions'!$D$85:$D$133,'Q4 Assumptions'!$A$61,'Q4 Assumptions'!$B$85:$B$133,">="&E$10,'Q4 Assumptions'!$B$85:$B$133,"<="&E$11) | F46: ='Q4 Assumptions'!$G$61*F$12+SUMIFS('Q4 Assumptions'!$C$85:$C$133,'Q4 Assumptions'!$D$85:$D$133,'Q4 Assumptions'!$A$61,'Q4 Assumptions'!$B$85:$B$133,">="&F$10,'Q4 Assumptions'!$B$85:$B$133,"<="&F$11) | G46: ='Q4 Assumptions'!$G$61*G$12+SUMIFS('Q4 Assumptions'!$C$85:$C$133,'Q4 Assumptions'!$D$85:$D$133,'Q4 Assumptions'!$A$61,'Q4 Assumptions'!$B$85:$B$133,">="&G$10,'Q4 Assumptions'!$B$85:$B$133,"<="&G$11) | H46: ='Q4 Assumptions'!$G$61*H$12+SUMIFS('Q4 Assumptions'!$C$85:$C$133,'Q4 Assumptions'!$D$85:$D$133,'Q4 Assumptions'!$A$61,'Q4 Assumptions'!$B$85:$B$133,">="&H$10,'Q4 Assumptions'!$B$85:$B$133,"<="&H$11) | I46: ='Q4 Assumptions'!$G$61*I$12+SUMIFS('Q4 Assumptions'!$C$85:$C$133,'Q4 Assumptions'!$D$85:$D$133,'Q4 Assumptions'!$A$61,'Q4 Assumptions'!$B$85:$B$133,">="&I$10,'Q4 Assumptions'!$B$85:$B$133,"<="&I$11) | J46: ='Q4 Assumptions'!$G$61*J$12+SUMIFS('Q4 Assumptions'!$C$85:$C$133,'Q4 Assumptions'!$D$85:$D$133,'Q4 Assumptions'!$A$61,'Q4 Assumptions'!$B$85:$B$133,">="&J$10,'Q4 Assumptions'!$B$85:$B$133,"<="&J$11) | K46: ='Q4 Assumptions'!$G$61*K$12+SUMIFS('Q4 Assumptions'!$C$85:$C$133,'Q4 Assumptions'!$D$85:$D$133,'Q4 Assumptions'!$A$61,'Q4 Assumptions'!$B$85:$B$133,">="&K$10,'Q4 Assumptions'!$B$85:$B$133,"<="&K$11) | ... Q46: ='Q4 Assumptions'!$G$61*Q$12+SUMIFS('Q4 Assumptions'!$C$85:$C$133,'Q4 Assumptions'!$D$85:$D$133,'Q4 Assumptions'!$A$61,'Q4 Assumptions'!$B$85:$B$133,">="&Q$10,'Q4 Assumptions'!$B$85:$B$133,"<="&Q$11) | R46: =SUM(D46:Q46)
B47: Proceeds from sale of motor vehicle | C47: ='Q4 Assumptions'!C62 | D47: ='Q4 Assumptions'!$G$62*D$12+SUMIFS('Q4 Assumptions'!$C$85:$C$133,'Q4 Assumptions'!$D$85:$D$133,'Q4 Assumptions'!$A$62,'Q4 Assumptions'!$B$85:$B$133,">="&D$10,'Q4 Assumptions'!$B$85:$B$133,"<="&D$11) | E47: ='Q4 Assumptions'!$G$62*E$12+SUMIFS('Q4 Assumptions'!$C$85:$C$133,'Q4 Assumptions'!$D$85:$D$133,'Q4 Assumptions'!$A$62,'Q4 Assumptions'!$B$85:$B$133,">="&E$10,'Q4 Assumptions'!$B$85:$B$133,"<="&E$11) | F47: ='Q4 Assumptions'!$G$62*F$12+SUMIFS('Q4 Assumptions'!$C$85:$C$133,'Q4 Assumptions'!$D$85:$D$133,'Q4 Assumptions'!$A$62,'Q4 Assumptions'!$B$85:$B$133,">="&F$10,'Q4 Assumptions'!$B$85:$B$133,"<="&F$11) | G47: ='Q4 Assumptions'!$G$62*G$12+SUMIFS('Q4 Assumptions'!$C$85:$C$133,'Q4 Assumptions'!$D$85:$D$133,'Q4 Assumptions'!$A$62,'Q4 Assumptions'!$B$85:$B$133,">="&G$10,'Q4 Assumptions'!$B$85:$B$133,"<="&G$11) | H47: ='Q4 Assumptions'!$G$62*H$12+SUMIFS('Q4 Assumptions'!$C$85:$C$133,'Q4 Assumptions'!$D$85:$D$133,'Q4 Assumptions'!$A$62,'Q4 Assumptions'!$B$85:$B$133,">="&H$10,'Q4 Assumptions'!$B$85:$B$133,"<="&H$11) | I47: ='Q4 Assumptions'!$G$62*I$12+SUMIFS('Q4 Assumptions'!$C$85:$C$133,'Q4 Assumptions'!$D$85:$D$133,'Q4 Assumptions'!$A$62,'Q4 Assumptions'!$B$85:$B$133,">="&I$10,'Q4 Assumptions'!$B$85:$B$133,"<="&I$11) | J47: ='Q4 Assumptions'!$G$62*J$12+SUMIFS('Q4 Assumptions'!$C$85:$C$133,'Q4 Assumptions'!$D$85:$D$133,'Q4 Assumptions'!$A$62,'Q4 Assumptions'!$B$85:$B$133,">="&J$10,'Q4 Assumptions'!$B$85:$B$133,"<="&J$11) | K47: ='Q4 Assumptions'!$G$62*K$12+SUMIFS('Q4 Assumptions'!$C$85:$C$133,'Q4 Assumptions'!$D$85:$D$133,'Q4 Assumptions'!$A$62,'Q4 Assumptions'!$B$85:$B$133,">="&K$10,'Q4 Assumptions'!$B$85:$B$133,"<="&K$11) | ... Q47: ='Q4 Assumptions'!$G$62*Q$12+SUMIFS('Q4 Assumptions'!$C$85:$C$133,'Q4 Assumptions'!$D$85:$D$133,'Q4 Assumptions'!$A$62,'Q4 Assumptions'!$B$85:$B$133,">="&Q$10,'Q4 Assumptions'!$B$85:$B$133,"<="&Q$11) | R47: =SUM(D47:Q47)
B48: Collection of Investor funds | C48: ='Q4 Assumptions'!C63 | D48: ='Q4 Assumptions'!$G$63*D$12+SUMIFS('Q4 Assumptions'!$C$85:$C$133,'Q4 Assumptions'!$D$85:$D$133,'Q4 Assumptions'!$A$63,'Q4 Assumptions'!$B$85:$B$133,">="&D$10,'Q4 Assumptions'!$B$85:$B$133,"<="&D$11) | E48: ='Q4 Assumptions'!$G$63*E$12+SUMIFS('Q4 Assumptions'!$C$85:$C$133,'Q4 Assumptions'!$D$85:$D$133,'Q4 Assumptions'!$A$63,'Q4 Assumptions'!$B$85:$B$133,">="&E$10,'Q4 Assumptions'!$B$85:$B$133,"<="&E$11) | F48: ='Q4 Assumptions'!$G$63*F$12+SUMIFS('Q4 Assumptions'!$C$85:$C$133,'Q4 Assumptions'!$D$85:$D$133,'Q4 Assumptions'!$A$63,'Q4 Assumptions'!$B$85:$B$133,">="&F$10,'Q4 Assumptions'!$B$85:$B$133,"<="&F$11) | G48: ='Q4 Assumptions'!$G$63*G$12+SUMIFS('Q4 Assumptions'!$C$85:$C$133,'Q4 Assumptions'!$D$85:$D$133,'Q4 Assumptions'!$A$63,'Q4 Assumptions'!$B$85:$B$133,">="&G$10,'Q4 Assumptions'!$B$85:$B$133,"<="&G$11) | H48: ='Q4 Assumptions'!$G$63*H$12+SUMIFS('Q4 Assumptions'!$C$85:$C$133,'Q4 Assumptions'!$D$85:$D$133,'Q4 Assumptions'!$A$63,'Q4 Assumptions'!$B$85:$B$133,">="&H$10,'Q4 Assumptions'!$B$85:$B$133,"<="&H$11) | I48: ='Q4 Assumptions'!$G$63*I$12+SUMIFS('Q4 Assumptions'!$C$85:$C$133,'Q4 Assumptions'!$D$85:$D$133,'Q4 Assumptions'!$A$63,'Q4 Assumptions'!$B$85:$B$133,">="&I$10,'Q4 Assumptions'!$B$85:$B$133,"<="&I$11) | J48: ='Q4 Assumptions'!$G$63*J$12+SUMIFS('Q4 Assumptions'!$C$85:$C$133,'Q4 Assumptions'!$D$85:$D$133,'Q4 Assumptions'!$A$63,'Q4 Assumptions'!$B$85:$B$133,">="&J$10,'Q4 Assumptions'!$B$85:$B$133,"<="&J$11) | K48: ='Q4 Assumptions'!$G$63*K$12+SUMIFS('Q4 Assumptions'!$C$85:$C$133,'Q4 Assumptions'!$D$85:$D$133,'Q4 Assumptions'!$A$63,'Q4 Assumptions'!$B$85:$B$133,">="&K$10,'Q4 Assumptions'!$B$85:$B$133,"<="&K$11) | ... Q48: ='Q4 Assumptions'!$G$63*Q$12+SUMIFS('Q4 Assumptions'!$C$85:$C$133,'Q4 Assumptions'!$D$85:$D$133,'Q4 Assumptions'!$A$63,'Q4 Assumptions'!$B$85:$B$133,">="&Q$10,'Q4 Assumptions'!$B$85:$B$133,"<="&Q$11) | R48: =SUM(D48:Q48)
B49: Interest received from Maybank pooled | C49: ='Q4 Assumptions'!C64 | D49: ='Q4 Assumptions'!$G$64*D$12+SUMIFS('Q4 Assumptions'!$C$85:$C$133,'Q4 Assumptions'!$D$85:$D$133,'Q4 Assumptions'!$A$64,'Q4 Assumptions'!$B$85:$B$133,">="&D$10,'Q4 Assumptions'!$B$85:$B$133,"<="&D$11) | E49: ='Q4 Assumptions'!$G$64*E$12+SUMIFS('Q4 Assumptions'!$C$85:$C$133,'Q4 Assumptions'!$D$85:$D$133,'Q4 Assumptions'!$A$64,'Q4 Assumptions'!$B$85:$B$133,">="&E$10,'Q4 Assumptions'!$B$85:$B$133,"<="&E$11) | F49: ='Q4 Assumptions'!$G$64*F$12+SUMIFS('Q4 Assumptions'!$C$85:$C$133,'Q4 Assumptions'!$D$85:$D$133,'Q4 Assumptions'!$A$64,'Q4 Assumptions'!$B$85:$B$133,">="&F$10,'Q4 Assumptions'!$B$85:$B$133,"<="&F$11) | G49: ='Q4 Assumptions'!$G$64*G$12+SUMIFS('Q4 Assumptions'!$C$85:$C$133,'Q4 Assumptions'!$D$85:$D$133,'Q4 Assumptions'!$A$64,'Q4 Assumptions'!$B$85:$B$133,">="&G$10,'Q4 Assumptions'!$B$85:$B$133,"<="&G$11) | H49: ='Q4 Assumptions'!$G$64*H$12+SUMIFS('Q4 Assumptions'!$C$85:$C$133,'Q4 Assumptions'!$D$85:$D$133,'Q4 Assumptions'!$A$64,'Q4 Assumptions'!$B$85:$B$133,">="&H$10,'Q4 Assumptions'!$B$85:$B$133,"<="&H$11) | I49: ='Q4 Assumptions'!$G$64*I$12+SUMIFS('Q4 Assumptions'!$C$85:$C$133,'Q4 Assumptions'!$D$85:$D$133,'Q4 Assumptions'!$A$64,'Q4 Assumptions'!$B$85:$B$133,">="&I$10,'Q4 Assumptions'!$B$85:$B$133,"<="&I$11) | J49: ='Q4 Assumptions'!$G$64*J$12+SUMIFS('Q4 Assumptions'!$C$85:$C$133,'Q4 Assumptions'!$D$85:$D$133,'Q4 Assumptions'!$A$64,'Q4 Assumptions'!$B$85:$B$133,">="&J$10,'Q4 Assumptions'!$B$85:$B$133,"<="&J$11) | K49: ='Q4 Assumptions'!$G$64*K$12+SUMIFS('Q4 Assumptions'!$C$85:$C$133,'Q4 Assumptions'!$D$85:$D$133,'Q4 Assumptions'!$A$64,'Q4 Assumptions'!$B$85:$B$133,">="&K$10,'Q4 Assumptions'!$B$85:$B$133,"<="&K$11) | ... Q49: ='Q4 Assumptions'!$G$64*Q$12+SUMIFS('Q4 Assumptions'!$C$85:$C$133,'Q4 Assumptions'!$D$85:$D$133,'Q4 Assumptions'!$A$64,'Q4 Assumptions'!$B$85:$B$133,">="&Q$10,'Q4 Assumptions'!$B$85:$B$133,"<="&Q$11) | R49: =SUM(D49:Q49)
B50: Sale of investment securities | C50: ='Q4 Assumptions'!C65 | D50: ='Q4 Assumptions'!$G$65*D$12+SUMIFS('Q4 Assumptions'!$C$85:$C$133,'Q4 Assumptions'!$D$85:$D$133,'Q4 Assumptions'!$A$65,'Q4 Assumptions'!$B$85:$B$133,">="&D$10,'Q4 Assumptions'!$B$85:$B$133,"<="&D$11) | E50: ='Q4 Assumptions'!$G$65*E$12+SUMIFS('Q4 Assumptions'!$C$85:$C$133,'Q4 Assumptions'!$D$85:$D$133,'Q4 Assumptions'!$A$65,'Q4 Assumptions'!$B$85:$B$133,">="&E$10,'Q4 Assumptions'!$B$85:$B$133,"<="&E$11) | F50: ='Q4 Assumptions'!$G$65*F$12+SUMIFS('Q4 Assumptions'!$C$85:$C$133,'Q4 Assumptions'!$D$85:$D$133,'Q4 Assumptions'!$A$65,'Q4 Assumptions'!$B$85:$B$133,">="&F$10,'Q4 Assumptions'!$B$85:$B$133,"<="&F$11) | G50: ='Q4 Assumptions'!$G$65*G$12+SUMIFS('Q4 Assumptions'!$C$85:$C$133,'Q4 Assumptions'!$D$85:$D$133,'Q4 Assumptions'!$A$65,'Q4 Assumptions'!$B$85:$B$133,">="&G$10,'Q4 Assumptions'!$B$85:$B$133,"<="&G$11) | H50: ='Q4 Assumptions'!$G$65*H$12+SUMIFS('Q4 Assumptions'!$C$85:$C$133,'Q4 Assumptions'!$D$85:$D$133,'Q4 Assumptions'!$A$65,'Q4 Assumptions'!$B$85:$B$133,">="&H$10,'Q4 Assumptions'!$B$85:$B$133,"<="&H$11) | I50: ='Q4 Assumptions'!$G$65*I$12+SUMIFS('Q4 Assumptions'!$C$85:$C$133,'Q4 Assumptions'!$D$85:$D$133,'Q4 Assumptions'!$A$65,'Q4 Assumptions'!$B$85:$B$133,">="&I$10,'Q4 Assumptions'!$B$85:$B$133,"<="&I$11) | J50: ='Q4 Assumptions'!$G$65*J$12+SUMIFS('Q4 Assumptions'!$C$85:$C$133,'Q4 Assumptions'!$D$85:$D$133,'Q4 Assumptions'!$A$65,'Q4 Assumptions'!$B$85:$B$133,">="&J$10,'Q4 Assumptions'!$B$85:$B$133,"<="&J$11) | K50: ='Q4 Assumptions'!$G$65*K$12+SUMIFS('Q4 Assumptions'!$C$85:$C$133,'Q4 Assumptions'!$D$85:$D$133,'Q4 Assumptions'!$A$65,'Q4 Assumptions'!$B$85:$B$133,">="&K$10,'Q4 Assumptions'!$B$85:$B$133,"<="&K$11) | ... Q50: ='Q4 Assumptions'!$G$65*Q$12+SUMIFS('Q4 Assumptions'!$C$85:$C$133,'Q4 Assumptions'!$D$85:$D$133,'Q4 Assumptions'!$A$65,'Q4 Assumptions'!$B$85:$B$133,">="&Q$10,'Q4 Assumptions'!$B$85:$B$133,"<="&Q$11) | R50: =SUM(D50:Q50)
A51: Cash paid for
B52: Purchase of property and equipment | C52: ='Q4 Assumptions'!C66 | D52: ='Q4 Assumptions'!$G$66*D$12+SUMIFS('Q4 Assumptions'!$C$85:$C$133,'Q4 Assumptions'!$D$85:$D$133,'Q4 Assumptions'!$A$66,'Q4 Assumptions'!$B$85:$B$133,">="&D$10,'Q4 Assumptions'!$B$85:$B$133,"<="&D$11) | E52: ='Q4 Assumptions'!$G$66*E$12+SUMIFS('Q4 Assumptions'!$C$85:$C$133,'Q4 Assumptions'!$D$85:$D$133,'Q4 Assumptions'!$A$66,'Q4 Assumptions'!$B$85:$B$133,">="&E$10,'Q4 Assumptions'!$B$85:$B$133,"<="&E$11) | F52: ='Q4 Assumptions'!$G$66*F$12+SUMIFS('Q4 Assumptions'!$C$85:$C$133,'Q4 Assumptions'!$D$85:$D$133,'Q4 Assumptions'!$A$66,'Q4 Assumptions'!$B$85:$B$133,">="&F$10,'Q4 Assumptions'!$B$85:$B$133,"<="&F$11) | G52: ='Q4 Assumptions'!$G$66*G$12+SUMIFS('Q4 Assumptions'!$C$85:$C$133,'Q4 Assumptions'!$D$85:$D$133,'Q4 Assumptions'!$A$66,'Q4 Assumptions'!$B$85:$B$133,">="&G$10,'Q4 Assumptions'!$B$85:$B$133,"<="&G$11) | H52: ='Q4 Assumptions'!$G$66*H$12+SUMIFS('Q4 Assumptions'!$C$85:$C$133,'Q4 Assumptions'!$D$85:$D$133,'Q4 Assumptions'!$A$66,'Q4 Assumptions'!$B$85:$B$133,">="&H$10,'Q4 Assumptions'!$B$85:$B$133,"<="&H$11) | I52: ='Q4 Assumptions'!$G$66*I$12+SUMIFS('Q4 Assumptions'!$C$85:$C$133,'Q4 Assumptions'!$D$85:$D$133,'Q4 Assumptions'!$A$66,'Q4 Assumptions'!$B$85:$B$133,">="&I$10,'Q4 Assumptions'!$B$85:$B$133,"<="&I$11) | J52: ='Q4 Assumptions'!$G$66*J$12+SUMIFS('Q4 Assumptions'!$C$85:$C$133,'Q4 Assumptions'!$D$85:$D$133,'Q4 Assumptions'!$A$66,'Q4 Assumptions'!$B$85:$B$133,">="&J$10,'Q4 Assumptions'!$B$85:$B$133,"<="&J$11) | K52: ='Q4 Assumptions'!$G$66*K$12+SUMIFS('Q4 Assumptions'!$C$85:$C$133,'Q4 Assumptions'!$D$85:$D$133,'Q4 Assumptions'!$A$66,'Q4 Assumptions'!$B$85:$B$133,">="&K$10,'Q4 Assumptions'!$B$85:$B$133,"<="&K$11) | ... Q52: ='Q4 Assumptions'!$G$66*Q$12+SUMIFS('Q4 Assumptions'!$C$85:$C$133,'Q4 Assumptions'!$D$85:$D$133,'Q4 Assumptions'!$A$66,'Q4 Assumptions'!$B$85:$B$133,">="&Q$10,'Q4 Assumptions'!$B$85:$B$133,"<="&Q$11) | R52: =SUM(D52:Q52)
B53: Capex New Branches | C53: ='Q4 Assumptions'!C67 | D53: ='Q4 Assumptions'!$G$67*D$12+SUMIFS('Q4 Assumptions'!$C$85:$C$133,'Q4 Assumptions'!$D$85:$D$133,'Q4 Assumptions'!$A$67,'Q4 Assumptions'!$B$85:$B$133,">="&D$10,'Q4 Assumptions'!$B$85:$B$133,"<="&D$11)+D89 | E53: ='Q4 Assumptions'!$G$67*E$12+SUMIFS('Q4 Assumptions'!$C$85:$C$133,'Q4 Assumptions'!$D$85:$D$133,'Q4 Assumptions'!$A$67,'Q4 Assumptions'!$B$85:$B$133,">="&E$10,'Q4 Assumptions'!$B$85:$B$133,"<="&E$11)+E89 | F53: ='Q4 Assumptions'!$G$67*F$12+SUMIFS('Q4 Assumptions'!$C$85:$C$133,'Q4 Assumptions'!$D$85:$D$133,'Q4 Assumptions'!$A$67,'Q4 Assumptions'!$B$85:$B$133,">="&F$10,'Q4 Assumptions'!$B$85:$B$133,"<="&F$11)+F89 | G53: ='Q4 Assumptions'!$G$67*G$12+SUMIFS('Q4 Assumptions'!$C$85:$C$133,'Q4 Assumptions'!$D$85:$D$133,'Q4 Assumptions'!$A$67,'Q4 Assumptions'!$B$85:$B$133,">="&G$10,'Q4 Assumptions'!$B$85:$B$133,"<="&G$11)+G89 | H53: ='Q4 Assumptions'!$G$67*H$12+SUMIFS('Q4 Assumptions'!$C$85:$C$133,'Q4 Assumptions'!$D$85:$D$133,'Q4 Assumptions'!$A$67,'Q4 Assumptions'!$B$85:$B$133,">="&H$10,'Q4 Assumptions'!$B$85:$B$133,"<="&H$11)+H89 | I53: ='Q4 Assumptions'!$G$67*I$12+SUMIFS('Q4 Assumptions'!$C$85:$C$133,'Q4 Assumptions'!$D$85:$D$133,'Q4 Assumptions'!$A$67,'Q4 Assumptions'!$B$85:$B$133,">="&I$10,'Q4 Assumptions'!$B$85:$B$133,"<="&I$11)+I89 | J53: ='Q4 Assumptions'!$G$67*J$12+SUMIFS('Q4 Assumptions'!$C$85:$C$133,'Q4 Assumptions'!$D$85:$D$133,'Q4 Assumptions'!$A$67,'Q4 Assumptions'!$B$85:$B$133,">="&J$10,'Q4 Assumptions'!$B$85:$B$133,"<="&J$11)+J89 | K53: ='Q4 Assumptions'!$G$67*K$12+SUMIFS('Q4 Assumptions'!$C$85:$C$133,'Q4 Assumptions'!$D$85:$D$133,'Q4 Assumptions'!$A$67,'Q4 Assumptions'!$B$85:$B$133,">="&K$10,'Q4 Assumptions'!$B$85:$B$133,"<="&K$11)+K89 | ... Q53: ='Q4 Assumptions'!$G$67*Q$12+SUMIFS('Q4 Assumptions'!$C$85:$C$133,'Q4 Assumptions'!$D$85:$D$133,'Q4 Assumptions'!$A$67,'Q4 Assumptions'!$B$85:$B$133,">="&Q$10,'Q4 Assumptions'!$B$85:$B$133,"<="&Q$11)+Q89 | R53: =SUM(D53:Q53)
B54: Placement of Fixed Deposit | C54: ='Q4 Assumptions'!C68 | D54: ='Q4 Assumptions'!$G$68*D$12+SUMIFS('Q4 Assumptions'!$C$85:$C$133,'Q4 Assumptions'!$D$85:$D$133,'Q4 Assumptions'!$A$68,'Q4 Assumptions'!$B$85:$B$133,">="&D$10,'Q4 Assumptions'!$B$85:$B$133,"<="&D$11) | E54: ='Q4 Assumptions'!$G$68*E$12+SUMIFS('Q4 Assumptions'!$C$85:$C$133,'Q4 Assumptions'!$D$85:$D$133,'Q4 Assumptions'!$A$68,'Q4 Assumptions'!$B$85:$B$133,">="&E$10,'Q4 Assumptions'!$B$85:$B$133,"<="&E$11) | F54: ='Q4 Assumptions'!$G$68*F$12+SUMIFS('Q4 Assumptions'!$C$85:$C$133,'Q4 Assumptions'!$D$85:$D$133,'Q4 Assumptions'!$A$68,'Q4 Assumptions'!$B$85:$B$133,">="&F$10,'Q4 Assumptions'!$B$85:$B$133,"<="&F$11) | G54: ='Q4 Assumptions'!$G$68*G$12+SUMIFS('Q4 Assumptions'!$C$85:$C$133,'Q4 Assumptions'!$D$85:$D$133,'Q4 Assumptions'!$A$68,'Q4 Assumptions'!$B$85:$B$133,">="&G$10,'Q4 Assumptions'!$B$85:$B$133,"<="&G$11) | H54: ='Q4 Assumptions'!$G$68*H$12+SUMIFS('Q4 Assumptions'!$C$85:$C$133,'Q4 Assumptions'!$D$85:$D$133,'Q4 Assumptions'!$A$68,'Q4 Assumptions'!$B$85:$B$133,">="&H$10,'Q4 Assumptions'!$B$85:$B$133,"<="&H$11) | I54: ='Q4 Assumptions'!$G$68*I$12+SUMIFS('Q4 Assumptions'!$C$85:$C$133,'Q4 Assumptions'!$D$85:$D$133,'Q4 Assumptions'!$A$68,'Q4 Assumptions'!$B$85:$B$133,">="&I$10,'Q4 Assumptions'!$B$85:$B$133,"<="&I$11) | J54: ='Q4 Assumptions'!$G$68*J$12+SUMIFS('Q4 Assumptions'!$C$85:$C$133,'Q4 Assumptions'!$D$85:$D$133,'Q4 Assumptions'!$A$68,'Q4 Assumptions'!$B$85:$B$133,">="&J$10,'Q4 Assumptions'!$B$85:$B$133,"<="&J$11) | K54: ='Q4 Assumptions'!$G$68*K$12+SUMIFS('Q4 Assumptions'!$C$85:$C$133,'Q4 Assumptions'!$D$85:$D$133,'Q4 Assumptions'!$A$68,'Q4 Assumptions'!$B$85:$B$133,">="&K$10,'Q4 Assumptions'!$B$85:$B$133,"<="&K$11) | ... Q54: ='Q4 Assumptions'!$G$68*Q$12+SUMIFS('Q4 Assumptions'!$C$85:$C$133,'Q4 Assumptions'!$D$85:$D$133,'Q4 Assumptions'!$A$68,'Q4 Assumptions'!$B$85:$B$133,">="&Q$10,'Q4 Assumptions'!$B$85:$B$133,"<="&Q$11) | R54: =SUM(D54:Q54)
B55: Purchase of investment | C55: ='Q4 Assumptions'!C69 | D55: ='Q4 Assumptions'!$G$69*D$12+SUMIFS('Q4 Assumptions'!$C$85:$C$133,'Q4 Assumptions'!$D$85:$D$133,'Q4 Assumptions'!$A$69,'Q4 Assumptions'!$B$85:$B$133,">="&D$10,'Q4 Assumptions'!$B$85:$B$133,"<="&D$11) | E55: ='Q4 Assumptions'!$G$69*E$12+SUMIFS('Q4 Assumptions'!$C$85:$C$133,'Q4 Assumptions'!$D$85:$D$133,'Q4 Assumptions'!$A$69,'Q4 Assumptions'!$B$85:$B$133,">="&E$10,'Q4 Assumptions'!$B$85:$B$133,"<="&E$11) | F55: ='Q4 Assumptions'!$G$69*F$12+SUMIFS('Q4 Assumptions'!$C$85:$C$133,'Q4 Assumptions'!$D$85:$D$133,'Q4 Assumptions'!$A$69,'Q4 Assumptions'!$B$85:$B$133,">="&F$10,'Q4 Assumptions'!$B$85:$B$133,"<="&F$11) | G55: ='Q4 Assumptions'!$G$69*G$12+SUMIFS('Q4 Assumptions'!$C$85:$C$133,'Q4 Assumptions'!$D$85:$D$133,'Q4 Assumptions'!$A$69,'Q4 Assumptions'!$B$85:$B$133,">="&G$10,'Q4 Assumptions'!$B$85:$B$133,"<="&G$11) | H55: ='Q4 Assumptions'!$G$69*H$12+SUMIFS('Q4 Assumptions'!$C$85:$C$133,'Q4 Assumptions'!$D$85:$D$133,'Q4 Assumptions'!$A$69,'Q4 Assumptions'!$B$85:$B$133,">="&H$10,'Q4 Assumptions'!$B$85:$B$133,"<="&H$11) | I55: ='Q4 Assumptions'!$G$69*I$12+SUMIFS('Q4 Assumptions'!$C$85:$C$133,'Q4 Assumptions'!$D$85:$D$133,'Q4 Assumptions'!$A$69,'Q4 Assumptions'!$B$85:$B$133,">="&I$10,'Q4 Assumptions'!$B$85:$B$133,"<="&I$11) | J55: ='Q4 Assumptions'!$G$69*J$12+SUMIFS('Q4 Assumptions'!$C$85:$C$133,'Q4 Assumptions'!$D$85:$D$133,'Q4 Assumptions'!$A$69,'Q4 Assumptions'!$B$85:$B$133,">="&J$10,'Q4 Assumptions'!$B$85:$B$133,"<="&J$11) | K55: ='Q4 Assumptions'!$G$69*K$12+SUMIFS('Q4 Assumptions'!$C$85:$C$133,'Q4 Assumptions'!$D$85:$D$133,'Q4 Assumptions'!$A$69,'Q4 Assumptions'!$B$85:$B$133,">="&K$10,'Q4 Assumptions'!$B$85:$B$133,"<="&K$11) | ... Q55: ='Q4 Assumptions'!$G$69*Q$12+SUMIFS('Q4 Assumptions'!$C$85:$C$133,'Q4 Assumptions'!$D$85:$D$133,'Q4 Assumptions'!$A$69,'Q4 Assumptions'!$B$85:$B$133,">="&Q$10,'Q4 Assumptions'!$B$85:$B$133,"<="&Q$11) | R55: =SUM(D55:Q55)
A56: Net Cash Flow from Investing Activities | C56: =C46+C47+C48+C49+C50+C52+C53+C54+C55 | D56: =D46+D47+D48+D49+D50+D52+D53+D54+D55 | E56: =E46+E47+E48+E49+E50+E52+E53+E54+E55 | F56: =F46+F47+F48+F49+F50+F52+F53+F54+F55 | G56: =G46+G47+G48+G49+G50+G52+G53+G54+G55 | H56: =H46+H47+H48+H49+H50+H52+H53+H54+H55 | I56: =I46+I47+I48+I49+I50+I52+I53+I54+I55 | J56: =J46+J47+J48+J49+J50+J52+J53+J54+J55 | ... R56: =R46+R47+R48+R49+R50+R52+R53+R54+R55
A58: Financing Activities
A59: Cash receipts from
B60: Issuance of stock | C60: ='Q4 Assumptions'!C70 | D60: ='Q4 Assumptions'!$G$70*D$12+SUMIFS('Q4 Assumptions'!$C$85:$C$133,'Q4 Assumptions'!$D$85:$D$133,'Q4 Assumptions'!$A$70,'Q4 Assumptions'!$B$85:$B$133,">="&D$10,'Q4 Assumptions'!$B$85:$B$133,"<="&D$11) | E60: ='Q4 Assumptions'!$G$70*E$12+SUMIFS('Q4 Assumptions'!$C$85:$C$133,'Q4 Assumptions'!$D$85:$D$133,'Q4 Assumptions'!$A$70,'Q4 Assumptions'!$B$85:$B$133,">="&E$10,'Q4 Assumptions'!$B$85:$B$133,"<="&E$11) | F60: ='Q4 Assumptions'!$G$70*F$12+SUMIFS('Q4 Assumptions'!$C$85:$C$133,'Q4 Assumptions'!$D$85:$D$133,'Q4 Assumptions'!$A$70,'Q4 Assumptions'!$B$85:$B$133,">="&F$10,'Q4 Assumptions'!$B$85:$B$133,"<="&F$11) | G60: ='Q4 Assumptions'!$G$70*G$12+SUMIFS('Q4 Assumptions'!$C$85:$C$133,'Q4 Assumptions'!$D$85:$D$133,'Q4 Assumptions'!$A$70,'Q4 Assumptions'!$B$85:$B$133,">="&G$10,'Q4 Assumptions'!$B$85:$B$133,"<="&G$11) | H60: ='Q4 Assumptions'!$G$70*H$12+SUMIFS('Q4 Assumptions'!$C$85:$C$133,'Q4 Assumptions'!$D$85:$D$133,'Q4 Assumptions'!$A$70,'Q4 Assumptions'!$B$85:$B$133,">="&H$10,'Q4 Assumptions'!$B$85:$B$133,"<="&H$11) | I60: ='Q4 Assumptions'!$G$70*I$12+SUMIFS('Q4 Assumptions'!$C$85:$C$133,'Q4 Assumptions'!$D$85:$D$133,'Q4 Assumptions'!$A$70,'Q4 Assumptions'!$B$85:$B$133,">="&I$10,'Q4 Assumptions'!$B$85:$B$133,"<="&I$11) | J60: ='Q4 Assumptions'!$G$70*J$12+SUMIFS('Q4 Assumptions'!$C$85:$C$133,'Q4 Assumptions'!$D$85:$D$133,'Q4 Assumptions'!$A$70,'Q4 Assumptions'!$B$85:$B$133,">="&J$10,'Q4 Assumptions'!$B$85:$B$133,"<="&J$11) | K60: ='Q4 Assumptions'!$G$70*K$12+SUMIFS('Q4 Assumptions'!$C$85:$C$133,'Q4 Assumptions'!$D$85:$D$133,'Q4 Assumptions'!$A$70,'Q4 Assumptions'!$B$85:$B$133,">="&K$10,'Q4 Assumptions'!$B$85:$B$133,"<="&K$11) | ... Q60: ='Q4 Assumptions'!$G$70*Q$12+SUMIFS('Q4 Assumptions'!$C$85:$C$133,'Q4 Assumptions'!$D$85:$D$133,'Q4 Assumptions'!$A$70,'Q4 Assumptions'!$B$85:$B$133,">="&Q$10,'Q4 Assumptions'!$B$85:$B$133,"<="&Q$11) | R60: =SUM(D60:Q60)
B61: Loan received | C61: ='Q4 Assumptions'!C71 | D61: ='Q4 Assumptions'!$G$71*D$12+SUMIFS('Q4 Assumptions'!$C$85:$C$133,'Q4 Assumptions'!$D$85:$D$133,'Q4 Assumptions'!$A$71,'Q4 Assumptions'!$B$85:$B$133,">="&D$10,'Q4 Assumptions'!$B$85:$B$133,"<="&D$11) | E61: ='Q4 Assumptions'!$G$71*E$12+SUMIFS('Q4 Assumptions'!$C$85:$C$133,'Q4 Assumptions'!$D$85:$D$133,'Q4 Assumptions'!$A$71,'Q4 Assumptions'!$B$85:$B$133,">="&E$10,'Q4 Assumptions'!$B$85:$B$133,"<="&E$11) | F61: ='Q4 Assumptions'!$G$71*F$12+SUMIFS('Q4 Assumptions'!$C$85:$C$133,'Q4 Assumptions'!$D$85:$D$133,'Q4 Assumptions'!$A$71,'Q4 Assumptions'!$B$85:$B$133,">="&F$10,'Q4 Assumptions'!$B$85:$B$133,"<="&F$11) | G61: ='Q4 Assumptions'!$G$71*G$12+SUMIFS('Q4 Assumptions'!$C$85:$C$133,'Q4 Assumptions'!$D$85:$D$133,'Q4 Assumptions'!$A$71,'Q4 Assumptions'!$B$85:$B$133,">="&G$10,'Q4 Assumptions'!$B$85:$B$133,"<="&G$11) | H61: ='Q4 Assumptions'!$G$71*H$12+SUMIFS('Q4 Assumptions'!$C$85:$C$133,'Q4 Assumptions'!$D$85:$D$133,'Q4 Assumptions'!$A$71,'Q4 Assumptions'!$B$85:$B$133,">="&H$10,'Q4 Assumptions'!$B$85:$B$133,"<="&H$11) | I61: ='Q4 Assumptions'!$G$71*I$12+SUMIFS('Q4 Assumptions'!$C$85:$C$133,'Q4 Assumptions'!$D$85:$D$133,'Q4 Assumptions'!$A$71,'Q4 Assumptions'!$B$85:$B$133,">="&I$10,'Q4 Assumptions'!$B$85:$B$133,"<="&I$11) | J61: ='Q4 Assumptions'!$G$71*J$12+SUMIFS('Q4 Assumptions'!$C$85:$C$133,'Q4 Assumptions'!$D$85:$D$133,'Q4 Assumptions'!$A$71,'Q4 Assumptions'!$B$85:$B$133,">="&J$10,'Q4 Assumptions'!$B$85:$B$133,"<="&J$11) | K61: ='Q4 Assumptions'!$G$71*K$12+SUMIFS('Q4 Assumptions'!$C$85:$C$133,'Q4 Assumptions'!$D$85:$D$133,'Q4 Assumptions'!$A$71,'Q4 Assumptions'!$B$85:$B$133,">="&K$10,'Q4 Assumptions'!$B$85:$B$133,"<="&K$11) | ... Q61: ='Q4 Assumptions'!$G$71*Q$12+SUMIFS('Q4 Assumptions'!$C$85:$C$133,'Q4 Assumptions'!$D$85:$D$133,'Q4 Assumptions'!$A$71,'Q4 Assumptions'!$B$85:$B$133,">="&Q$10,'Q4 Assumptions'!$B$85:$B$133,"<="&Q$11) | R61: =SUM(D61:Q61)
B62: Borrowing | C62: ='Q4 Assumptions'!C72 | D62: ='Q4 Assumptions'!$G$72*D$12+SUMIFS('Q4 Assumptions'!$C$85:$C$133,'Q4 Assumptions'!$D$85:$D$133,'Q4 Assumptions'!$A$72,'Q4 Assumptions'!$B$85:$B$133,">="&D$10,'Q4 Assumptions'!$B$85:$B$133,"<="&D$11) | E62: ='Q4 Assumptions'!$G$72*E$12+SUMIFS('Q4 Assumptions'!$C$85:$C$133,'Q4 Assumptions'!$D$85:$D$133,'Q4 Assumptions'!$A$72,'Q4 Assumptions'!$B$85:$B$133,">="&E$10,'Q4 Assumptions'!$B$85:$B$133,"<="&E$11) | F62: ='Q4 Assumptions'!$G$72*F$12+SUMIFS('Q4 Assumptions'!$C$85:$C$133,'Q4 Assumptions'!$D$85:$D$133,'Q4 Assumptions'!$A$72,'Q4 Assumptions'!$B$85:$B$133,">="&F$10,'Q4 Assumptions'!$B$85:$B$133,"<="&F$11) | G62: ='Q4 Assumptions'!$G$72*G$12+SUMIFS('Q4 Assumptions'!$C$85:$C$133,'Q4 Assumptions'!$D$85:$D$133,'Q4 Assumptions'!$A$72,'Q4 Assumptions'!$B$85:$B$133,">="&G$10,'Q4 Assumptions'!$B$85:$B$133,"<="&G$11) | H62: ='Q4 Assumptions'!$G$72*H$12+SUMIFS('Q4 Assumptions'!$C$85:$C$133,'Q4 Assumptions'!$D$85:$D$133,'Q4 Assumptions'!$A$72,'Q4 Assumptions'!$B$85:$B$133,">="&H$10,'Q4 Assumptions'!$B$85:$B$133,"<="&H$11) | I62: ='Q4 Assumptions'!$G$72*I$12+SUMIFS('Q4 Assumptions'!$C$85:$C$133,'Q4 Assumptions'!$D$85:$D$133,'Q4 Assumptions'!$A$72,'Q4 Assumptions'!$B$85:$B$133,">="&I$10,'Q4 Assumptions'!$B$85:$B$133,"<="&I$11) | J62: ='Q4 Assumptions'!$G$72*J$12+SUMIFS('Q4 Assumptions'!$C$85:$C$133,'Q4 Assumptions'!$D$85:$D$133,'Q4 Assumptions'!$A$72,'Q4 Assumptions'!$B$85:$B$133,">="&J$10,'Q4 Assumptions'!$B$85:$B$133,"<="&J$11) | K62: ='Q4 Assumptions'!$G$72*K$12+SUMIFS('Q4 Assumptions'!$C$85:$C$133,'Q4 Assumptions'!$D$85:$D$133,'Q4 Assumptions'!$A$72,'Q4 Assumptions'!$B$85:$B$133,">="&K$10,'Q4 Assumptions'!$B$85:$B$133,"<="&K$11) | ... Q62: ='Q4 Assumptions'!$G$72*Q$12+SUMIFS('Q4 Assumptions'!$C$85:$C$133,'Q4 Assumptions'!$D$85:$D$133,'Q4 Assumptions'!$A$72,'Q4 Assumptions'!$B$85:$B$133,">="&Q$10,'Q4 Assumptions'!$B$85:$B$133,"<="&Q$11) | R62: =SUM(D62:Q62)
B63: Repayment from related parties | C63: ='Q4 Assumptions'!C73 | D63: ='Q4 Assumptions'!$G$73*D$12+SUMIFS('Q4 Assumptions'!$C$85:$C$133,'Q4 Assumptions'!$D$85:$D$133,'Q4 Assumptions'!$A$73,'Q4 Assumptions'!$B$85:$B$133,">="&D$10,'Q4 Assumptions'!$B$85:$B$133,"<="&D$11) | E63: ='Q4 Assumptions'!$G$73*E$12+SUMIFS('Q4 Assumptions'!$C$85:$C$133,'Q4 Assumptions'!$D$85:$D$133,'Q4 Assumptions'!$A$73,'Q4 Assumptions'!$B$85:$B$133,">="&E$10,'Q4 Assumptions'!$B$85:$B$133,"<="&E$11) | F63: ='Q4 Assumptions'!$G$73*F$12+SUMIFS('Q4 Assumptions'!$C$85:$C$133,'Q4 Assumptions'!$D$85:$D$133,'Q4 Assumptions'!$A$73,'Q4 Assumptions'!$B$85:$B$133,">="&F$10,'Q4 Assumptions'!$B$85:$B$133,"<="&F$11) | G63: ='Q4 Assumptions'!$G$73*G$12+SUMIFS('Q4 Assumptions'!$C$85:$C$133,'Q4 Assumptions'!$D$85:$D$133,'Q4 Assumptions'!$A$73,'Q4 Assumptions'!$B$85:$B$133,">="&G$10,'Q4 Assumptions'!$B$85:$B$133,"<="&G$11) | H63: ='Q4 Assumptions'!$G$73*H$12+SUMIFS('Q4 Assumptions'!$C$85:$C$133,'Q4 Assumptions'!$D$85:$D$133,'Q4 Assumptions'!$A$73,'Q4 Assumptions'!$B$85:$B$133,">="&H$10,'Q4 Assumptions'!$B$85:$B$133,"<="&H$11) | I63: ='Q4 Assumptions'!$G$73*I$12+SUMIFS('Q4 Assumptions'!$C$85:$C$133,'Q4 Assumptions'!$D$85:$D$133,'Q4 Assumptions'!$A$73,'Q4 Assumptions'!$B$85:$B$133,">="&I$10,'Q4 Assumptions'!$B$85:$B$133,"<="&I$11) | J63: ='Q4 Assumptions'!$G$73*J$12+SUMIFS('Q4 Assumptions'!$C$85:$C$133,'Q4 Assumptions'!$D$85:$D$133,'Q4 Assumptions'!$A$73,'Q4 Assumptions'!$B$85:$B$133,">="&J$10,'Q4 Assumptions'!$B$85:$B$133,"<="&J$11) | K63: ='Q4 Assumptions'!$G$73*K$12+SUMIFS('Q4 Assumptions'!$C$85:$C$133,'Q4 Assumptions'!$D$85:$D$133,'Q4 Assumptions'!$A$73,'Q4 Assumptions'!$B$85:$B$133,">="&K$10,'Q4 Assumptions'!$B$85:$B$133,"<="&K$11) | ... Q63: ='Q4 Assumptions'!$G$73*Q$12+SUMIFS('Q4 Assumptions'!$C$85:$C$133,'Q4 Assumptions'!$D$85:$D$133,'Q4 Assumptions'!$A$73,'Q4 Assumptions'!$B$85:$B$133,">="&Q$10,'Q4 Assumptions'!$B$85:$B$133,"<="&Q$11) | R63: =SUM(D63:Q63)
A64: Cash paid for
B65: Repurchase of stock (treasury stock) | C65: ='Q4 Assumptions'!C74 | D65: ='Q4 Assumptions'!$G$74*D$12+SUMIFS('Q4 Assumptions'!$C$85:$C$133,'Q4 Assumptions'!$D$85:$D$133,'Q4 Assumptions'!$A$74,'Q4 Assumptions'!$B$85:$B$133,">="&D$10,'Q4 Assumptions'!$B$85:$B$133,"<="&D$11) | E65: ='Q4 Assumptions'!$G$74*E$12+SUMIFS('Q4 Assumptions'!$C$85:$C$133,'Q4 Assumptions'!$D$85:$D$133,'Q4 Assumptions'!$A$74,'Q4 Assumptions'!$B$85:$B$133,">="&E$10,'Q4 Assumptions'!$B$85:$B$133,"<="&E$11) | F65: ='Q4 Assumptions'!$G$74*F$12+SUMIFS('Q4 Assumptions'!$C$85:$C$133,'Q4 Assumptions'!$D$85:$D$133,'Q4 Assumptions'!$A$74,'Q4 Assumptions'!$B$85:$B$133,">="&F$10,'Q4 Assumptions'!$B$85:$B$133,"<="&F$11) | G65: ='Q4 Assumptions'!$G$74*G$12+SUMIFS('Q4 Assumptions'!$C$85:$C$133,'Q4 Assumptions'!$D$85:$D$133,'Q4 Assumptions'!$A$74,'Q4 Assumptions'!$B$85:$B$133,">="&G$10,'Q4 Assumptions'!$B$85:$B$133,"<="&G$11) | H65: ='Q4 Assumptions'!$G$74*H$12+SUMIFS('Q4 Assumptions'!$C$85:$C$133,'Q4 Assumptions'!$D$85:$D$133,'Q4 Assumptions'!$A$74,'Q4 Assumptions'!$B$85:$B$133,">="&H$10,'Q4 Assumptions'!$B$85:$B$133,"<="&H$11) | I65: ='Q4 Assumptions'!$G$74*I$12+SUMIFS('Q4 Assumptions'!$C$85:$C$133,'Q4 Assumptions'!$D$85:$D$133,'Q4 Assumptions'!$A$74,'Q4 Assumptions'!$B$85:$B$133,">="&I$10,'Q4 Assumptions'!$B$85:$B$133,"<="&I$11) | J65: ='Q4 Assumptions'!$G$74*J$12+SUMIFS('Q4 Assumptions'!$C$85:$C$133,'Q4 Assumptions'!$D$85:$D$133,'Q4 Assumptions'!$A$74,'Q4 Assumptions'!$B$85:$B$133,">="&J$10,'Q4 Assumptions'!$B$85:$B$133,"<="&J$11) | K65: ='Q4 Assumptions'!$G$74*K$12+SUMIFS('Q4 Assumptions'!$C$85:$C$133,'Q4 Assumptions'!$D$85:$D$133,'Q4 Assumptions'!$A$74,'Q4 Assumptions'!$B$85:$B$133,">="&K$10,'Q4 Assumptions'!$B$85:$B$133,"<="&K$11) | ... Q65: ='Q4 Assumptions'!$G$74*Q$12+SUMIFS('Q4 Assumptions'!$C$85:$C$133,'Q4 Assumptions'!$D$85:$D$133,'Q4 Assumptions'!$A$74,'Q4 Assumptions'!$B$85:$B$133,">="&Q$10,'Q4 Assumptions'!$B$85:$B$133,"<="&Q$11) | R65: =SUM(D65:Q65)
B66: Purchase of investment | C66: ='Q4 Assumptions'!C75 | D66: ='Q4 Assumptions'!$G$75*D$12+SUMIFS('Q4 Assumptions'!$C$85:$C$133,'Q4 Assumptions'!$D$85:$D$133,'Q4 Assumptions'!$A$75,'Q4 Assumptions'!$B$85:$B$133,">="&D$10,'Q4 Assumptions'!$B$85:$B$133,"<="&D$11) | E66: ='Q4 Assumptions'!$G$75*E$12+SUMIFS('Q4 Assumptions'!$C$85:$C$133,'Q4 Assumptions'!$D$85:$D$133,'Q4 Assumptions'!$A$75,'Q4 Assumptions'!$B$85:$B$133,">="&E$10,'Q4 Assumptions'!$B$85:$B$133,"<="&E$11) | F66: ='Q4 Assumptions'!$G$75*F$12+SUMIFS('Q4 Assumptions'!$C$85:$C$133,'Q4 Assumptions'!$D$85:$D$133,'Q4 Assumptions'!$A$75,'Q4 Assumptions'!$B$85:$B$133,">="&F$10,'Q4 Assumptions'!$B$85:$B$133,"<="&F$11) | G66: ='Q4 Assumptions'!$G$75*G$12+SUMIFS('Q4 Assumptions'!$C$85:$C$133,'Q4 Assumptions'!$D$85:$D$133,'Q4 Assumptions'!$A$75,'Q4 Assumptions'!$B$85:$B$133,">="&G$10,'Q4 Assumptions'!$B$85:$B$133,"<="&G$11) | H66: ='Q4 Assumptions'!$G$75*H$12+SUMIFS('Q4 Assumptions'!$C$85:$C$133,'Q4 Assumptions'!$D$85:$D$133,'Q4 Assumptions'!$A$75,'Q4 Assumptions'!$B$85:$B$133,">="&H$10,'Q4 Assumptions'!$B$85:$B$133,"<="&H$11) | I66: ='Q4 Assumptions'!$G$75*I$12+SUMIFS('Q4 Assumptions'!$C$85:$C$133,'Q4 Assumptions'!$D$85:$D$133,'Q4 Assumptions'!$A$75,'Q4 Assumptions'!$B$85:$B$133,">="&I$10,'Q4 Assumptions'!$B$85:$B$133,"<="&I$11) | J66: ='Q4 Assumptions'!$G$75*J$12+SUMIFS('Q4 Assumptions'!$C$85:$C$133,'Q4 Assumptions'!$D$85:$D$133,'Q4 Assumptions'!$A$75,'Q4 Assumptions'!$B$85:$B$133,">="&J$10,'Q4 Assumptions'!$B$85:$B$133,"<="&J$11) | K66: ='Q4 Assumptions'!$G$75*K$12+SUMIFS('Q4 Assumptions'!$C$85:$C$133,'Q4 Assumptions'!$D$85:$D$133,'Q4 Assumptions'!$A$75,'Q4 Assumptions'!$B$85:$B$133,">="&K$10,'Q4 Assumptions'!$B$85:$B$133,"<="&K$11) | ... Q66: ='Q4 Assumptions'!$G$75*Q$12+SUMIFS('Q4 Assumptions'!$C$85:$C$133,'Q4 Assumptions'!$D$85:$D$133,'Q4 Assumptions'!$A$75,'Q4 Assumptions'!$B$85:$B$133,">="&Q$10,'Q4 Assumptions'!$B$85:$B$133,"<="&Q$11) | R66: =SUM(D66:Q66)
B67: Repayment of loans | C67: ='Q4 Assumptions'!C76 | D67: ='Q4 Assumptions'!$G$76*D$12+SUMIFS('Q4 Assumptions'!$C$85:$C$133,'Q4 Assumptions'!$D$85:$D$133,'Q4 Assumptions'!$A$76,'Q4 Assumptions'!$B$85:$B$133,">="&D$10,'Q4 Assumptions'!$B$85:$B$133,"<="&D$11) | E67: ='Q4 Assumptions'!$G$76*E$12+SUMIFS('Q4 Assumptions'!$C$85:$C$133,'Q4 Assumptions'!$D$85:$D$133,'Q4 Assumptions'!$A$76,'Q4 Assumptions'!$B$85:$B$133,">="&E$10,'Q4 Assumptions'!$B$85:$B$133,"<="&E$11) | F67: ='Q4 Assumptions'!$G$76*F$12+SUMIFS('Q4 Assumptions'!$C$85:$C$133,'Q4 Assumptions'!$D$85:$D$133,'Q4 Assumptions'!$A$76,'Q4 Assumptions'!$B$85:$B$133,">="&F$10,'Q4 Assumptions'!$B$85:$B$133,"<="&F$11) | G67: ='Q4 Assumptions'!$G$76*G$12+SUMIFS('Q4 Assumptions'!$C$85:$C$133,'Q4 Assumptions'!$D$85:$D$133,'Q4 Assumptions'!$A$76,'Q4 Assumptions'!$B$85:$B$133,">="&G$10,'Q4 Assumptions'!$B$85:$B$133,"<="&G$11) | H67: ='Q4 Assumptions'!$G$76*H$12+SUMIFS('Q4 Assumptions'!$C$85:$C$133,'Q4 Assumptions'!$D$85:$D$133,'Q4 Assumptions'!$A$76,'Q4 Assumptions'!$B$85:$B$133,">="&H$10,'Q4 Assumptions'!$B$85:$B$133,"<="&H$11) | I67: ='Q4 Assumptions'!$G$76*I$12+SUMIFS('Q4 Assumptions'!$C$85:$C$133,'Q4 Assumptions'!$D$85:$D$133,'Q4 Assumptions'!$A$76,'Q4 Assumptions'!$B$85:$B$133,">="&I$10,'Q4 Assumptions'!$B$85:$B$133,"<="&I$11) | J67: ='Q4 Assumptions'!$G$76*J$12+SUMIFS('Q4 Assumptions'!$C$85:$C$133,'Q4 Assumptions'!$D$85:$D$133,'Q4 Assumptions'!$A$76,'Q4 Assumptions'!$B$85:$B$133,">="&J$10,'Q4 Assumptions'!$B$85:$B$133,"<="&J$11) | K67: ='Q4 Assumptions'!$G$76*K$12+SUMIFS('Q4 Assumptions'!$C$85:$C$133,'Q4 Assumptions'!$D$85:$D$133,'Q4 Assumptions'!$A$76,'Q4 Assumptions'!$B$85:$B$133,">="&K$10,'Q4 Assumptions'!$B$85:$B$133,"<="&K$11) | ... Q67: ='Q4 Assumptions'!$G$76*Q$12+SUMIFS('Q4 Assumptions'!$C$85:$C$133,'Q4 Assumptions'!$D$85:$D$133,'Q4 Assumptions'!$A$76,'Q4 Assumptions'!$B$85:$B$133,">="&Q$10,'Q4 Assumptions'!$B$85:$B$133,"<="&Q$11) | R67: =SUM(D67:Q67)
B68: Dividends | C68: ='Q4 Assumptions'!C77 | D68: ='Q4 Assumptions'!$G$77*D$12+SUMIFS('Q4 Assumptions'!$C$85:$C$133,'Q4 Assumptions'!$D$85:$D$133,'Q4 Assumptions'!$A$77,'Q4 Assumptions'!$B$85:$B$133,">="&D$10,'Q4 Assumptions'!$B$85:$B$133,"<="&D$11) | E68: ='Q4 Assumptions'!$G$77*E$12+SUMIFS('Q4 Assumptions'!$C$85:$C$133,'Q4 Assumptions'!$D$85:$D$133,'Q4 Assumptions'!$A$77,'Q4 Assumptions'!$B$85:$B$133,">="&E$10,'Q4 Assumptions'!$B$85:$B$133,"<="&E$11) | F68: ='Q4 Assumptions'!$G$77*F$12+SUMIFS('Q4 Assumptions'!$C$85:$C$133,'Q4 Assumptions'!$D$85:$D$133,'Q4 Assumptions'!$A$77,'Q4 Assumptions'!$B$85:$B$133,">="&F$10,'Q4 Assumptions'!$B$85:$B$133,"<="&F$11) | G68: ='Q4 Assumptions'!$G$77*G$12+SUMIFS('Q4 Assumptions'!$C$85:$C$133,'Q4 Assumptions'!$D$85:$D$133,'Q4 Assumptions'!$A$77,'Q4 Assumptions'!$B$85:$B$133,">="&G$10,'Q4 Assumptions'!$B$85:$B$133,"<="&G$11) | H68: ='Q4 Assumptions'!$G$77*H$12+SUMIFS('Q4 Assumptions'!$C$85:$C$133,'Q4 Assumptions'!$D$85:$D$133,'Q4 Assumptions'!$A$77,'Q4 Assumptions'!$B$85:$B$133,">="&H$10,'Q4 Assumptions'!$B$85:$B$133,"<="&H$11) | I68: ='Q4 Assumptions'!$G$77*I$12+SUMIFS('Q4 Assumptions'!$C$85:$C$133,'Q4 Assumptions'!$D$85:$D$133,'Q4 Assumptions'!$A$77,'Q4 Assumptions'!$B$85:$B$133,">="&I$10,'Q4 Assumptions'!$B$85:$B$133,"<="&I$11) | J68: ='Q4 Assumptions'!$G$77*J$12+SUMIFS('Q4 Assumptions'!$C$85:$C$133,'Q4 Assumptions'!$D$85:$D$133,'Q4 Assumptions'!$A$77,'Q4 Assumptions'!$B$85:$B$133,">="&J$10,'Q4 Assumptions'!$B$85:$B$133,"<="&J$11) | K68: ='Q4 Assumptions'!$G$77*K$12+SUMIFS('Q4 Assumptions'!$C$85:$C$133,'Q4 Assumptions'!$D$85:$D$133,'Q4 Assumptions'!$A$77,'Q4 Assumptions'!$B$85:$B$133,">="&K$10,'Q4 Assumptions'!$B$85:$B$133,"<="&K$11) | ... Q68: ='Q4 Assumptions'!$G$77*Q$12+SUMIFS('Q4 Assumptions'!$C$85:$C$133,'Q4 Assumptions'!$D$85:$D$133,'Q4 Assumptions'!$A$77,'Q4 Assumptions'!$B$85:$B$133,">="&Q$10,'Q4 Assumptions'!$B$85:$B$133,"<="&Q$11) | R68: =SUM(D68:Q68)
B69: Advance to related parties | C69: ='Q4 Assumptions'!C78 | D69: ='Q4 Assumptions'!$G$78*D$12+SUMIFS('Q4 Assumptions'!$C$85:$C$133,'Q4 Assumptions'!$D$85:$D$133,'Q4 Assumptions'!$A$78,'Q4 Assumptions'!$B$85:$B$133,">="&D$10,'Q4 Assumptions'!$B$85:$B$133,"<="&D$11) | E69: ='Q4 Assumptions'!$G$78*E$12+SUMIFS('Q4 Assumptions'!$C$85:$C$133,'Q4 Assumptions'!$D$85:$D$133,'Q4 Assumptions'!$A$78,'Q4 Assumptions'!$B$85:$B$133,">="&E$10,'Q4 Assumptions'!$B$85:$B$133,"<="&E$11) | F69: ='Q4 Assumptions'!$G$78*F$12+SUMIFS('Q4 Assumptions'!$C$85:$C$133,'Q4 Assumptions'!$D$85:$D$133,'Q4 Assumptions'!$A$78,'Q4 Assumptions'!$B$85:$B$133,">="&F$10,'Q4 Assumptions'!$B$85:$B$133,"<="&F$11) | G69: ='Q4 Assumptions'!$G$78*G$12+SUMIFS('Q4 Assumptions'!$C$85:$C$133,'Q4 Assumptions'!$D$85:$D$133,'Q4 Assumptions'!$A$78,'Q4 Assumptions'!$B$85:$B$133,">="&G$10,'Q4 Assumptions'!$B$85:$B$133,"<="&G$11) | H69: ='Q4 Assumptions'!$G$78*H$12+SUMIFS('Q4 Assumptions'!$C$85:$C$133,'Q4 Assumptions'!$D$85:$D$133,'Q4 Assumptions'!$A$78,'Q4 Assumptions'!$B$85:$B$133,">="&H$10,'Q4 Assumptions'!$B$85:$B$133,"<="&H$11) | I69: ='Q4 Assumptions'!$G$78*I$12+SUMIFS('Q4 Assumptions'!$C$85:$C$133,'Q4 Assumptions'!$D$85:$D$133,'Q4 Assumptions'!$A$78,'Q4 Assumptions'!$B$85:$B$133,">="&I$10,'Q4 Assumptions'!$B$85:$B$133,"<="&I$11) | J69: ='Q4 Assumptions'!$G$78*J$12+SUMIFS('Q4 Assumptions'!$C$85:$C$133,'Q4 Assumptions'!$D$85:$D$133,'Q4 Assumptions'!$A$78,'Q4 Assumptions'!$B$85:$B$133,">="&J$10,'Q4 Assumptions'!$B$85:$B$133,"<="&J$11) | K69: ='Q4 Assumptions'!$G$78*K$12+SUMIFS('Q4 Assumptions'!$C$85:$C$133,'Q4 Assumptions'!$D$85:$D$133,'Q4 Assumptions'!$A$78,'Q4 Assumptions'!$B$85:$B$133,">="&K$10,'Q4 Assumptions'!$B$85:$B$133,"<="&K$11) | ... Q69: ='Q4 Assumptions'!$G$78*Q$12+SUMIFS('Q4 Assumptions'!$C$85:$C$133,'Q4 Assumptions'!$D$85:$D$133,'Q4 Assumptions'!$A$78,'Q4 Assumptions'!$B$85:$B$133,">="&Q$10,'Q4 Assumptions'!$B$85:$B$133,"<="&Q$11) | R69: =SUM(D69:Q69)
B70: Repayment to related parties | C70: ='Q4 Assumptions'!C79 | D70: ='Q4 Assumptions'!$G$79*D$12+SUMIFS('Q4 Assumptions'!$C$85:$C$133,'Q4 Assumptions'!$D$85:$D$133,'Q4 Assumptions'!$A$79,'Q4 Assumptions'!$B$85:$B$133,">="&D$10,'Q4 Assumptions'!$B$85:$B$133,"<="&D$11) | E70: ='Q4 Assumptions'!$G$79*E$12+SUMIFS('Q4 Assumptions'!$C$85:$C$133,'Q4 Assumptions'!$D$85:$D$133,'Q4 Assumptions'!$A$79,'Q4 Assumptions'!$B$85:$B$133,">="&E$10,'Q4 Assumptions'!$B$85:$B$133,"<="&E$11) | F70: ='Q4 Assumptions'!$G$79*F$12+SUMIFS('Q4 Assumptions'!$C$85:$C$133,'Q4 Assumptions'!$D$85:$D$133,'Q4 Assumptions'!$A$79,'Q4 Assumptions'!$B$85:$B$133,">="&F$10,'Q4 Assumptions'!$B$85:$B$133,"<="&F$11) | G70: ='Q4 Assumptions'!$G$79*G$12+SUMIFS('Q4 Assumptions'!$C$85:$C$133,'Q4 Assumptions'!$D$85:$D$133,'Q4 Assumptions'!$A$79,'Q4 Assumptions'!$B$85:$B$133,">="&G$10,'Q4 Assumptions'!$B$85:$B$133,"<="&G$11) | H70: ='Q4 Assumptions'!$G$79*H$12+SUMIFS('Q4 Assumptions'!$C$85:$C$133,'Q4 Assumptions'!$D$85:$D$133,'Q4 Assumptions'!$A$79,'Q4 Assumptions'!$B$85:$B$133,">="&H$10,'Q4 Assumptions'!$B$85:$B$133,"<="&H$11) | I70: ='Q4 Assumptions'!$G$79*I$12+SUMIFS('Q4 Assumptions'!$C$85:$C$133,'Q4 Assumptions'!$D$85:$D$133,'Q4 Assumptions'!$A$79,'Q4 Assumptions'!$B$85:$B$133,">="&I$10,'Q4 Assumptions'!$B$85:$B$133,"<="&I$11) | J70: ='Q4 Assumptions'!$G$79*J$12+SUMIFS('Q4 Assumptions'!$C$85:$C$133,'Q4 Assumptions'!$D$85:$D$133,'Q4 Assumptions'!$A$79,'Q4 Assumptions'!$B$85:$B$133,">="&J$10,'Q4 Assumptions'!$B$85:$B$133,"<="&J$11) | K70: ='Q4 Assumptions'!$G$79*K$12+SUMIFS('Q4 Assumptions'!$C$85:$C$133,'Q4 Assumptions'!$D$85:$D$133,'Q4 Assumptions'!$A$79,'Q4 Assumptions'!$B$85:$B$133,">="&K$10,'Q4 Assumptions'!$B$85:$B$133,"<="&K$11) | ... Q70: ='Q4 Assumptions'!$G$79*Q$12+SUMIFS('Q4 Assumptions'!$C$85:$C$133,'Q4 Assumptions'!$D$85:$D$133,'Q4 Assumptions'!$A$79,'Q4 Assumptions'!$B$85:$B$133,">="&Q$10,'Q4 Assumptions'!$B$85:$B$133,"<="&Q$11) | R70: =SUM(D70:Q70)
B71: Pending | C71: ='Q4 Assumptions'!C80 | D71: ='Q4 Assumptions'!$G$80*D$12+SUMIFS('Q4 Assumptions'!$C$85:$C$133,'Q4 Assumptions'!$D$85:$D$133,'Q4 Assumptions'!$A$80,'Q4 Assumptions'!$B$85:$B$133,">="&D$10,'Q4 Assumptions'!$B$85:$B$133,"<="&D$11) | E71: ='Q4 Assumptions'!$G$80*E$12+SUMIFS('Q4 Assumptions'!$C$85:$C$133,'Q4 Assumptions'!$D$85:$D$133,'Q4 Assumptions'!$A$80,'Q4 Assumptions'!$B$85:$B$133,">="&E$10,'Q4 Assumptions'!$B$85:$B$133,"<="&E$11) | F71: ='Q4 Assumptions'!$G$80*F$12+SUMIFS('Q4 Assumptions'!$C$85:$C$133,'Q4 Assumptions'!$D$85:$D$133,'Q4 Assumptions'!$A$80,'Q4 Assumptions'!$B$85:$B$133,">="&F$10,'Q4 Assumptions'!$B$85:$B$133,"<="&F$11) | G71: ='Q4 Assumptions'!$G$80*G$12+SUMIFS('Q4 Assumptions'!$C$85:$C$133,'Q4 Assumptions'!$D$85:$D$133,'Q4 Assumptions'!$A$80,'Q4 Assumptions'!$B$85:$B$133,">="&G$10,'Q4 Assumptions'!$B$85:$B$133,"<="&G$11) | H71: ='Q4 Assumptions'!$G$80*H$12+SUMIFS('Q4 Assumptions'!$C$85:$C$133,'Q4 Assumptions'!$D$85:$D$133,'Q4 Assumptions'!$A$80,'Q4 Assumptions'!$B$85:$B$133,">="&H$10,'Q4 Assumptions'!$B$85:$B$133,"<="&H$11) | I71: ='Q4 Assumptions'!$G$80*I$12+SUMIFS('Q4 Assumptions'!$C$85:$C$133,'Q4 Assumptions'!$D$85:$D$133,'Q4 Assumptions'!$A$80,'Q4 Assumptions'!$B$85:$B$133,">="&I$10,'Q4 Assumptions'!$B$85:$B$133,"<="&I$11) | J71: ='Q4 Assumptions'!$G$80*J$12+SUMIFS('Q4 Assumptions'!$C$85:$C$133,'Q4 Assumptions'!$D$85:$D$133,'Q4 Assumptions'!$A$80,'Q4 Assumptions'!$B$85:$B$133,">="&J$10,'Q4 Assumptions'!$B$85:$B$133,"<="&J$11) | K71: ='Q4 Assumptions'!$G$80*K$12+SUMIFS('Q4 Assumptions'!$C$85:$C$133,'Q4 Assumptions'!$D$85:$D$133,'Q4 Assumptions'!$A$80,'Q4 Assumptions'!$B$85:$B$133,">="&K$10,'Q4 Assumptions'!$B$85:$B$133,"<="&K$11) | ... Q71: ='Q4 Assumptions'!$G$80*Q$12+SUMIFS('Q4 Assumptions'!$C$85:$C$133,'Q4 Assumptions'!$D$85:$D$133,'Q4 Assumptions'!$A$80,'Q4 Assumptions'!$B$85:$B$133,">="&Q$10,'Q4 Assumptions'!$B$85:$B$133,"<="&Q$11) | R71: =SUM(D71:Q71)
A72: Net Cash Flow from Financing Activities | C72: =C60+C61+C62+C63+C65+C66+C67+C68+C69+C70+C71 | D72: =D60+D61+D62+D63+D65+D66+D67+D68+D69+D70+D71 | E72: =E60+E61+E62+E63+E65+E66+E67+E68+E69+E70+E71 | F72: =F60+F61+F62+F63+F65+F66+F67+F68+F69+F70+F71 | G72: =G60+G61+G62+G63+G65+G66+G67+G68+G69+G70+G71 | H72: =H60+H61+H62+H63+H65+H66+H67+H68+H69+H70+H71 | I72: =I60+I61+I62+I63+I65+I66+I67+I68+I69+I70+I71 | J72: =J60+J61+J62+J63+J65+J66+J67+J68+J69+J70+J71 | ... R72: =R60+R61+R62+R63+R65+R66+R67+R68+R69+R70+R71
A74: Net Cash Flow | C74: =C41+C56+C72 | D74: =D41+D56+D72 | E74: =E41+E56+E72 | F74: =F41+F56+F72 | G74: =G41+G56+G72 | H74: =H41+H56+H72 | I74: =I41+I56+I72 | J74: =J41+J56+J72 | ... R74: =R41+R56+R72
A76: Bank Balance at Beginning of Period - MAYBANK + RHB | C76: ='Q4 Assumptions'!$B$33 | D76: ='Q4 Assumptions'!$B$7+'Q4 Assumptions'!$B$8 | E76: =D77 | F76: =E77 | G76: =F77 | H76: =G77 | I76: =H77 | J76: =I77 | K76: =J77 | L76: =K77 | ... Q76: =P77 | R76: =D76
A77: Bank Balance at End of Period - MAYBANK + RHB | C77: =C76+C74 | D77: =D76+D74 | E77: =E76+E74 | F77: =F76+F74 | G77: =G76+G74 | H77: =H76+H74 | I77: =I76+I74 | J77: =J76+J74 | ... R77: =R76+R74
A78: of which MAYBANK | C78: =C77 | D78: =D99 | E78: =E99 | F78: =F99 | G78: =G99 | H78: =H99 | I78: =I99 | J78: =J99 | K78: =K99 | ... R78: =R99
A79: of which RHB | C79: n/a | D79: =D98 | E79: =E98 | F79: =F98 | G79: =G98 | H79: =H98 | I79: =I98 | J79: =J98 | K79: =K98 | ... R79: =R98
A82: MEMO — amounts already included in the lines above
A83: New-outlet sales (in Customers & Sales) | D83: ='Q4 Outlet Schedule'!I18 | E83: ='Q4 Outlet Schedule'!J18 | F83: ='Q4 Outlet Schedule'!K18 | G83: ='Q4 Outlet Schedule'!L18 | H83: ='Q4 Outlet Schedule'!M18 | I83: ='Q4 Outlet Schedule'!N18 | J83: ='Q4 Outlet Schedule'!O18 | K83: ='Q4 Outlet Schedule'!P18 | ... Q83: ='Q4 Outlet Schedule'!V18 | R83: =SUM(D83:Q83)
A84: Average no. of new outlets open in the week | D84: =D83/('Q4 Assumptions'!$B$13*D$12) | E84: =E83/('Q4 Assumptions'!$B$13*E$12) | F84: =F83/('Q4 Assumptions'!$B$13*F$12) | G84: =G83/('Q4 Assumptions'!$B$13*G$12) | H84: =H83/('Q4 Assumptions'!$B$13*H$12) | I84: =I83/('Q4 Assumptions'!$B$13*I$12) | J84: =J83/('Q4 Assumptions'!$B$13*J$12) | K84: =K83/('Q4 Assumptions'!$B$13*K$12) | ... Q84: =Q83/('Q4 Assumptions'!$B$13*Q$12)
A85: Wage increase +2% per new outlet (in Wage expenses) | D85: =SUMIFS('Q4 Assumptions'!$C$85:$C$133,'Q4 Assumptions'!$F$85:$F$133,"Y",'Q4 Assumptions'!$B$85:$B$133,">="&D$10,'Q4 Assumptions'!$B$85:$B$133,"<="&D$11)*'Q4 Assumptions'!$B$15*D84 | E85: =SUMIFS('Q4 Assumptions'!$C$85:$C$133,'Q4 Assumptions'!$F$85:$F$133,"Y",'Q4 Assumptions'!$B$85:$B$133,">="&E$10,'Q4 Assumptions'!$B$85:$B$133,"<="&E$11)*'Q4 Assumptions'!$B$15*E84 | F85: =SUMIFS('Q4 Assumptions'!$C$85:$C$133,'Q4 Assumptions'!$F$85:$F$133,"Y",'Q4 Assumptions'!$B$85:$B$133,">="&F$10,'Q4 Assumptions'!$B$85:$B$133,"<="&F$11)*'Q4 Assumptions'!$B$15*F84 | G85: =SUMIFS('Q4 Assumptions'!$C$85:$C$133,'Q4 Assumptions'!$F$85:$F$133,"Y",'Q4 Assumptions'!$B$85:$B$133,">="&G$10,'Q4 Assumptions'!$B$85:$B$133,"<="&G$11)*'Q4 Assumptions'!$B$15*G84 | H85: =SUMIFS('Q4 Assumptions'!$C$85:$C$133,'Q4 Assumptions'!$F$85:$F$133,"Y",'Q4 Assumptions'!$B$85:$B$133,">="&H$10,'Q4 Assumptions'!$B$85:$B$133,"<="&H$11)*'Q4 Assumptions'!$B$15*H84 | I85: =SUMIFS('Q4 Assumptions'!$C$85:$C$133,'Q4 Assumptions'!$F$85:$F$133,"Y",'Q4 Assumptions'!$B$85:$B$133,">="&I$10,'Q4 Assumptions'!$B$85:$B$133,"<="&I$11)*'Q4 Assumptions'!$B$15*I84 | J85: =SUMIFS('Q4 Assumptions'!$C$85:$C$133,'Q4 Assumptions'!$F$85:$F$133,"Y",'Q4 Assumptions'!$B$85:$B$133,">="&J$10,'Q4 Assumptions'!$B$85:$B$133,"<="&J$11)*'Q4 Assumptions'!$B$15*J84 | K85: =SUMIFS('Q4 Assumptions'!$C$85:$C$133,'Q4 Assumptions'!$F$85:$F$133,"Y",'Q4 Assumptions'!$B$85:$B$133,">="&K$10,'Q4 Assumptions'!$B$85:$B$133,"<="&K$11)*'Q4 Assumptions'!$B$15*K84 | ... Q85: =SUMIFS('Q4 Assumptions'!$C$85:$C$133,'Q4 Assumptions'!$F$85:$F$133,"Y",'Q4 Assumptions'!$B$85:$B$133,">="&Q$10,'Q4 Assumptions'!$B$85:$B$133,"<="&Q$11)*'Q4 Assumptions'!$B$15*Q84 | R85: =SUM(D85:Q85)
A86: Upkeep increase +1% per new outlet (in Branch Expenditure & Upkeep) | D86: ='Q4 Assumptions'!$G$52*D$12*'Q4 Assumptions'!$B$16*D84 | E86: ='Q4 Assumptions'!$G$52*E$12*'Q4 Assumptions'!$B$16*E84 | F86: ='Q4 Assumptions'!$G$52*F$12*'Q4 Assumptions'!$B$16*F84 | G86: ='Q4 Assumptions'!$G$52*G$12*'Q4 Assumptions'!$B$16*G84 | H86: ='Q4 Assumptions'!$G$52*H$12*'Q4 Assumptions'!$B$16*H84 | I86: ='Q4 Assumptions'!$G$52*I$12*'Q4 Assumptions'!$B$16*I84 | J86: ='Q4 Assumptions'!$G$52*J$12*'Q4 Assumptions'!$B$16*J84 | K86: ='Q4 Assumptions'!$G$52*K$12*'Q4 Assumptions'!$B$16*K84 | ... Q86: ='Q4 Assumptions'!$G$52*Q$12*'Q4 Assumptions'!$B$16*Q84 | R86: =SUM(D86:Q86)
A87: Inventory increase +3% per new outlet (in Inventory purchases) | D87: ='Q4 Assumptions'!$G$41*D$12*'Q4 Assumptions'!$B$17*D84 | E87: ='Q4 Assumptions'!$G$41*E$12*'Q4 Assumptions'!$B$17*E84 | F87: ='Q4 Assumptions'!$G$41*F$12*'Q4 Assumptions'!$B$17*F84 | G87: ='Q4 Assumptions'!$G$41*G$12*'Q4 Assumptions'!$B$17*G84 | H87: ='Q4 Assumptions'!$G$41*H$12*'Q4 Assumptions'!$B$17*H84 | I87: ='Q4 Assumptions'!$G$41*I$12*'Q4 Assumptions'!$B$17*I84 | J87: ='Q4 Assumptions'!$G$41*J$12*'Q4 Assumptions'!$B$17*J84 | K87: ='Q4 Assumptions'!$G$41*K$12*'Q4 Assumptions'!$B$17*K84 | ... Q87: ='Q4 Assumptions'!$G$41*Q$12*'Q4 Assumptions'!$B$17*Q84 | R87: =SUM(D87:Q87)
A88: New-outlet rental 5% of sales (in Rental) | D88: =-D83*'Q4 Assumptions'!$B$14 | E88: =-E83*'Q4 Assumptions'!$B$14 | F88: =-F83*'Q4 Assumptions'!$B$14 | G88: =-G83*'Q4 Assumptions'!$B$14 | H88: =-H83*'Q4 Assumptions'!$B$14 | I88: =-I83*'Q4 Assumptions'!$B$14 | J88: =-J83*'Q4 Assumptions'!$B$14 | K88: =-K83*'Q4 Assumptions'!$B$14 | ... Q88: =-Q83*'Q4 Assumptions'!$B$14 | R88: =SUM(D88:Q88)
A89: Capex new outlets (Capex New Branches) | D89: =-SUMIFS('Q4 Outlet Schedule'!$F$6:$F$17,'Q4 Outlet Schedule'!$G$6:$G$17,">="&D$10,'Q4 Outlet Schedule'!$G$6:$G$17,"<="&D$11) | E89: =-SUMIFS('Q4 Outlet Schedule'!$F$6:$F$17,'Q4 Outlet Schedule'!$G$6:$G$17,">="&E$10,'Q4 Outlet Schedule'!$G$6:$G$17,"<="&E$11) | F89: =-SUMIFS('Q4 Outlet Schedule'!$F$6:$F$17,'Q4 Outlet Schedule'!$G$6:$G$17,">="&F$10,'Q4 Outlet Schedule'!$G$6:$G$17,"<="&F$11) | G89: =-SUMIFS('Q4 Outlet Schedule'!$F$6:$F$17,'Q4 Outlet Schedule'!$G$6:$G$17,">="&G$10,'Q4 Outlet Schedule'!$G$6:$G$17,"<="&G$11) | H89: =-SUMIFS('Q4 Outlet Schedule'!$F$6:$F$17,'Q4 Outlet Schedule'!$G$6:$G$17,">="&H$10,'Q4 Outlet Schedule'!$G$6:$G$17,"<="&H$11) | I89: =-SUMIFS('Q4 Outlet Schedule'!$F$6:$F$17,'Q4 Outlet Schedule'!$G$6:$G$17,">="&I$10,'Q4 Outlet Schedule'!$G$6:$G$17,"<="&I$11) | J89: =-SUMIFS('Q4 Outlet Schedule'!$F$6:$F$17,'Q4 Outlet Schedule'!$G$6:$G$17,">="&J$10,'Q4 Outlet Schedule'!$G$6:$G$17,"<="&J$11) | K89: =-SUMIFS('Q4 Outlet Schedule'!$F$6:$F$17,'Q4 Outlet Schedule'!$G$6:$G$17,">="&K$10,'Q4 Outlet Schedule'!$G$6:$G$17,"<="&K$11) | ... Q89: =-SUMIFS('Q4 Outlet Schedule'!$F$6:$F$17,'Q4 Outlet Schedule'!$G$6:$G$17,">="&Q$10,'Q4 Outlet Schedule'!$G$6:$G$17,"<="&Q$11) | R89: =SUM(D89:Q89)
A90: RHB cash deposits (in Customers & Sales) | D90: ='Q4 Assumptions'!$B$27*D$12 | E90: ='Q4 Assumptions'!$B$27*E$12 | F90: ='Q4 Assumptions'!$B$27*F$12 | G90: ='Q4 Assumptions'!$B$27*G$12 | H90: ='Q4 Assumptions'!$B$27*H$12 | I90: ='Q4 Assumptions'!$B$27*I$12 | J90: ='Q4 Assumptions'!$B$27*J$12 | K90: ='Q4 Assumptions'!$B$27*K$12 | ... Q90: ='Q4 Assumptions'!$B$27*Q$12 | R90: =SUM(D90:Q90)
A92: SPLIT BY BANK — RHB is topped up from Maybank only when payroll needs it (transfer nets to zero combined)
A93: RHB opening balance | D93: ='Q4 Assumptions'!$B$8 | E93: =D98 | F93: =E98 | G93: =F98 | H93: =G98 | I93: =H98 | J93: =I98 | K93: =J98 | L93: =K98 | ... Q93: =P98 | R93: =D93
A94: RHB cash deposits | D94: =D90 | E94: =E90 | F94: =F90 | G94: =G90 | H94: =H90 | I94: =I90 | J94: =J90 | K94: =K90 | ... Q94: =Q90 | R94: =SUM(D94:Q94)
A95: RHB licensing / payroll (incl. +2% per outlet) / bonus | D95: =SUMIFS('Q4 Assumptions'!$C$85:$C$133,'Q4 Assumptions'!$E$85:$E$133,"RHB",'Q4 Assumptions'!$B$85:$B$133,">="&D$10,'Q4 Assumptions'!$B$85:$B$133,"<="&D$11)+SUMIFS('Q4 Assumptions'!$C$85:$C$133,'Q4 Assumptions'!$E$85:$E$133,"RHB",'Q4 Assumptions'!$F$85:$F$133,"Y",'Q4 Assumptions'!$B$85:$B$133,">="&D$10,'Q4 Assumptions'!$B$85:$B$133,"<="&D$11)*'Q4 Assumptions'!$B$15*D84 | E95: =SUMIFS('Q4 Assumptions'!$C$85:$C$133,'Q4 Assumptions'!$E$85:$E$133,"RHB",'Q4 Assumptions'!$B$85:$B$133,">="&E$10,'Q4 Assumptions'!$B$85:$B$133,"<="&E$11)+SUMIFS('Q4 Assumptions'!$C$85:$C$133,'Q4 Assumptions'!$E$85:$E$133,"RHB",'Q4 Assumptions'!$F$85:$F$133,"Y",'Q4 Assumptions'!$B$85:$B$133,">="&E$10,'Q4 Assumptions'!$B$85:$B$133,"<="&E$11)*'Q4 Assumptions'!$B$15*E84 | F95: =SUMIFS('Q4 Assumptions'!$C$85:$C$133,'Q4 Assumptions'!$E$85:$E$133,"RHB",'Q4 Assumptions'!$B$85:$B$133,">="&F$10,'Q4 Assumptions'!$B$85:$B$133,"<="&F$11)+SUMIFS('Q4 Assumptions'!$C$85:$C$133,'Q4 Assumptions'!$E$85:$E$133,"RHB",'Q4 Assumptions'!$F$85:$F$133,"Y",'Q4 Assumptions'!$B$85:$B$133,">="&F$10,'Q4 Assumptions'!$B$85:$B$133,"<="&F$11)*'Q4 Assumptions'!$B$15*F84 | G95: =SUMIFS('Q4 Assumptions'!$C$85:$C$133,'Q4 Assumptions'!$E$85:$E$133,"RHB",'Q4 Assumptions'!$B$85:$B$133,">="&G$10,'Q4 Assumptions'!$B$85:$B$133,"<="&G$11)+SUMIFS('Q4 Assumptions'!$C$85:$C$133,'Q4 Assumptions'!$E$85:$E$133,"RHB",'Q4 Assumptions'!$F$85:$F$133,"Y",'Q4 Assumptions'!$B$85:$B$133,">="&G$10,'Q4 Assumptions'!$B$85:$B$133,"<="&G$11)*'Q4 Assumptions'!$B$15*G84 | H95: =SUMIFS('Q4 Assumptions'!$C$85:$C$133,'Q4 Assumptions'!$E$85:$E$133,"RHB",'Q4 Assumptions'!$B$85:$B$133,">="&H$10,'Q4 Assumptions'!$B$85:$B$133,"<="&H$11)+SUMIFS('Q4 Assumptions'!$C$85:$C$133,'Q4 Assumptions'!$E$85:$E$133,"RHB",'Q4 Assumptions'!$F$85:$F$133,"Y",'Q4 Assumptions'!$B$85:$B$133,">="&H$10,'Q4 Assumptions'!$B$85:$B$133,"<="&H$11)*'Q4 Assumptions'!$B$15*H84 | I95: =SUMIFS('Q4 Assumptions'!$C$85:$C$133,'Q4 Assumptions'!$E$85:$E$133,"RHB",'Q4 Assumptions'!$B$85:$B$133,">="&I$10,'Q4 Assumptions'!$B$85:$B$133,"<="&I$11)+SUMIFS('Q4 Assumptions'!$C$85:$C$133,'Q4 Assumptions'!$E$85:$E$133,"RHB",'Q4 Assumptions'!$F$85:$F$133,"Y",'Q4 Assumptions'!$B$85:$B$133,">="&I$10,'Q4 Assumptions'!$B$85:$B$133,"<="&I$11)*'Q4 Assumptions'!$B$15*I84 | J95: =SUMIFS('Q4 Assumptions'!$C$85:$C$133,'Q4 Assumptions'!$E$85:$E$133,"RHB",'Q4 Assumptions'!$B$85:$B$133,">="&J$10,'Q4 Assumptions'!$B$85:$B$133,"<="&J$11)+SUMIFS('Q4 Assumptions'!$C$85:$C$133,'Q4 Assumptions'!$E$85:$E$133,"RHB",'Q4 Assumptions'!$F$85:$F$133,"Y",'Q4 Assumptions'!$B$85:$B$133,">="&J$10,'Q4 Assumptions'!$B$85:$B$133,"<="&J$11)*'Q4 Assumptions'!$B$15*J84 | K95: =SUMIFS('Q4 Assumptions'!$C$85:$C$133,'Q4 Assumptions'!$E$85:$E$133,"RHB",'Q4 Assumptions'!$B$85:$B$133,">="&K$10,'Q4 Assumptions'!$B$85:$B$133,"<="&K$11)+SUMIFS('Q4 Assumptions'!$C$85:$C$133,'Q4 Assumptions'!$E$85:$E$133,"RHB",'Q4 Assumptions'!$F$85:$F$133,"Y",'Q4 Assumptions'!$B$85:$B$133,">="&K$10,'Q4 Assumptions'!$B$85:$B$133,"<="&K$11)*'Q4 Assumptions'!$B$15*K84 | ... Q95: =SUMIFS('Q4 Assumptions'!$C$85:$C$133,'Q4 Assumptions'!$E$85:$E$133,"RHB",'Q4 Assumptions'!$B$85:$B$133,">="&Q$10,'Q4 Assumptions'!$B$85:$B$133,"<="&Q$11)+SUMIFS('Q4 Assumptions'!$C$85:$C$133,'Q4 Assumptions'!$E$85:$E$133,"RHB",'Q4 Assumptions'!$F$85:$F$133,"Y",'Q4 Assumptions'!$B$85:$B$133,">="&Q$10,'Q4 Assumptions'!$B$85:$B$133,"<="&Q$11)*'Q4 Assumptions'!$B$15*Q84 | R95: =SUM(D95:Q95)
A96: RHB balance before top-up | D96: =D93+D94+D95 | E96: =E93+E94+E95 | F96: =F93+F94+F95 | G96: =G93+G94+G95 | H96: =H93+H94+H95 | I96: =I93+I94+I95 | J96: =J93+J94+J95 | K96: =K93+K94+K95 | ... Q96: =Q93+Q94+Q95
A97: Transfer Maybank → RHB | D97: =MAX(0,'Q4 Assumptions'!$B$29-D96) | E97: =MAX(0,'Q4 Assumptions'!$B$29-E96) | F97: =MAX(0,'Q4 Assumptions'!$B$29-F96) | G97: =MAX(0,'Q4 Assumptions'!$B$29-G96) | H97: =MAX(0,'Q4 Assumptions'!$B$29-H96) | I97: =MAX(0,'Q4 Assumptions'!$B$29-I96) | J97: =MAX(0,'Q4 Assumptions'!$B$29-J96) | K97: =MAX(0,'Q4 Assumptions'!$B$29-K96) | ... Q97: =MAX(0,'Q4 Assumptions'!$B$29-Q96) | R97: =SUM(D97:Q97)
A98: RHB closing balance | D98: =D96+D97 | E98: =E96+E97 | F98: =F96+F97 | G98: =G96+G97 | H98: =H96+H97 | I98: =I96+I97 | J98: =J96+J97 | K98: =K96+K97 | ... Q98: =Q96+Q97 | R98: =Q98
A99: Maybank closing balance | D99: =D77-D98 | E99: =E77-E98 | F99: =F77-F98 | G99: =G77-G98 | H99: =H77-H98 | I99: =I77-I98 | J99: =J77-J98 | K99: =K77-K98 | ... Q99: =Q77-Q98 | R99: =Q99
A101: Check: Sept'26 column net vs statement −987,655.35 (should be 0) | C101: =ROUND(C74-(-987655.35),2)

Sheet Q4 Outlet Schedule
A1: New Outlet Schedule — sales and capex timing (Q4 2026)
A2: Sales = RM/day × days open in the week (from grand-opening day). Capex balance paid on GO − lead days (not earlier than 1 Oct). ICOMSRWK excluded until GO date confirmed.
H3: Week start | I3: ='Q4 Weekly Cash Flow'!D10 | J3: ='Q4 Weekly Cash Flow'!E10 | K3: ='Q4 Weekly Cash Flow'!F10 | L3: ='Q4 Weekly Cash Flow'!G10 | M3: ='Q4 Weekly Cash Flow'!H10 | N3: ='Q4 Weekly Cash Flow'!I10 | O3: ='Q4 Weekly Cash Flow'!J10 | P3: ='Q4 Weekly Cash Flow'!K10 | ... V3: ='Q4 Weekly Cash Flow'!Q10
H4: Week end | I4: ='Q4 Weekly Cash Flow'!D11 | J4: ='Q4 Weekly Cash Flow'!E11 | K4: ='Q4 Weekly Cash Flow'!F11 | L4: ='Q4 Weekly Cash Flow'!G11 | M4: ='Q4 Weekly Cash Flow'!H11 | N4: ='Q4 Weekly Cash Flow'!I11 | O4: ='Q4 Weekly Cash Flow'!J11 | P4: ='Q4 Weekly Cash Flow'!K11 | ... V4: ='Q4 Weekly Cash Flow'!Q11
A5: No. | B5: Project | C5: Grand Opening | D5: Capex (RM) | E5: Paid to 30 Sep | F5: Capex balance | G5: Capex pay date | H5: Sales/day | I5: Week 1 | J5: Week 2 | K5: Week 3 | L5: Week 4 | M5: Week 5 | N5: Week 6 | O5: Week 7 | P5: Week 8 | Q5: Week 9 | R5: Week 10 | S5: Week 11 | T5: Week 12 | U5: Week 13 | V5: Week 14 | W5: Q4 sales
A6: ='Outlet Plan'!A2 | B6: ='Outlet Plan'!B2 | C6: ='Outlet Plan'!C2 | D6: ='Q4 Assumptions'!$B$19 | E6: ='Q4 Assumptions'!$B$21 | F6: =IF(ISNUMBER(C6),D6-E6,0) | G6: =IF(ISNUMBER(C6),MAX(C6-'Q4 Assumptions'!$B$18,'Q4 Assumptions'!$B$5),"TBD") | H6: ='Q4 Assumptions'!$B$13 | I6: =IF(ISNUMBER($C6),MAX(0,I$4-MAX(I$3,$C6)+1)*$H6,0) | J6: =IF(ISNUMBER($C6),MAX(0,J$4-MAX(J$3,$C6)+1)*$H6,0) | K6: =IF(ISNUMBER($C6),MAX(0,K$4-MAX(K$3,$C6)+1)*$H6,0) | L6: =IF(ISNUMBER($C6),MAX(0,L$4-MAX(L$3,$C6)+1)*$H6,0) | M6: =IF(ISNUMBER($C6),MAX(0,M$4-MAX(M$3,$C6)+1)*$H6,0) | N6: =IF(ISNUMBER($C6),MAX(0,N$4-MAX(N$3,$C6)+1)*$H6,0) | O6: =IF(ISNUMBER($C6),MAX(0,O$4-MAX(O$3,$C6)+1)*$H6,0) | P6: =IF(ISNUMBER($C6),MAX(0,P$4-MAX(P$3,$C6)+1)*$H6,0) | ... V6: =IF(ISNUMBER($C6),MAX(0,V$4-MAX(V$3,$C6)+1)*$H6,0) | W6: =SUM(I6:V6)
A7: ='Outlet Plan'!A3 | B7: ='Outlet Plan'!B3 | C7: ='Outlet Plan'!C3 | D7: ='Q4 Assumptions'!$B$19 | E7: ='Q4 Assumptions'!$B$22 | F7: =IF(ISNUMBER(C7),D7-E7,0) | G7: =IF(ISNUMBER(C7),MAX(C7-'Q4 Assumptions'!$B$18,'Q4 Assumptions'!$B$5),"TBD") | H7: ='Q4 Assumptions'!$B$13 | I7: =IF(ISNUMBER($C7),MAX(0,I$4-MAX(I$3,$C7)+1)*$H7,0) | J7: =IF(ISNUMBER($C7),MAX(0,J$4-MAX(J$3,$C7)+1)*$H7,0) | K7: =IF(ISNUMBER($C7),MAX(0,K$4-MAX(K$3,$C7)+1)*$H7,0) | L7: =IF(ISNUMBER($C7),MAX(0,L$4-MAX(L$3,$C7)+1)*$H7,0) | M7: =IF(ISNUMBER($C7),MAX(0,M$4-MAX(M$3,$C7)+1)*$H7,0) | N7: =IF(ISNUMBER($C7),MAX(0,N$4-MAX(N$3,$C7)+1)*$H7,0) | O7: =IF(ISNUMBER($C7),MAX(0,O$4-MAX(O$3,$C7)+1)*$H7,0) | P7: =IF(ISNUMBER($C7),MAX(0,P$4-MAX(P$3,$C7)+1)*$H7,0) | ... V7: =IF(ISNUMBER($C7),MAX(0,V$4-MAX(V$3,$C7)+1)*$H7,0) | W7: =SUM(I7:V7)
A8: ='Outlet Plan'!A4 | B8: ='Outlet Plan'!B4 | C8: ='Outlet Plan'!C4 | D8: ='Q4 Assumptions'!$B$19 | E8: ='Q4 Assumptions'!$B$23 | F8: =IF(ISNUMBER(C8),D8-E8,0) | G8: =IF(ISNUMBER(C8),MAX(C8-'Q4 Assumptions'!$B$18,'Q4 Assumptions'!$B$5),"TBD") | H8: ='Q4 Assumptions'!$B$13 | I8: =IF(ISNUMBER($C8),MAX(0,I$4-MAX(I$3,$C8)+1)*$H8,0) | J8: =IF(ISNUMBER($C8),MAX(0,J$4-MAX(J$3,$C8)+1)*$H8,0) | K8: =IF(ISNUMBER($C8),MAX(0,K$4-MAX(K$3,$C8)+1)*$H8,0) | L8: =IF(ISNUMBER($C8),MAX(0,L$4-MAX(L$3,$C8)+1)*$H8,0) | M8: =IF(ISNUMBER($C8),MAX(0,M$4-MAX(M$3,$C8)+1)*$H8,0) | N8: =IF(ISNUMBER($C8),MAX(0,N$4-MAX(N$3,$C8)+1)*$H8,0) | O8: =IF(ISNUMBER($C8),MAX(0,O$4-MAX(O$3,$C8)+1)*$H8,0) | P8: =IF(ISNUMBER($C8),MAX(0,P$4-MAX(P$3,$C8)+1)*$H8,0) | ... V8: =IF(ISNUMBER($C8),MAX(0,V$4-MAX(V$3,$C8)+1)*$H8,0) | W8: =SUM(I8:V8)
A9: ='Outlet Plan'!A5 | B9: ='Outlet Plan'!B5 | C9: ='Outlet Plan'!C5 | D9: ='Q4 Assumptions'!$B$20 | E9: 0 | F9: =IF(ISNUMBER(C9),D9-E9,0) | G9: =IF(ISNUMBER(C9),MAX(C9-'Q4 Assumptions'!$B$18,'Q4 Assumptions'!$B$5),"TBD") | H9: ='Q4 Assumptions'!$B$13 | I9: =IF(ISNUMBER($C9),MAX(0,I$4-MAX(I$3,$C9)+1)*$H9,0) | J9: =IF(ISNUMBER($C9),MAX(0,J$4-MAX(J$3,$C9)+1)*$H9,0) | K9: =IF(ISNUMBER($C9),MAX(0,K$4-MAX(K$3,$C9)+1)*$H9,0) | L9: =IF(ISNUMBER($C9),MAX(0,L$4-MAX(L$3,$C9)+1)*$H9,0) | M9: =IF(ISNUMBER($C9),MAX(0,M$4-MAX(M$3,$C9)+1)*$H9,0) | N9: =IF(ISNUMBER($C9),MAX(0,N$4-MAX(N$3,$C9)+1)*$H9,0) | O9: =IF(ISNUMBER($C9),MAX(0,O$4-MAX(O$3,$C9)+1)*$H9,0) | P9: =IF(ISNUMBER($C9),MAX(0,P$4-MAX(P$3,$C9)+1)*$H9,0) | ... V9: =IF(ISNUMBER($C9),MAX(0,V$4-MAX(V$3,$C9)+1)*$H9,0) | W9: =SUM(I9:V9)
A10: ='Outlet Plan'!A6 | B10: ='Outlet Plan'!B6 | C10: ='Outlet Plan'!C6 | D10: ='Q4 Assumptions'!$B$20 | E10: 0 | F10: =IF(ISNUMBER(C10),D10-E10,0) | G10: =IF(ISNUMBER(C10),MAX(C10-'Q4 Assumptions'!$B$18,'Q4 Assumptions'!$B$5),"TBD") | H10: ='Q4 Assumptions'!$B$13 | I10: =IF(ISNUMBER($C10),MAX(0,I$4-MAX(I$3,$C10)+1)*$H10,0) | J10: =IF(ISNUMBER($C10),MAX(0,J$4-MAX(J$3,$C10)+1)*$H10,0) | K10: =IF(ISNUMBER($C10),MAX(0,K$4-MAX(K$3,$C10)+1)*$H10,0) | L10: =IF(ISNUMBER($C10),MAX(0,L$4-MAX(L$3,$C10)+1)*$H10,0) | M10: =IF(ISNUMBER($C10),MAX(0,M$4-MAX(M$3,$C10)+1)*$H10,0) | N10: =IF(ISNUMBER($C10),MAX(0,N$4-MAX(N$3,$C10)+1)*$H10,0) | O10: =IF(ISNUMBER($C10),MAX(0,O$4-MAX(O$3,$C10)+1)*$H10,0) | P10: =IF(ISNUMBER($C10),MAX(0,P$4-MAX(P$3,$C10)+1)*$H10,0) | ... V10: =IF(ISNUMBER($C10),MAX(0,V$4-MAX(V$3,$C10)+1)*$H10,0) | W10: =SUM(I10:V10)
A11: ='Outlet Plan'!A7 | B11: ='Outlet Plan'!B7 | C11: ='Outlet Plan'!C7 | D11: ='Q4 Assumptions'!$B$20 | E11: 0 | F11: =IF(ISNUMBER(C11),D11-E11,0) | G11: =IF(ISNUMBER(C11),MAX(C11-'Q4 Assumptions'!$B$18,'Q4 Assumptions'!$B$5),"TBD") | H11: ='Q4 Assumptions'!$B$13 | I11: =IF(ISNUMBER($C11),MAX(0,I$4-MAX(I$3,$C11)+1)*$H11,0) | J11: =IF(ISNUMBER($C11),MAX(0,J$4-MAX(J$3,$C11)+1)*$H11,0) | K11: =IF(ISNUMBER($C11),MAX(0,K$4-MAX(K$3,$C11)+1)*$H11,0) | L11: =IF(ISNUMBER($C11),MAX(0,L$4-MAX(L$3,$C11)+1)*$H11,0) | M11: =IF(ISNUMBER($C11),MAX(0,M$4-MAX(M$3,$C11)+1)*$H11,0) | N11: =IF(ISNUMBER($C11),MAX(0,N$4-MAX(N$3,$C11)+1)*$H11,0) | O11: =IF(ISNUMBER($C11),MAX(0,O$4-MAX(O$3,$C11)+1)*$H11,0) | P11: =IF(ISNUMBER($C11),MAX(0,P$4-MAX(P$3,$C11)+1)*$H11,0) | ... V11: =IF(ISNUMBER($C11),MAX(0,V$4-MAX(V$3,$C11)+1)*$H11,0) | W11: =SUM(I11:V11)
A12: ='Outlet Plan'!A8 | B12: ='Outlet Plan'!B8 | C12: ='Outlet Plan'!C8 | D12: ='Q4 Assumptions'!$B$20 | E12: 0 | F12: =IF(ISNUMBER(C12),D12-E12,0) | G12: =IF(ISNUMBER(C12),MAX(C12-'Q4 Assumptions'!$B$18,'Q4 Assumptions'!$B$5),"TBD") | H12: ='Q4 Assumptions'!$B$13 | I12: =IF(ISNUMBER($C12),MAX(0,I$4-MAX(I$3,$C12)+1)*$H12,0) | J12: =IF(ISNUMBER($C12),MAX(0,J$4-MAX(J$3,$C12)+1)*$H12,0) | K12: =IF(ISNUMBER($C12),MAX(0,K$4-MAX(K$3,$C12)+1)*$H12,0) | L12: =IF(ISNUMBER($C12),MAX(0,L$4-MAX(L$3,$C12)+1)*$H12,0) | M12: =IF(ISNUMBER($C12),MAX(0,M$4-MAX(M$3,$C12)+1)*$H12,0) | N12: =IF(ISNUMBER($C12),MAX(0,N$4-MAX(N$3,$C12)+1)*$H12,0) | O12: =IF(ISNUMBER($C12),MAX(0,O$4-MAX(O$3,$C12)+1)*$H12,0) | P12: =IF(ISNUMBER($C12),MAX(0,P$4-MAX(P$3,$C12)+1)*$H12,0) | ... V12: =IF(ISNUMBER($C12),MAX(0,V$4-MAX(V$3,$C12)+1)*$H12,0) | W12: =SUM(I12:V12)
A13: ='Outlet Plan'!A9 | B13: ='Outlet Plan'!B9 | C13: ='Outlet Plan'!C9 | D13: ='Q4 Assumptions'!$B$20 | E13: 0 | F13: =IF(ISNUMBER(C13),D13-E13,0) | G13: =IF(ISNUMBER(C13),MAX(C13-'Q4 Assumptions'!$B$18,'Q4 Assumptions'!$B$5),"TBD") | H13: ='Q4 Assumptions'!$B$13 | I13: =IF(ISNUMBER($C13),MAX(0,I$4-MAX(I$3,$C13)+1)*$H13,0) | J13: =IF(ISNUMBER($C13),MAX(0,J$4-MAX(J$3,$C13)+1)*$H13,0) | K13: =IF(ISNUMBER($C13),MAX(0,K$4-MAX(K$3,$C13)+1)*$H13,0) | L13: =IF(ISNUMBER($C13),MAX(0,L$4-MAX(L$3,$C13)+1)*$H13,0) | M13: =IF(ISNUMBER($C13),MAX(0,M$4-MAX(M$3,$C13)+1)*$H13,0) | N13: =IF(ISNUMBER($C13),MAX(0,N$4-MAX(N$3,$C13)+1)*$H13,0) | O13: =IF(ISNUMBER($C13),MAX(0,O$4-MAX(O$3,$C13)+1)*$H13,0) | P13: =IF(ISNUMBER($C13),MAX(0,P$4-MAX(P$3,$C13)+1)*$H13,0) | ... V13: =IF(ISNUMBER($C13),MAX(0,V$4-MAX(V$3,$C13)+1)*$H13,0) | W13: =SUM(I13:V13)
A14: ='Outlet Plan'!A10 | B14: ='Outlet Plan'!B10 | C14: ='Outlet Plan'!C10 | D14: ='Q4 Assumptions'!$B$20 | E14: 0 | F14: =IF(ISNUMBER(C14),D14-E14,0) | G14: =IF(ISNUMBER(C14),MAX(C14-'Q4 Assumptions'!$B$18,'Q4 Assumptions'!$B$5),"TBD") | H14: ='Q4 Assumptions'!$B$13 | I14: =IF(ISNUMBER($C14),MAX(0,I$4-MAX(I$3,$C14)+1)*$H14,0) | J14: =IF(ISNUMBER($C14),MAX(0,J$4-MAX(J$3,$C14)+1)*$H14,0) | K14: =IF(ISNUMBER($C14),MAX(0,K$4-MAX(K$3,$C14)+1)*$H14,0) | L14: =IF(ISNUMBER($C14),MAX(0,L$4-MAX(L$3,$C14)+1)*$H14,0) | M14: =IF(ISNUMBER($C14),MAX(0,M$4-MAX(M$3,$C14)+1)*$H14,0) | N14: =IF(ISNUMBER($C14),MAX(0,N$4-MAX(N$3,$C14)+1)*$H14,0) | O14: =IF(ISNUMBER($C14),MAX(0,O$4-MAX(O$3,$C14)+1)*$H14,0) | P14: =IF(ISNUMBER($C14),MAX(0,P$4-MAX(P$3,$C14)+1)*$H14,0) | ... V14: =IF(ISNUMBER($C14),MAX(0,V$4-MAX(V$3,$C14)+1)*$H14,0) | W14: =SUM(I14:V14)
A15: ='Outlet Plan'!A11 | B15: ='Outlet Plan'!B11 | C15: ='Outlet Plan'!C11 | D15: ='Q4 Assumptions'!$B$20 | E15: 0 | F15: =IF(ISNUMBER(C15),D15-E15,0) | G15: =IF(ISNUMBER(C15),MAX(C15-'Q4 Assumptions'!$B$18,'Q4 Assumptions'!$B$5),"TBD") | H15: ='Q4 Assumptions'!$B$13 | I15: =IF(ISNUMBER($C15),MAX(0,I$4-MAX(I$3,$C15)+1)*$H15,0) | J15: =IF(ISNUMBER($C15),MAX(0,J$4-MAX(J$3,$C15)+1)*$H15,0) | K15: =IF(ISNUMBER($C15),MAX(0,K$4-MAX(K$3,$C15)+1)*$H15,0) | L15: =IF(ISNUMBER($C15),MAX(0,L$4-MAX(L$3,$C15)+1)*$H15,0) | M15: =IF(ISNUMBER($C15),MAX(0,M$4-MAX(M$3,$C15)+1)*$H15,0) | N15: =IF(ISNUMBER($C15),MAX(0,N$4-MAX(N$3,$C15)+1)*$H15,0) | O15: =IF(ISNUMBER($C15),MAX(0,O$4-MAX(O$3,$C15)+1)*$H15,0) | P15: =IF(ISNUMBER($C15),MAX(0,P$4-MAX(P$3,$C15)+1)*$H15,0) | ... V15: =IF(ISNUMBER($C15),MAX(0,V$4-MAX(V$3,$C15)+1)*$H15,0) | W15: =SUM(I15:V15)
A16: ='Outlet Plan'!A12 | B16: ='Outlet Plan'!B12 | C16: ='Outlet Plan'!C12 | D16: ='Q4 Assumptions'!$B$20 | E16: 0 | F16: =IF(ISNUMBER(C16),D16-E16,0) | G16: =IF(ISNUMBER(C16),MAX(C16-'Q4 Assumptions'!$B$18,'Q4 Assumptions'!$B$5),"TBD") | H16: ='Q4 Assumptions'!$B$13 | I16: =IF(ISNUMBER($C16),MAX(0,I$4-MAX(I$3,$C16)+1)*$H16,0) | J16: =IF(ISNUMBER($C16),MAX(0,J$4-MAX(J$3,$C16)+1)*$H16,0) | K16: =IF(ISNUMBER($C16),MAX(0,K$4-MAX(K$3,$C16)+1)*$H16,0) | L16: =IF(ISNUMBER($C16),MAX(0,L$4-MAX(L$3,$C16)+1)*$H16,0) | M16: =IF(ISNUMBER($C16),MAX(0,M$4-MAX(M$3,$C16)+1)*$H16,0) | N16: =IF(ISNUMBER($C16),MAX(0,N$4-MAX(N$3,$C16)+1)*$H16,0) | O16: =IF(ISNUMBER($C16),MAX(0,O$4-MAX(O$3,$C16)+1)*$H16,0) | P16: =IF(ISNUMBER($C16),MAX(0,P$4-MAX(P$3,$C16)+1)*$H16,0) | ... V16: =IF(ISNUMBER($C16),MAX(0,V$4-MAX(V$3,$C16)+1)*$H16,0) | W16: =SUM(I16:V16)
A17: ='Outlet Plan'!A13 | B17: ='Outlet Plan'!B13 | C17: ='Outlet Plan'!C13 | D17: ='Q4 Assumptions'!$B$20 | E17: 0 | F17: =IF(ISNUMBER(C17),D17-E17,0) | G17: =IF(ISNUMBER(C17),MAX(C17-'Q4 Assumptions'!$B$18,'Q4 Assumptions'!$B$5),"TBD") | H17: ='Q4 Assumptions'!$B$13 | I17: =IF(ISNUMBER($C17),MAX(0,I$4-MAX(I$3,$C17)+1)*$H17,0) | J17: =IF(ISNUMBER($C17),MAX(0,J$4-MAX(J$3,$C17)+1)*$H17,0) | K17: =IF(ISNUMBER($C17),MAX(0,K$4-MAX(K$3,$C17)+1)*$H17,0) | L17: =IF(ISNUMBER($C17),MAX(0,L$4-MAX(L$3,$C17)+1)*$H17,0) | M17: =IF(ISNUMBER($C17),MAX(0,M$4-MAX(M$3,$C17)+1)*$H17,0) | N17: =IF(ISNUMBER($C17),MAX(0,N$4-MAX(N$3,$C17)+1)*$H17,0) | O17: =IF(ISNUMBER($C17),MAX(0,O$4-MAX(O$3,$C17)+1)*$H17,0) | P17: =IF(ISNUMBER($C17),MAX(0,P$4-MAX(P$3,$C17)+1)*$H17,0) | ... V17: =IF(ISNUMBER($C17),MAX(0,V$4-MAX(V$3,$C17)+1)*$H17,0) | W17: =SUM(I17:V17)
B18: Total | D18: =SUM(D6:D17) | E18: =SUM(E6:E17) | F18: =SUM(F6:F17) | I18: =SUM(I6:I17) | J18: =SUM(J6:J17) | K18: =SUM(K6:K17) | L18: =SUM(L6:L17) | M18: =SUM(M6:M17) | N18: =SUM(N6:N17) | O18: =SUM(O6:O17) | P18: =SUM(P6:P17) | ... W18: =SUM(W6:W17)
B20: New outlets opening 1 Oct–31 Dec | C20: =COUNTIFS(C6:C17,">="&'Q4 Assumptions'!$B$5,C6:C17,"<="&'Q4 Assumptions'!$B$6)
B21: Outlets operating at 31 Dec | C21: ='Q4 Assumptions'!$B$9+C20
